Workbook

Sheet Documents_PIA
B2: FIRST COMMUNITY COOPERTIVE DATA INVENTORY
G7: DATA LIFE CYCLE
A8: Doc Ref No. | B8: DOCUMENT/ FILE NAME | C8: DOCUMENT TYPE | D8: DOCUMENT OWNER | E8: BUSINESS PROCESS | F8: DOCUMENT PURPOSE | G8: CONSENT IN COLLECTION | H8: USE | I8: SHARING/ ACCESS BY | J8: STORAGE/REPOSITORY | K8: RETENTION PERIOD | L8: BASIS OF RETENTION | M8: DISPOSAL | N8: DOCUMENT OWNER
A9: DI-IA-01 | B9: Audit Work Program (AWP) & Data Extraction Log | C9: Both (Physical/ Electronic) | D9: Internal Audit | E9: Audit Fieldwork, Sampling, and Evidence Gathering | F9: To determine procedures to perform and explicitly log what PI/SPI was extracted during the audit. | G9: Absence of data privacy consent (Legitimate Interest / Statutory mandate) | H9: Information obtained to prepare audit report | I9: Not shared (Internal Audit only) | J9: Secure locked cabinet / Encrypted Drive | K9: E.g., 3 years after the final audit report is approved | L9: No established retention period | M9: Cross-cut shredding / Secure digital wipe | N9: Internal Audit
A10: DI-IA-02 | B10: Internal Audit DPA Addendum & Independence Declaration | C10: Physical Form | D10: Internal Audit | E10: Auditor Independence & QA Management | F10: To ensure auditor objectivity and enforce DPA confidentiality and data handling rules. | G10: Consent obtained (Signed declaration) | I10: Not shared (HR & IA only) | J10: 201 Employee File / Compliance Folder | K10: E.g., 5 years post-employment | M10: Cross-cut shredding
A11: DI-IA-03 | B11: Incident / Whistleblower Report | C11: Both | D11: Internal Audit | E11: Fraud Investigation and Whistleblower Handling | F11: To document allegations of fraud or misconduct for independent investigation. | G11: Consent obtained / Legitimate Interest | I11: Legal Dept, Board of Directors (BOD) | J11: Restricted IA Database / Vault | K11: E.g., 10 years or until legal case resolution | M11: Secure digital wipe / Cross-cut shredding
A12: DI-IA-04 | B12: Final Audit Report | C12: Both | D12: Internal Audit | E12: Audit Reporting and Issue Tracking | F12: To report sanitized findings and assign operational accountability to management/BOD. | G12: Absence of data privacy consent | I12: BOD, Audit Committee, Dept Heads | J12: Data Center / Central Vault | K12: E.g., 5-10 years (Standard Corporate Record) | M12: Secure digital wipe / Shredding
A13: DI-IA-05 | B13: Audit Data Disposal Certificate/Log | C13: Electronic | D13: Internal Audit | E13: Audit Fieldwork, Sampling, and Evidence Gathering | F13: To serve as verifiable proof that raw data/evidence was securely destroyed after an audit. | G13: N/A | I13: DPO (For compliance verification) | J13: Encrypted IA Drive | K13: Permanent (Compliance Record) | M13: N/A

Sheet Data Fields_PIA
B2: FIRST COMMUNITY COOPERTIVE DATA INVENTORY
A9: No. | B9: DATA FIELD | C9: DOCUMENT | D9: Doc Ref No. | E9: GENERIC DATA CLASSIFICATION | F9: DATA CLASSIFICATION | G9: DATA SUBJECT CATEGORY | H9: PURPOSE OF COLLECTION | I9: REMARKS | J9: DOCUMENT OWNER
A10: 1 | B10: Specific Data Extracted (e.g., Names, Loan Balances) | C10: AWP & Data Extraction Log | D10: DI-IA-01 | F10: Sensitive Personal Information | G10: Member / Employee | H10: To track exactly what sensitive data the auditor pulled for control testing. | J10: Internal Audit
A11: 2 | B11: Justification for Extraction | C11: AWP & Data Extraction Log | D11: DI-IA-01 | F11: Non-personal Information | G11: N/A | H11: To enforce the Principle of Proportionality (Data Minimization). | J11: Internal Audit
A12: =A11+1 -> 3 | B12: Name of Auditor | C12: IA DPA Addendum & Independence Declaration | D12: DI-IA-02 | F12: Personal Information | G12: Employee (Auditor) | H12: To identify the auditor bound by the NDA. | J12: Internal Audit / HR
A13: =A12+1 -> 4 | B13: Declared Conflicts of Interest (e.g., family ties, business interests) | C13: IA DPA Addendum & Independence Declaration | D13: DI-IA-02 | F13: Sensitive Personal Information | G13: Employee (Auditor) | H13: To fulfill regulatory requirements for audit objectivity and independence. | J13: Internal Audit
A14: =A13+1 -> 5 | B14: Name of Complainant / Whistleblower | C14: Incident / Whistleblower Report | D14: DI-IA-03 | F14: Personal Information | G14: Employee / Member | H14: To establish the source of the allegation (often kept strictly confidential). | J14: Internal Audit
A15: =A14+1 -> 6 | B15: Allegation Details (Potential Offenses) | C15: Incident / Whistleblower Report | D15: DI-IA-03 | F15: Sensitive Personal Information (Offense/Legal) | G15: Employee / Member | H15: To provide grounds for the fraud/misconduct investigation. | J15: Internal Audit
A16: =A15+1 -> 7 | B16: Accountable Officer Name | C16: Final Audit Report | D16: DI-IA-04 | F16: Personal Information | G16: Employee | H16: To assign operational accountability for audit findings. | J16: Internal Audit
A17: =A16+1 -> 8 | B17: Administrative Sanction/Penalty Recommended | C17: Final Audit Report | D17: DI-IA-04 | F17: Sensitive Personal Information | G17: Employee | H17: To recommend remediation and disciplinary action to the Board/HR. | J17: Internal Audit

Sheet Documents
G9: DATA LIFE CYCLE
A10: Doc Ref No. | B10: DOCUMENT/ FILE NAME | C10: DOCUMENT TYPE | D10: DOCUMENT OWNER | E10: BUSINESS PROCESS | F10: DOCUMENT PURPOSE | G10: CONSENT IN COLLECTION | H10: USE | I10: SHARING | J10: STORAGE/REPOSITORY | K10: RETENTION PERIOD | L10: BASIS OF RETENTION | M10: DISPOSAL
A11: DI-BO-01 | B11: Membership Information Sheet | C11: Physical Form | D11: Branch Operations | E11: New accounts Management | F11: To obtain membership data for various applications | G11: Absence of data privacy consent | H11: Information obtained used for background check of applicant and approval of membership | I11: Shared to legal only if necessary | J11: File cabinet, electronic copies are stored in local computer | K11: No established retention period | L11: No established retention period | M11: No disposal policy and procedure. Per practice, idle forms are either shredded or sold when office clutter becomes an impediment in operation, or is no longer needed.
A12: DI-BO-02 | B12: Client Master: Maintenance | C12: Electronic | D12: Branch Operations | E12: New accounts Management | F12: To profile and identify current and former members | G12: Absence of data privacy consent | H12: Information obtained used for identification and profiling of members | I12: Shared to EdCom for reporting | J12: Data Center | K12: No established retention period | L12: No established retention period | M12: No disposal policy and procedure.Data retained since 1991.
A13: DI-BO-03 | B13: Personal Record Card | C13: Physical Form | D13: Branch Operations | E13: New accounts Management | F13: To obtain personal data for application of membership | G13: Absence of data privacy consent | H13: Information obtained used for background check of applicant and approval of membership | I13: Shared to other departments | J13: File cabinet, electronic copies are stored in local computer | K13: No established retention period | L13: No established retention period | M13: No disposal policy and procedure. Per practice, idle forms are either shredded or sold when office clutter becomes an impediment in operation, or is no longer needed.
A14: DI-BO-04 | B14: Loan Application | C14: Physical Form | D14: Branch Operations | E14: Loans Processing | F14: To obtain membership and loan data for application of loan | G14: Absence of data privacy consent | H14: Information obtained used for background check of applicant and approval of loan | I14: Shared to legal only if necessary | J14: File cabinet, electronic copies are stored in local computer | K14: No established retention period | L14: No established retention period | M14: No disposal policy and procedure. Per practice, idle forms are either shredded or sold when office clutter becomes an impediment in operation, or is no longer needed.
A15: DI-BO-05 | B15: Promissory Note | C15: Physical Form | D15: Branch Operations | E15: Loans Processing | F15: To complete required data fields in completion of promissiory note | G15: Absence of data privacy consent | H15: Information obtained used for background check of applicant and approval of loan | I15: Shared to legal only if necessary | J15: File cabinet, electronic copies are stored in local computer | K15: No established retention period | L15: No established retention period | M15: No disposal policy and procedure. Per practice, idle forms are either shredded or sold when office clutter becomes an impediment in operation, or is no longer needed.
A16: DI-BO-06 | B16: Co-maker's Statement | C16: Physical Form | D16: Branch Operations | E16: Loans Processing | F16: To complete required data fields in completion of co-maker's statement | G16: Absence of data privacy consent | H16: Information obtained used for background check of applicant and approval of loan | I16: Shared to legal only if necessary | J16: File cabinet, electronic copies are stored in local computer | K16: No established retention period | L16: No established retention period | M16: No disposal policy and procedure. Per practice, idle forms are either shredded or sold when office clutter becomes an impediment in operation, or is no longer needed.
A17: DI-BO-07 | B17: Pre-hospitalization/Medical Loan Application | C17: Physical Form | D17: Branch Operations | E17: Loans Processing | F17: To obtain personal data and details for application of pre-hospitalization/medical loan | G17: Absence of data privacy consent | H17: Information obtained used for background check of applicant and approval of loan | I17: Shared to legal only if necessary | J17: File cabinet, electronic copies are stored in local computer | K17: No established retention period | L17: No established retention period | M17: No disposal policy and procedure. Per practice, idle forms are either shredded or sold when office clutter becomes an impediment in operation, or is no longer needed.
A18: DI-BO-08 | B18: Commodity Loan Application | C18: Physical Form | D18: Branch Operations | E18: Loans Processing | F18: To obtain membership data and details for application of commodity loan | G18: Absence of data privacy consent | H18: Information obtained used for background check of applicant and approval of loan | I18: Shared to legal only if necessary | J18: File cabinet, electronic copies are stored in local computer | K18: No established retention period | L18: No established retention period | M18: No disposal policy and procedure. Per practice, idle forms are either shredded or sold when office clutter becomes an impediment in operation, or is no longer needed.
A19: DI-BO-09 | B19: Petty Cash Loan Application | C19: Physical Form | D19: Branch Operations | E19: Loans Processing | F19: To obtain membership data for application of petty cash loan | G19: Absence of data privacy consent | H19: Information obtained used for background check of applicant and approval of loan | I19: Shared to legal only if necessary | J19: File cabinet, electronic copies are stored in local computer | K19: No established retention period | L19: No established retention period | M19: No disposal policy and procedure. Per practice, idle forms are either shredded or sold when office clutter becomes an impediment in operation, or is no longer needed.
A20: DI-BO-10 | B20: SM/Ororama/GC Gift Cheque Loan Application | C20: Physical Form | D20: Branch Operations | E20: Loans Processing | F20: To obtain membership data for application of GC Loan | G20: Absence of data privacy consent | H20: Information obtained used for background check of applicant and approval of loan | I20: Shared to legal only if necessary | J20: File cabinet, electronic copies are stored in local computer | K20: No established retention period | L20: No established retention period | M20: No disposal policy and procedure. Per practice, idle forms are either shredded or sold when office clutter becomes an impediment in operation, or is no longer needed.
A21: DI-BO-11 | B21: Rice Loan Application & Promissory Note | C21: Physical Form | D21: Branch Operations | E21: Loans Processing | F21: To obtain membership data for application of Rice Loan | G21: Absence of data privacy consent | H21: Information obtained used for background check of applicant and approval of loan | I21: Shared to legal only if necessary | J21: File cabinet, electronic copies are stored in local computer | K21: No established retention period | L21: No established retention period | M21: No disposal policy and procedure. Per practice, idle forms are either shredded or sold when office clutter becomes an impediment in operation, or is no longer needed.
... A101: DI-AM-01 | B101: Pre-Qualification Checklist | C101: Physical Form | D101: Asset Management | E101: Construction Management | F101: To determine bidders' qualifications | G101: Absence of data privacy consent | H101: Information obtained to ensure bidders are qualified for construction projects | I101: Not shared | J101: File cabinet | K101: No established retention period | L101: No established retention period | M101: No disposal policy and procedure. Per practice, idle forms are either shredded or sold when office clutter becomes an impediment in operation, or is no longer needed.

Sheet Data Fields
B9: No. | C9: DATA FIELD | D9: DOCUMENT | E9: Doc Ref No. | F9: GENERIC DATA CLASSIFICATION | G9: DATA CLASSIFICATION | H9: DATA SUBJECT CATEGORY | I9: PURPOSE OF COLLECTION | J9: REMARKS | K9: DOCUMENT OWNER
B10: 1 | C10: Name | D10: Membership Information Sheet | E10: DI-BO-01 | G10: Personal Information | H10: Member | I10: To determine the name of the borrower | K10: Branch Operations
B11: 2 | C11: Age | D11: Membership Information Sheet | E11: DI-BO-01 | G11: Sensitive Personal Information | H11: Member | I11: To determine the age of the borrower | K11: Branch Operations
B12: 3 | C12: Gender | D12: Membership Information Sheet | E12: DI-BO-01 | G12: Sensitive Personal Information | H12: Member | I12: To determine the gender of the borrower | K12: Branch Operations
B13: 4 | C13: Place of birth | D13: Membership Information Sheet | E13: DI-BO-01 | G13: Personal Information | H13: Member | I13: To determine the place of birth of the borrower | K13: Branch Operations
B14: 5 | C14: Date of birth | D14: Membership Information Sheet | E14: DI-BO-01 | G14: Personal Information | H14: Member | I14: To determine the date of birth of the borrower | K14: Branch Operations
B15: 6 | C15: Nationality | D15: Membership Information Sheet | E15: DI-BO-01 | G15: Sensitive Personal Information | H15: Member | I15: To determine the nationality of the borrower | K15: Branch Operations
B16: 7 | C16: Civil Status | D16: Membership Information Sheet | E16: DI-BO-01 | G16: Sensitive Personal Information | H16: Member | I16: To determine the civil status of the borrower | K16: Branch Operations
B17: 8 | C17: Blood Type | D17: Membership Information Sheet | E17: DI-BO-01 | G17: Sensitive Personal Information | H17: Member | I17: To determine the blood type of the borrower | K17: Branch Operations
B18: 9 | C18: Present Address | D18: Membership Information Sheet | E18: DI-BO-01 | G18: Personal Information | H18: Member | I18: To determine the present address of the borrower | K18: Branch Operations
B19: 10 | C19: # of years in this address | D19: Membership Information Sheet | E19: DI-BO-01 | G19: Sensitive Personal Information | H19: Member | I19: To determine the length of stay of the borrower in the present address | K19: Branch Operations
B20: 11 | C20: Previous Address | D20: Membership Information Sheet | E20: DI-BO-01 | G20: Personal Information | H20: Member | I20: To determine the previous address of the borrower | K20: Branch Operations
B21: 12 | C21: # of years in this address | D21: Membership Information Sheet | E21: DI-BO-01 | G21: Sensitive Personal Information | H21: Member | I21: To determine the length of stay of the borrower in the previous address | K21: Branch Operations
... B2390: 2381 | C2390: Total | D2390: Final Demand Letter | E2390: DI-LD-01 | G2390: Non-personal Information | H2390: Member | I2390: To demand collection from delinquent account | K2390: Legal Department
B2391: 2382 | C2391: Civil Case No. | D2391: Statement of Claim | E2391: DI-LD-02 | G2391: Sensitive Personal Information | H2391: Member | I2391: To fill out information for filing of case to RTC | J2391: RTC Form | K2391: Legal Department
B2392: 2383 | C2392: Name of Plantiff/s | D2392: Statement of Claim | E2392: DI-LD-02 | G2392: Personal Information | H2392: Member | I2392: To fill out information for filing of case to RTC | J2392: RTC Form | K2392: Legal Department
B2393: 2384 | C2393: Sex | D2393: Statement of Claim | E2393: DI-LD-02 | G2393: Personal Information | H2393: Member | I2393: To fill out information for filing of case to RTC | J2393: RTC Form | K2393: Legal Department
B2394: 2385 | C2394: Age | D2394: Statement of Claim | E2394: DI-LD-02 | G2394: Personal Information | H2394: Member | I2394: To fill out information for filing of case to RTC | J2394: RTC Form | K2394: Legal Department
B2395: 2386 | C2395: Civil Status | D2395: Statement of Claim | E2395: DI-LD-02 | G2395: Sensitive Personal Information | H2395: Member | I2395: To fill out information for filing of case to RTC | J2395: RTC Form | K2395: Legal Department
B2396: 2387 | C2396: Individual | D2396: Statement of Claim | E2396: DI-LD-02 | G2396: Personal Information | H2396: Member | I2396: To fill out information for filing of case to RTC | J2396: RTC Form | K2396: Legal Department
B2397: 2388 | C2397: Corporation | D2397: Statement of Claim | E2397: DI-LD-02 | G2397: Non-personal Information | H2397: Member | I2397: To fill out information for filing of case to RTC | J2397: RTC Form | K2397: Legal Department
B2398: 2389 | C2398: Partnership | D2398: Statement of Claim | E2398: DI-LD-02 | G2398: Non-personal Information | H2398: Member | I2398: To fill out information for filing of case to RTC | J2398: RTC Form | K2398: Legal Department
B2399: 2390 | C2399: Cooperative | D2399: Statement of Claim | E2399: DI-LD-02 | G2399: Non-personal Information | H2399: Member | I2399: To fill out information for filing of case to RTC | J2399: RTC Form | K2399: Legal Department
B2400: 2391 | C2400: Sole Proprietorship | D2400: Statement of Claim | E2400: DI-LD-02 | G2400: Non-personal Information | H2400: Member | I2400: To fill out information for filing of case to RTC | J2400: RTC Form | K2400: Legal Department
B2401: 2392 | C2401: Nature of Business | D2401: Statement of Claim | E2401: DI-LD-02 | G2401: Personal Information | H2401: Member | I2401: To fill out information for filing of case to RTC | J2401: RTC Form | K2401: Legal Department
B2402: 2393 | C2402: Plaintiff's Home Address City | D2402: Statement of Claim | E2402: DI-LD-02 | G2402: Personal Information | H2402: Member | I2402: To fill out information for filing of case to RTC | J2402: RTC Form | K2402: Legal Department
... B2463: 2454 | C2463: How many small claims cases have you filed within this calendar year prior to this present case, in this court station and in the entire country: | D2463: Statement of Claim | E2463: DI-LD-02 | G2463: Non-personal Information | H2463: Member | I2463: To fill out information for filing of case to RTC | J2463: RTC Form | K2463: Legal Department
B2464: 2455 | C2464: Borrowers: | D2464: Statement of Account | E2464: DI-LD-03 | G2464: Personal Information | H2464: Member | I2464: Required details for filing of case to RTC | K2464: Legal Department
B2465: 2456 | C2465: Type of Loan: | D2465: Statement of Account | E2465: DI-LD-03 | G2465: Sensitive Personal Information | H2465: Member | I2465: Required details for filing of case to RTC | K2465: Legal Department
B2466: 2457 | C2466: Principal Balance: | D2466: Statement of Account | E2466: DI-LD-03 | G2466: Non-personal Information | H2466: Member | I2466: Required details for filing of case to RTC | K2466: Legal Department
B2467: 2458 | C2467: Interest: | D2467: Statement of Account | E2467: DI-LD-03 | G2467: Non-personal Information | H2467: Member | I2467: Required details for filing of case to RTC | K2467: Legal Department
B2468: 2459 | C2468: Fines: | D2468: Statement of Account | E2468: DI-LD-03 | G2468: Non-personal Information | H2468: Member | I2468: Required details for filing of case to RTC | K2468: Legal Department
B2469: 2460 | C2469: Attorney's Fee | D2469: Statement of Account | E2469: DI-LD-03 | G2469: Non-personal Information | H2469: Member | I2469: Required details for filing of case to RTC | K2469: Legal Department
B2470: 2461 | C2470: Expenses | D2470: Statement of Account | E2470: DI-LD-03 | G2470: Non-personal Information | H2470: Member | I2470: Required details for filing of case to RTC | K2470: Legal Department
B2471: 2462 | C2471: Total Amount | D2471: Statement of Account | E2471: DI-LD-03 | G2471: Non-personal Information | H2471: Member | I2471: Required details for filing of case to RTC | K2471: Legal Department
B2472: 2463 | C2472: Computed by: Accountant | D2472: Statement of Account | E2472: DI-LD-03 | G2472: Sensitive Personal Information | H2472: Member | I2472: Required details for filing of case to RTC | K2472: Legal Department
B2473: 2464 | C2473: Date | D2473: Visitors' Logbook | E2473: DI-AD-01 | G2473: Personal Information | H2473: Visitors | I2473: To determine the date | K2473: Administrative department
B2474: 2465 | C2474: Time in | D2474: Visitors' Logbook | E2474: DI-AD-01 | G2474: Personal Information | H2474: Visitors | I2474: To determine the time in of the visitor | K2474: Administrative department
B2475: 2466 | C2475: Name | D2475: Visitors' Logbook | E2475: DI-AD-01 | G2475: Personal Information | H2475: Visitors | I2475: To determine the name of the visitor | K2475: Administrative department
... B2597: 2588 | C2597: Teller | D2597: Savings Deposit Passbook | E2597: DI-BO-28 | G2597: Sensitive Personal Information | H2597: Member | I2597: To determine the Teller of the transaction of member | K2597: Branch Operations
B2598: =B2597+1 -> 2589 | C2598: Date Conducted | D2598: Audit Work Program | E2598: DI-IA-01 | G2598: Non-personal Information | H2598: Employee | I2598: To determine date of performance of procedure | K2598: Internal Audit
B2599: =B2598+1 -> 2590 | C2599: FICCO Branch/Office | D2599: Audit Work Program | E2599: DI-IA-01 | G2599: Non-personal Information | H2599: Employee | I2599: To determine branch/office being audited | K2599: Internal Audit
B2600: =B2599+1 -> 2591 | C2600: Procedures | D2600: Audit Work Program | E2600: DI-IA-01 | G2600: Non-personal Information | H2600: Member/Employee/Vendor | I2600: To determine audit procedures to perform | K2600: Internal Audit
B2601: =B2600+1 -> 2592 | C2601: Findings | D2601: Audit Work Program | E2601: DI-IA-01 | G2601: Non-personal Information | H2601: Member/Employee/Vendor | I2601: To determine audit findings | K2601: Internal Audit
B2602: =B2601+1 -> 2593 | C2602: Name of Company/Bidder | D2602: Pre-Qualification Checklist | E2602: DI-AM-01 | G2602: Non-personal Information | H2602: Bidder | I2602: To determine if bidder is qualified to enter construction service | K2602: Asset Management
B2603: =B2602+1 -> 2594 | C2603: Business Trade Name and Principal business address | D2603: Pre-Qualification Checklist | E2603: DI-AM-01 | G2603: Non-personal Information | H2603: Bidder | I2603: To determine if bidder is qualified to enter construction service | K2603: Asset Management
B2604: =B2603+1 -> 2595 | C2604: Business permit | D2604: Pre-Qualification Checklist | E2604: DI-AM-01 | G2604: Non-personal Information | H2604: Bidder | I2604: To determine if bidder is qualified to enter construction service | K2604: Asset Management
B2605: =B2604+1 -> 2596 | C2605: SEC Registration/DTI | D2605: Pre-Qualification Checklist | E2605: DI-AM-01 | G2605: Non-personal Information | H2605: Bidder | I2605: To determine if bidder is qualified to enter construction service | K2605: Asset Management
B2606: =B2605+1 -> 2597 | C2606: Certificate of Registration from BIR | D2606: Pre-Qualification Checklist | E2606: DI-AM-01 | G2606: Non-personal Information | H2606: Bidder | I2606: To determine if bidder is qualified to enter construction service | K2606: Asset Management
B2607: =B2606+1 -> 2598 | C2607: Audited Financial Statement for the past 2 years | D2607: Pre-Qualification Checklist | E2607: DI-AM-01 | G2607: Non-personal Information | H2607: Bidder | I2607: To determine if bidder is qualified to enter construction service | K2607: Asset Management
B2608: =B2607+1 -> 2599 | C2608: List of Manpower (Schedule of Manpower) -to include project management team e.g. Civil Engineer, Electrical Engineer, Safety Engineer and foreman. | D2608: Pre-Qualification Checklist | E2608: DI-AM-01 | G2608: Non-personal Information | H2608: Bidder | I2608: To determine if bidder is qualified to enter construction service | K2608: Asset Management
B2609: =B2608+1 -> 2600 | C2609: List of Equipment needed related to FICCO Project | D2609: Pre-Qualification Checklist | E2609: DI-AM-01 | G2609: Non-personal Information | H2609: Bidder | I2609: To determine if bidder is qualified to enter construction service | K2609: Asset Management
... B2611: =B2610+1 -> 2602 | C2611: Safety officer - Certificate from DOLE | D2611: Pre-Qualification Checklist | E2611: DI-AM-01 | G2611: Non-personal Information | H2611: Bidder | I2611: To determine if bidder is qualified to enter construction service | K2611: Asset Management
B2612: =B2611+1 -> 2603
B2613: =B2612+1 -> 2604
B2614: =B2613+1 -> 2605

Sheet Branch Operations
B9: No. | C9: DATA FIELD | D9: DOCUMENT | E9: Doc Ref No. | F9: GENERIC DATA CLASSIFICATION | G9: DATA CLASSIFICATION | H9: DATA SUBJECT CATEGORY | I9: PURPOSE OF COLLECTION | J9: REMARKS | K9: DOCUMENT OWNER
B10: 1 | C10: =IFERROR(INDEX('Data Fields'!$B:$K,MATCH($B10,'Data Fields'!$B:$B,0),MATCH(B$9,'Data Fields'!$9:$9,0)),0) -> Name | D10: =IFERROR(INDEX('Data Fields'!$B:$K,MATCH($B10,'Data Fields'!$B:$B,0),MATCH(C$9,'Data Fields'!$9:$9,0)),0) -> Membership Information Sheet | E10: =IFERROR(INDEX('Data Fields'!$B:$K,MATCH($B10,'Data Fields'!$B:$B,0),MATCH(D$9,'Data Fields'!$9:$9,0)),0) -> DI-BO-01 | F10: =IFERROR(INDEX('Data Fields'!$B:$K,MATCH($B10,'Data Fields'!$B:$B,0),MATCH(E$9,'Data Fields'!$9:$9,0)),0) -> 0 | G10: =IFERROR(INDEX('Data Fields'!$B:$K,MATCH($B10,'Data Fields'!$B:$B,0),MATCH(F$9,'Data Fields'!$9:$9,0)),0) -> Personal Information | H10: =IFERROR(INDEX('Data Fields'!$B:$K,MATCH($B10,'Data Fields'!$B:$B,0),MATCH(G$9,'Data Fields'!$9:$9,0)),0) -> Member | I10: =IFERROR(INDEX('Data Fields'!$B:$K,MATCH($B10,'Data Fields'!$B:$B,0),MATCH(H$9,'Data Fields'!$9:$9,0)),0) -> To determine the name of the borrower | J10: =IFERROR(INDEX('Data Fields'!$B:$K,MATCH($B10,'Data Fields'!$B:$B,0),MATCH(I$9,'Data Fields'!$9:$9,0)),0) -> 0 | K10: =IFERROR(INDEX('Data Fields'!$B:$K,MATCH($B10,'Data Fields'!$B:$B,0),MATCH(J$9,'Data Fields'!$9:$9,0)),0) -> Branch Operations
B11: 2 | C11: =IFERROR(INDEX('Data Fields'!$B:$K,MATCH($B11,'Data Fields'!$B:$B,0),MATCH(B$9,'Data Fields'!$9:$9,0)),0) -> Age | D11: =IFERROR(INDEX('Data Fields'!$B:$K,MATCH($B11,'Data Fields'!$B:$B,0),MATCH(C$9,'Data Fields'!$9:$9,0)),0) -> Membership Information Sheet | E11: =IFERROR(INDEX('Data Fields'!$B:$K,MATCH($B11,'Data Fields'!$B:$B,0),MATCH(D$9,'Data Fields'!$9:$9,0)),0) -> DI-BO-01 | F11: =IFERROR(INDEX('Data Fields'!$B:$K,MATCH($B11,'Data Fields'!$B:$B,0),MATCH(E$9,'Data Fields'!$9:$9,0)),0) -> 0 | G11: =IFERROR(INDEX('Data Fields'!$B:$K,MATCH($B11,'Data Fields'!$B:$B,0),MATCH(F$9,'Data Fields'!$9:$9,0)),0) -> Sensitive Personal Information | H11: =IFERROR(INDEX('Data Fields'!$B:$K,MATCH($B11,'Data Fields'!$B:$B,0),MATCH(G$9,'Data Fields'!$9:$9,0)),0) -> Member | I11: =IFERROR(INDEX('Data Fields'!$B:$K,MATCH($B11,'Data Fields'!$B:$B,0),MATCH(H$9,'Data Fields'!$9:$9,0)),0) -> To determine the age of the borrower | J11: =IFERROR(INDEX('Data Fields'!$B:$K,MATCH($B11,'Data Fields'!$B:$B,0),MATCH(I$9,'Data Fields'!$9:$9,0)),0) -> 0 | K11: =IFERROR(INDEX('Data Fields'!$B:$K,MATCH($B11,'Data Fields'!$B:$B,0),MATCH(J$9,'Data Fields'!$9:$9,0)),0) -> Branch Operations
B12: 3 | C12: =IFERROR(INDEX('Data Fields'!$B:$K,MATCH($B12,'Data Fields'!$B:$B,0),MATCH(B$9,'Data Fields'!$9:$9,0)),0) -> Gender | D12: =IFERROR(INDEX('Data Fields'!$B:$K,MATCH($B12,'Data Fields'!$B:$B,0),MATCH(C$9,'Data Fields'!$9:$9,0)),0) -> Membership Information Sheet | E12: =IFERROR(INDEX('Data Fields'!$B:$K,MATCH($B12,'Data Fields'!$B:$B,0),MATCH(D$9,'Data Fields'!$9:$9,0)),0) -> DI-BO-01 | F12: =IFERROR(INDEX('Data Fields'!$B:$K,MATCH($B12,'Data Fields'!$B:$B,0),MATCH(E$9,'Data Fields'!$9:$9,0)),0) -> 0 | G12: =IFERROR(INDEX('Data Fields'!$B:$K,MATCH($B12,'Data Fields'!$B:$B,0),MATCH(F$9,'Data Fields'!$9:$9,0)),0) -> Sensitive Personal Information | H12: =IFERROR(INDEX('Data Fields'!$B:$K,MATCH($B12,'Data Fields'!$B:$B,0),MATCH(G$9,'Data Fields'!$9:$9,0)),0) -> Member | I12: =IFERROR(INDEX('Data Fields'!$B:$K,MATCH($B12,'Data Fields'!$B:$B,0),MATCH(H$9,'Data Fields'!$9:$9,0)),0) -> To determine the gender of the borrower | J12: =IFERROR(INDEX('Data Fields'!$B:$K,MATCH($B12,'Data Fields'!$B:$B,0),MATCH(I$9,'Data Fields'!$9:$9,0)),0) -> 0 | K12: =IFERROR(INDEX('Data Fields'!$B:$K,MATCH($B12,'Data Fields'!$B:$B,0),MATCH(J$9,'Data Fields'!$9:$9,0)),0) -> Branch Operations
B13: 4 | C13: =IFERROR(INDEX('Data Fields'!$B:$K,MATCH($B13,'Data Fields'!$B:$B,0),MATCH(B$9,'Data Fields'!$9:$9,0)),0) -> Place of birth | D13: =IFERROR(INDEX('Data Fields'!$B:$K,MATCH($B13,'Data Fields'!$B:$B,0),MATCH(C$9,'Data Fields'!$9:$9,0)),0) -> Membership Information Sheet | E13: =IFERROR(INDEX('Data Fields'!$B:$K,MATCH($B13,'Data Fields'!$B:$B,0),MATCH(D$9,'Data Fields'!$9:$9,0)),0) -> DI-BO-01 | F13: =IFERROR(INDEX('Data Fields'!$B:$K,MATCH($B13,'Data Fields'!$B:$B,0),MATCH(E$9,'Data Fields'!$9:$9,0)),0) -> 0 | G13: =IFERROR(INDEX('Data Fields'!$B:$K,MATCH($B13,'Data Fields'!$B:$B,0),MATCH(F$9,'Data Fields'!$9:$9,0)),0) -> Personal Information | H13: =IFERROR(INDEX('Data Fields'!$B:$K,MATCH($B13,'Data Fields'!$B:$B,0),MATCH(G$9,'Data Fields'!$9:$9,0)),0) -> Member | I13: =IFERROR(INDEX('Data Fields'!$B:$K,MATCH($B13,'Data Fields'!$B:$B,0),MATCH(H$9,'Data Fields'!$9:$9,0)),0) -> To determine the place of birth of the borrower | J13: =IFERROR(INDEX('Data Fields'!$B:$K,MATCH($B13,'Data Fields'!$B:$B,0),MATCH(I$9,'Data Fields'!$9:$9,0)),0) -> 0 | K13: =IFERROR(INDEX('Data Fields'!$B:$K,MATCH($B13,'Data Fields'!$B:$B,0),MATCH(J$9,'Data Fields'!$9:$9,0)),0) -> Branch Operations
B14: 5 | C14: =IFERROR(INDEX('Data Fields'!$B:$K,MATCH($B14,'Data Fields'!$B:$B,0),MATCH(B$9,'Data Fields'!$9:$9,0)),0) -> Date of birth | D14: =IFERROR(INDEX('Data Fields'!$B:$K,MATCH($B14,'Data Fields'!$B:$B,0),MATCH(C$9,'Data Fields'!$9:$9,0)),0) -> Membership Information Sheet | E14: =IFERROR(INDEX('Data Fields'!$B:$K,MATCH($B14,'Data Fields'!$B:$B,0),MATCH(D$9,'Data Fields'!$9:$9,0)),0) -> DI-BO-01 | F14: =IFERROR(INDEX('Data Fields'!$B:$K,MATCH($B14,'Data Fields'!$B:$B,0),MATCH(E$9,'Data Fields'!$9:$9,0)),0) -> 0 | G14: =IFERROR(INDEX('Data Fields'!$B:$K,MATCH($B14,'Data Fields'!$B:$B,0),MATCH(F$9,'Data Fields'!$9:$9,0)),0) -> Personal Information | H14: =IFERROR(INDEX('Data Fields'!$B:$K,MATCH($B14,'Data Fields'!$B:$B,0),MATCH(G$9,'Data Fields'!$9:$9,0)),0) -> Member | I14: =IFERROR(INDEX('Data Fields'!$B:$K,MATCH($B14,'Data Fields'!$B:$B,0),MATCH(H$9,'Data Fields'!$9:$9,0)),0) -> To determine the date of birth of the borrower | J14: =IFERROR(INDEX('Data Fields'!$B:$K,MATCH($B14,'Data Fields'!$B:$B,0),MATCH(I$9,'Data Fields'!$9:$9,0)),0) -> 0 | K14: =IFERROR(INDEX('Data Fields'!$B:$K,MATCH($B14,'Data Fields'!$B:$B,0),MATCH(J$9,'Data Fields'!$9:$9,0)),0) -> Branch Operations
B15: 6 | C15: =IFERROR(INDEX('Data Fields'!$B:$K,MATCH($B15,'Data Fields'!$B:$B,0),MATCH(B$9,'Data Fields'!$9:$9,0)),0) -> Nationality | D15: =IFERROR(INDEX('Data Fields'!$B:$K,MATCH($B15,'Data Fields'!$B:$B,0),MATCH(C$9,'Data Fields'!$9:$9,0)),0) -> Membership Information Sheet | E15: =IFERROR(INDEX('Data Fields'!$B:$K,MATCH($B15,'Data Fields'!$B:$B,0),MATCH(D$9,'Data Fields'!$9:$9,0)),0) -> DI-BO-01 | F15: =IFERROR(INDEX('Data Fields'!$B:$K,MATCH($B15,'Data Fields'!$B:$B,0),MATCH(E$9,'Data Fields'!$9:$9,0)),0) -> 0 | G15: =IFERROR(INDEX('Data Fields'!$B:$K,MATCH($B15,'Data Fields'!$B:$B,0),MATCH(F$9,'Data Fields'!$9:$9,0)),0) -> Sensitive Personal Information | H15: =IFERROR(INDEX('Data Fields'!$B:$K,MATCH($B15,'Data Fields'!$B:$B,0),MATCH(G$9,'Data Fields'!$9:$9,0)),0) -> Member | I15: =IFERROR(INDEX('Data Fields'!$B:$K,MATCH($B15,'Data Fields'!$B:$B,0),MATCH(H$9,'Data Fields'!$9:$9,0)),0) -> To determine the nationality of the borrower | J15: =IFERROR(INDEX('Data Fields'!$B:$K,MATCH($B15,'Data Fields'!$B:$B,0),MATCH(I$9,'Data Fields'!$9:$9,0)),0) -> 0 | K15: =IFERROR(INDEX('Data Fields'!$B:$K,MATCH($B15,'Data Fields'!$B:$B,0),MATCH(J$9,'Data Fields'!$9:$9,0)),0) -> Branch Operations
B16: 7 | C16: =IFERROR(INDEX('Data Fields'!$B:$K,MATCH($B16,'Data Fields'!$B:$B,0),MATCH(B$9,'Data Fields'!$9:$9,0)),0) -> Civil Status | D16: =IFERROR(INDEX('Data Fields'!$B:$K,MATCH($B16,'Data Fields'!$B:$B,0),MATCH(C$9,'Data Fields'!$9:$9,0)),0) -> Membership Information Sheet | E16: =IFERROR(INDEX('Data Fields'!$B:$K,MATCH($B16,'Data Fields'!$B:$B,0),MATCH(D$9,'Data Fields'!$9:$9,0)),0) -> DI-BO-01 | F16: =IFERROR(INDEX('Data Fields'!$B:$K,MATCH($B16,'Data Fields'!$B:$B,0),MATCH(E$9,'Data Fields'!$9:$9,0)),0) -> 0 | G16: =IFERROR(INDEX('Data Fields'!$B:$K,MATCH($B16,'Data Fields'!$B:$B,0),MATCH(F$9,'Data Fields'!$9:$9,0)),0) -> Sensitive Personal Information | H16: =IFERROR(INDEX('Data Fields'!$B:$K,MATCH($B16,'Data Fields'!$B:$B,0),MATCH(G$9,'Data Fields'!$9:$9,0)),0) -> Member | I16: =IFERROR(INDEX('Data Fields'!$B:$K,MATCH($B16,'Data Fields'!$B:$B,0),MATCH(H$9,'Data Fields'!$9:$9,0)),0) -> To determine the civil status of the borrower | J16: =IFERROR(INDEX('Data Fields'!$B:$K,MATCH($B16,'Data Fields'!$B:$B,0),MATCH(I$9,'Data Fields'!$9:$9,0)),0) -> 0 | K16: =IFERROR(INDEX('Data Fields'!$B:$K,MATCH($B16,'Data Fields'!$B:$B,0),MATCH(J$9,'Data Fields'!$9:$9,0)),0) -> Branch Operations
B17: 8 | C17: =IFERROR(INDEX('Data Fields'!$B:$K,MATCH($B17,'Data Fields'!$B:$B,0),MATCH(B$9,'Data Fields'!$9:$9,0)),0) -> Blood Type | D17: =IFERROR(INDEX('Data Fields'!$B:$K,MATCH($B17,'Data Fields'!$B:$B,0),MATCH(C$9,'Data Fields'!$9:$9,0)),0) -> Membership Information Sheet | E17: =IFERROR(INDEX('Data Fields'!$B:$K,MATCH($B17,'Data Fields'!$B:$B,0),MATCH(D$9,'Data Fields'!$9:$9,0)),0) -> DI-BO-01 | F17: =IFERROR(INDEX('Data Fields'!$B:$K,MATCH($B17,'Data Fields'!$B:$B,0),MATCH(E$9,'Data Fields'!$9:$9,0)),0) -> 0 | G17: =IFERROR(INDEX('Data Fields'!$B:$K,MATCH($B17,'Data Fields'!$B:$B,0),MATCH(F$9,'Data Fields'!$9:$9,0)),0) -> Sensitive Personal Information | H17: =IFERROR(INDEX('Data Fields'!$B:$K,MATCH($B17,'Data Fields'!$B:$B,0),MATCH(G$9,'Data Fields'!$9:$9,0)),0) -> Member | I17: =IFERROR(INDEX('Data Fields'!$B:$K,MATCH($B17,'Data Fields'!$B:$B,0),MATCH(H$9,'Data Fields'!$9:$9,0)),0) -> To determine the blood type of the borrower | J17: =IFERROR(INDEX('Data Fields'!$B:$K,MATCH($B17,'Data Fields'!$B:$B,0),MATCH(I$9,'Data Fields'!$9:$9,0)),0) -> 0 | K17: =IFERROR(INDEX('Data Fields'!$B:$K,MATCH($B17,'Data Fields'!$B:$B,0),MATCH(J$9,'Data Fields'!$9:$9,0)),0) -> Branch Operations
B18: 9 | C18: =IFERROR(INDEX('Data Fields'!$B:$K,MATCH($B18,'Data Fields'!$B:$B,0),MATCH(B$9,'Data Fields'!$9:$9,0)),0) -> Present Address | D18: =IFERROR(INDEX('Data Fields'!$B:$K,MATCH($B18,'Data Fields'!$B:$B,0),MATCH(C$9,'Data Fields'!$9:$9,0)),0) -> Membership Information Sheet | E18: =IFERROR(INDEX('Data Fields'!$B:$K,MATCH($B18,'Data Fields'!$B:$B,0),MATCH(D$9,'Data Fields'!$9:$9,0)),0) -> DI-BO-01 | F18: =IFERROR(INDEX('Data Fields'!$B:$K,MATCH($B18,'Data Fields'!$B:$B,0),MATCH(E$9,'Data Fields'!$9:$9,0)),0) -> 0 | G18: =IFERROR(INDEX('Data Fields'!$B:$K,MATCH($B18,'Data Fields'!$B:$B,0),MATCH(F$9,'Data Fields'!$9:$9,0)),0) -> Personal Information | H18: =IFERROR(INDEX('Data Fields'!$B:$K,MATCH($B18,'Data Fields'!$B:$B,0),MATCH(G$9,'Data Fields'!$9:$9,0)),0) -> Member | I18: =IFERROR(INDEX('Data Fields'!$B:$K,MATCH($B18,'Data Fields'!$B:$B,0),MATCH(H$9,'Data Fields'!$9:$9,0)),0) -> To determine the present address of the borrower | J18: =IFERROR(INDEX('Data Fields'!$B:$K,MATCH($B18,'Data Fields'!$B:$B,0),MATCH(I$9,'Data Fields'!$9:$9,0)),0) -> 0 | K18: =IFERROR(INDEX('Data Fields'!$B:$K,MATCH($B18,'Data Fields'!$B:$B,0),MATCH(J$9,'Data Fields'!$9:$9,0)),0) -> Branch Operations
B19: 10 | C19: =IFERROR(INDEX('Data Fields'!$B:$K,MATCH($B19,'Data Fields'!$B:$B,0),MATCH(B$9,'Data Fields'!$9:$9,0)),0) -> # of years in this address | D19: =IFERROR(INDEX('Data Fields'!$B:$K,MATCH($B19,'Data Fields'!$B:$B,0),MATCH(C$9,'Data Fields'!$9:$9,0)),0) -> Membership Information Sheet | E19: =IFERROR(INDEX('Data Fields'!$B:$K,MATCH($B19,'Data Fields'!$B:$B,0),MATCH(D$9,'Data Fields'!$9:$9,0)),0) -> DI-BO-01 | F19: =IFERROR(INDEX('Data Fields'!$B:$K,MATCH($B19,'Data Fields'!$B:$B,0),MATCH(E$9,'Data Fields'!$9:$9,0)),0) -> 0 | G19: =IFERROR(INDEX('Data Fields'!$B:$K,MATCH($B19,'Data Fields'!$B:$B,0),MATCH(F$9,'Data Fields'!$9:$9,0)),0) -> Sensitive Personal Information | H19: =IFERROR(INDEX('Data Fields'!$B:$K,MATCH($B19,'Data Fields'!$B:$B,0),MATCH(G$9,'Data Fields'!$9:$9,0)),0) -> Member | I19: =IFERROR(INDEX('Data Fields'!$B:$K,MATCH($B19,'Data Fields'!$B:$B,0),MATCH(H$9,'Data Fields'!$9:$9,0)),0) -> To determine the length of stay of the borrower in the present address | J19: =IFERROR(INDEX('Data Fields'!$B:$K,MATCH($B19,'Data Fields'!$B:$B,0),MATCH(I$9,'Data Fields'!$9:$9,0)),0) -> 0 | K19: =IFERROR(INDEX('Data Fields'!$B:$K,MATCH($B19,'Data Fields'!$B:$B,0),MATCH(J$9,'Data Fields'!$9:$9,0)),0) -> Branch Operations
B20: 11 | C20: =IFERROR(INDEX('Data Fields'!$B:$K,MATCH($B20,'Data Fields'!$B:$B,0),MATCH(B$9,'Data Fields'!$9:$9,0)),0) -> Previous Address | D20: =IFERROR(INDEX('Data Fields'!$B:$K,MATCH($B20,'Data Fields'!$B:$B,0),MATCH(C$9,'Data Fields'!$9:$9,0)),0) -> Membership Information Sheet | E20: =IFERROR(INDEX('Data Fields'!$B:$K,MATCH($B20,'Data Fields'!$B:$B,0),MATCH(D$9,'Data Fields'!$9:$9,0)),0) -> DI-BO-01 | F20: =IFERROR(INDEX('Data Fields'!$B:$K,MATCH($B20,'Data Fields'!$B:$B,0),MATCH(E$9,'Data Fields'!$9:$9,0)),0) -> 0 | G20: =IFERROR(INDEX('Data Fields'!$B:$K,MATCH($B20,'Data Fields'!$B:$B,0),MATCH(F$9,'Data Fields'!$9:$9,0)),0) -> Personal Information | H20: =IFERROR(INDEX('Data Fields'!$B:$K,MATCH($B20,'Data Fields'!$B:$B,0),MATCH(G$9,'Data Fields'!$9:$9,0)),0) -> Member | I20: =IFERROR(INDEX('Data Fields'!$B:$K,MATCH($B20,'Data Fields'!$B:$B,0),MATCH(H$9,'Data Fields'!$9:$9,0)),0) -> To determine the previous address of the borrower | J20: =IFERROR(INDEX('Data Fields'!$B:$K,MATCH($B20,'Data Fields'!$B:$B,0),MATCH(I$9,'Data Fields'!$9:$9,0)),0) -> 0 | K20: =IFERROR(INDEX('Data Fields'!$B:$K,MATCH($B20,'Data Fields'!$B:$B,0),MATCH(J$9,'Data Fields'!$9:$9,0)),0) -> Branch Operations
B21: 12 | C21: =IFERROR(INDEX('Data Fields'!$B:$K,MATCH($B21,'Data Fields'!$B:$B,0),MATCH(B$9,'Data Fields'!$9:$9,0)),0) -> # of years in this address | D21: =IFERROR(INDEX('Data Fields'!$B:$K,MATCH($B21,'Data Fields'!$B:$B,0),MATCH(C$9,'Data Fields'!$9:$9,0)),0) -> Membership Information Sheet | E21: =IFERROR(INDEX('Data Fields'!$B:$K,MATCH($B21,'Data Fields'!$B:$B,0),MATCH(D$9,'Data Fields'!$9:$9,0)),0) -> DI-BO-01 | F21: =IFERROR(INDEX('Data Fields'!$B:$K,MATCH($B21,'Data Fields'!$B:$B,0),MATCH(E$9,'Data Fields'!$9:$9,0)),0) -> 0 | G21: =IFERROR(INDEX('Data Fields'!$B:$K,MATCH($B21,'Data Fields'!$B:$B,0),MATCH(F$9,'Data Fields'!$9:$9,0)),0) -> Sensitive Personal Information | H21: =IFERROR(INDEX('Data Fields'!$B:$K,MATCH($B21,'Data Fields'!$B:$B,0),MATCH(G$9,'Data Fields'!$9:$9,0)),0) -> Member | I21: =IFERROR(INDEX('Data Fields'!$B:$K,MATCH($B21,'Data Fields'!$B:$B,0),MATCH(H$9,'Data Fields'!$9:$9,0)),0) -> To determine the length of stay of the borrower in the previous address | J21: =IFERROR(INDEX('Data Fields'!$B:$K,MATCH($B21,'Data Fields'!$B:$B,0),MATCH(I$9,'Data Fields'!$9:$9,0)),0) -> 0 | K21: =IFERROR(INDEX('Data Fields'!$B:$K,MATCH($B21,'Data Fields'!$B:$B,0),MATCH(J$9,'Data Fields'!$9:$9,0)),0) -> Branch Operations
... B926: 2517 | C926: =IFERROR(INDEX('Data Fields'!$B:$K,MATCH($B926,'Data Fields'!$B:$B,0),MATCH(B$9,'Data Fields'!$9:$9,0)),0) -> Interviewed by | D926: =IFERROR(INDEX('Data Fields'!$B:$K,MATCH($B926,'Data Fields'!$B:$B,0),MATCH(C$9,'Data Fields'!$9:$9,0)),0) -> Credit Committee slip | E926: =IFERROR(INDEX('Data Fields'!$B:$K,MATCH($B926,'Data Fields'!$B:$B,0),MATCH(D$9,'Data Fields'!$9:$9,0)),0) -> DI-BO-22 | F926: =IFERROR(INDEX('Data Fields'!$B:$K,MATCH($B926,'Data Fields'!$B:$B,0),MATCH(E$9,'Data Fields'!$9:$9,0)),0) -> 0 | G926: =IFERROR(INDEX('Data Fields'!$B:$K,MATCH($B926,'Data Fields'!$B:$B,0),MATCH(F$9,'Data Fields'!$9:$9,0)),0) -> Sensitive Personal Information | H926: =IFERROR(INDEX('Data Fields'!$B:$K,MATCH($B926,'Data Fields'!$B:$B,0),MATCH(G$9,'Data Fields'!$9:$9,0)),0) -> Member | I926: =IFERROR(INDEX('Data Fields'!$B:$K,MATCH($B926,'Data Fields'!$B:$B,0),MATCH(H$9,'Data Fields'!$9:$9,0)),0) -> To determine who interviewed the borrower | J926: =IFERROR(INDEX('Data Fields'!$B:$K,MATCH($B926,'Data Fields'!$B:$B,0),MATCH(I$9,'Data Fields'!$9:$9,0)),0) -> 0 | K926: =IFERROR(INDEX('Data Fields'!$B:$K,MATCH($B926,'Data Fields'!$B:$B,0),MATCH(J$9,'Data Fields'!$9:$9,0)),0) -> Branch Operations

Sheet EdCom
B9: No. | C9: DATA FIELD | D9: DOCUMENT | E9: Doc Ref No. | F9: GENERIC DATA CLASSIFICATION | G9: DATA CLASSIFICATION | H9: DATA SUBJECT CATEGORY | I9: PURPOSE OF COLLECTION | J9: REMARKS | K9: DOCUMENT OWNER
B10: 891 | C10: =IFERROR(INDEX('Data Fields'!$B:$K,MATCH($B10,'Data Fields'!$B:$B,0),MATCH(B$9,'Data Fields'!$9:$9,0)),0) -> Name | D10: =IFERROR(INDEX('Data Fields'!$B:$K,MATCH($B10,'Data Fields'!$B:$B,0),MATCH(C$9,'Data Fields'!$9:$9,0)),0) -> PMS Attendance Sheet | E10: =IFERROR(INDEX('Data Fields'!$B:$K,MATCH($B10,'Data Fields'!$B:$B,0),MATCH(D$9,'Data Fields'!$9:$9,0)),0) -> DI-ED-01 | F10: =IFERROR(INDEX('Data Fields'!$B:$K,MATCH($B10,'Data Fields'!$B:$B,0),MATCH(E$9,'Data Fields'!$9:$9,0)),0) -> 0 | G10: =IFERROR(INDEX('Data Fields'!$B:$K,MATCH($B10,'Data Fields'!$B:$B,0),MATCH(F$9,'Data Fields'!$9:$9,0)),0) -> Personal Information | H10: =IFERROR(INDEX('Data Fields'!$B:$K,MATCH($B10,'Data Fields'!$B:$B,0),MATCH(G$9,'Data Fields'!$9:$9,0)),0) -> Member | I10: =IFERROR(INDEX('Data Fields'!$B:$K,MATCH($B10,'Data Fields'!$B:$B,0),MATCH(H$9,'Data Fields'!$9:$9,0)),0) -> To identify attendee | J10: =IFERROR(INDEX('Data Fields'!$B:$K,MATCH($B10,'Data Fields'!$B:$B,0),MATCH(I$9,'Data Fields'!$9:$9,0)),0) -> 0 | K10: =IFERROR(INDEX('Data Fields'!$B:$K,MATCH($B10,'Data Fields'!$B:$B,0),MATCH(J$9,'Data Fields'!$9:$9,0)),0) -> Education and Training Committee
B11: 892 | C11: =IFERROR(INDEX('Data Fields'!$B:$K,MATCH($B11,'Data Fields'!$B:$B,0),MATCH(B$9,'Data Fields'!$9:$9,0)),0) -> Address | D11: =IFERROR(INDEX('Data Fields'!$B:$K,MATCH($B11,'Data Fields'!$B:$B,0),MATCH(C$9,'Data Fields'!$9:$9,0)),0) -> PMS Attendance Sheet | E11: =IFERROR(INDEX('Data Fields'!$B:$K,MATCH($B11,'Data Fields'!$B:$B,0),MATCH(D$9,'Data Fields'!$9:$9,0)),0) -> DI-ED-01 | F11: =IFERROR(INDEX('Data Fields'!$B:$K,MATCH($B11,'Data Fields'!$B:$B,0),MATCH(E$9,'Data Fields'!$9:$9,0)),0) -> 0 | G11: =IFERROR(INDEX('Data Fields'!$B:$K,MATCH($B11,'Data Fields'!$B:$B,0),MATCH(F$9,'Data Fields'!$9:$9,0)),0) -> Personal Information | H11: =IFERROR(INDEX('Data Fields'!$B:$K,MATCH($B11,'Data Fields'!$B:$B,0),MATCH(G$9,'Data Fields'!$9:$9,0)),0) -> Member | I11: =IFERROR(INDEX('Data Fields'!$B:$K,MATCH($B11,'Data Fields'!$B:$B,0),MATCH(H$9,'Data Fields'!$9:$9,0)),0) -> To identify attendee | J11: =IFERROR(INDEX('Data Fields'!$B:$K,MATCH($B11,'Data Fields'!$B:$B,0),MATCH(I$9,'Data Fields'!$9:$9,0)),0) -> 0 | K11: =IFERROR(INDEX('Data Fields'!$B:$K,MATCH($B11,'Data Fields'!$B:$B,0),MATCH(J$9,'Data Fields'!$9:$9,0)),0) -> Education and Training Committee
B12: 893 | C12: =IFERROR(INDEX('Data Fields'!$B:$K,MATCH($B12,'Data Fields'!$B:$B,0),MATCH(B$9,'Data Fields'!$9:$9,0)),0) -> Age (Immediate Family Member) | D12: =IFERROR(INDEX('Data Fields'!$B:$K,MATCH($B12,'Data Fields'!$B:$B,0),MATCH(C$9,'Data Fields'!$9:$9,0)),0) -> PMS Attendance Sheet | E12: =IFERROR(INDEX('Data Fields'!$B:$K,MATCH($B12,'Data Fields'!$B:$B,0),MATCH(D$9,'Data Fields'!$9:$9,0)),0) -> DI-ED-01 | F12: =IFERROR(INDEX('Data Fields'!$B:$K,MATCH($B12,'Data Fields'!$B:$B,0),MATCH(E$9,'Data Fields'!$9:$9,0)),0) -> 0 | G12: =IFERROR(INDEX('Data Fields'!$B:$K,MATCH($B12,'Data Fields'!$B:$B,0),MATCH(F$9,'Data Fields'!$9:$9,0)),0) -> Personal Information | H12: =IFERROR(INDEX('Data Fields'!$B:$K,MATCH($B12,'Data Fields'!$B:$B,0),MATCH(G$9,'Data Fields'!$9:$9,0)),0) -> Member | I12: =IFERROR(INDEX('Data Fields'!$B:$K,MATCH($B12,'Data Fields'!$B:$B,0),MATCH(H$9,'Data Fields'!$9:$9,0)),0) -> To identify attendee | J12: =IFERROR(INDEX('Data Fields'!$B:$K,MATCH($B12,'Data Fields'!$B:$B,0),MATCH(I$9,'Data Fields'!$9:$9,0)),0) -> 0 | K12: =IFERROR(INDEX('Data Fields'!$B:$K,MATCH($B12,'Data Fields'!$B:$B,0),MATCH(J$9,'Data Fields'!$9:$9,0)),0) -> Education and Training Committee
B13: 894 | C13: =IFERROR(INDEX('Data Fields'!$B:$K,MATCH($B13,'Data Fields'!$B:$B,0),MATCH(B$9,'Data Fields'!$9:$9,0)),0) -> Contact No. | D13: =IFERROR(INDEX('Data Fields'!$B:$K,MATCH($B13,'Data Fields'!$B:$B,0),MATCH(C$9,'Data Fields'!$9:$9,0)),0) -> PMS Attendance Sheet | E13: =IFERROR(INDEX('Data Fields'!$B:$K,MATCH($B13,'Data Fields'!$B:$B,0),MATCH(D$9,'Data Fields'!$9:$9,0)),0) -> DI-ED-01 | F13: =IFERROR(INDEX('Data Fields'!$B:$K,MATCH($B13,'Data Fields'!$B:$B,0),MATCH(E$9,'Data Fields'!$9:$9,0)),0) -> 0 | G13: =IFERROR(INDEX('Data Fields'!$B:$K,MATCH($B13,'Data Fields'!$B:$B,0),MATCH(F$9,'Data Fields'!$9:$9,0)),0) -> Sensitive Personal Information | H13: =IFERROR(INDEX('Data Fields'!$B:$K,MATCH($B13,'Data Fields'!$B:$B,0),MATCH(G$9,'Data Fields'!$9:$9,0)),0) -> Member | I13: =IFERROR(INDEX('Data Fields'!$B:$K,MATCH($B13,'Data Fields'!$B:$B,0),MATCH(H$9,'Data Fields'!$9:$9,0)),0) -> To contact attendee | J13: =IFERROR(INDEX('Data Fields'!$B:$K,MATCH($B13,'Data Fields'!$B:$B,0),MATCH(I$9,'Data Fields'!$9:$9,0)),0) -> 0 | K13: =IFERROR(INDEX('Data Fields'!$B:$K,MATCH($B13,'Data Fields'!$B:$B,0),MATCH(J$9,'Data Fields'!$9:$9,0)),0) -> Education and Training Committee
B14: 895 | C14: =IFERROR(INDEX('Data Fields'!$B:$K,MATCH($B14,'Data Fields'!$B:$B,0),MATCH(B$9,'Data Fields'!$9:$9,0)),0) -> Occupation | D14: =IFERROR(INDEX('Data Fields'!$B:$K,MATCH($B14,'Data Fields'!$B:$B,0),MATCH(C$9,'Data Fields'!$9:$9,0)),0) -> PMS Attendance Sheet | E14: =IFERROR(INDEX('Data Fields'!$B:$K,MATCH($B14,'Data Fields'!$B:$B,0),MATCH(D$9,'Data Fields'!$9:$9,0)),0) -> DI-ED-01 | F14: =IFERROR(INDEX('Data Fields'!$B:$K,MATCH($B14,'Data Fields'!$B:$B,0),MATCH(E$9,'Data Fields'!$9:$9,0)),0) -> 0 | G14: =IFERROR(INDEX('Data Fields'!$B:$K,MATCH($B14,'Data Fields'!$B:$B,0),MATCH(F$9,'Data Fields'!$9:$9,0)),0) -> Sensitive Personal Information | H14: =IFERROR(INDEX('Data Fields'!$B:$K,MATCH($B14,'Data Fields'!$B:$B,0),MATCH(G$9,'Data Fields'!$9:$9,0)),0) -> Member | I14: =IFERROR(INDEX('Data Fields'!$B:$K,MATCH($B14,'Data Fields'!$B:$B,0),MATCH(H$9,'Data Fields'!$9:$9,0)),0) -> To determine attendance of PMS | J14: =IFERROR(INDEX('Data Fields'!$B:$K,MATCH($B14,'Data Fields'!$B:$B,0),MATCH(I$9,'Data Fields'!$9:$9,0)),0) -> 0 | K14: =IFERROR(INDEX('Data Fields'!$B:$K,MATCH($B14,'Data Fields'!$B:$B,0),MATCH(J$9,'Data Fields'!$9:$9,0)),0) -> Education and Training Committee
B15: 896 | C15: =IFERROR(INDEX('Data Fields'!$B:$K,MATCH($B15,'Data Fields'!$B:$B,0),MATCH(B$9,'Data Fields'!$9:$9,0)),0) -> Civil Status | D15: =IFERROR(INDEX('Data Fields'!$B:$K,MATCH($B15,'Data Fields'!$B:$B,0),MATCH(C$9,'Data Fields'!$9:$9,0)),0) -> PMS Attendance Sheet | E15: =IFERROR(INDEX('Data Fields'!$B:$K,MATCH($B15,'Data Fields'!$B:$B,0),MATCH(D$9,'Data Fields'!$9:$9,0)),0) -> DI-ED-01 | F15: =IFERROR(INDEX('Data Fields'!$B:$K,MATCH($B15,'Data Fields'!$B:$B,0),MATCH(E$9,'Data Fields'!$9:$9,0)),0) -> 0 | G15: =IFERROR(INDEX('Data Fields'!$B:$K,MATCH($B15,'Data Fields'!$B:$B,0),MATCH(F$9,'Data Fields'!$9:$9,0)),0) -> Sensitive Personal Information | H15: =IFERROR(INDEX('Data Fields'!$B:$K,MATCH($B15,'Data Fields'!$B:$B,0),MATCH(G$9,'Data Fields'!$9:$9,0)),0) -> Member | I15: =IFERROR(INDEX('Data Fields'!$B:$K,MATCH($B15,'Data Fields'!$B:$B,0),MATCH(H$9,'Data Fields'!$9:$9,0)),0) -> To determine attendance of PMS | J15: =IFERROR(INDEX('Data Fields'!$B:$K,MATCH($B15,'Data Fields'!$B:$B,0),MATCH(I$9,'Data Fields'!$9:$9,0)),0) -> 0 | K15: =IFERROR(INDEX('Data Fields'!$B:$K,MATCH($B15,'Data Fields'!$B:$B,0),MATCH(J$9,'Data Fields'!$9:$9,0)),0) -> Education and Training Committee
B16: 897 | C16: =IFERROR(INDEX('Data Fields'!$B:$K,MATCH($B16,'Data Fields'!$B:$B,0),MATCH(B$9,'Data Fields'!$9:$9,0)),0) -> Member's Name | D16: =IFERROR(INDEX('Data Fields'!$B:$K,MATCH($B16,'Data Fields'!$B:$B,0),MATCH(C$9,'Data Fields'!$9:$9,0)),0) -> Loan Briefing Attendance Sheet | E16: =IFERROR(INDEX('Data Fields'!$B:$K,MATCH($B16,'Data Fields'!$B:$B,0),MATCH(D$9,'Data Fields'!$9:$9,0)),0) -> DI-ED-02 | F16: =IFERROR(INDEX('Data Fields'!$B:$K,MATCH($B16,'Data Fields'!$B:$B,0),MATCH(E$9,'Data Fields'!$9:$9,0)),0) -> 0 | G16: =IFERROR(INDEX('Data Fields'!$B:$K,MATCH($B16,'Data Fields'!$B:$B,0),MATCH(F$9,'Data Fields'!$9:$9,0)),0) -> Personal Information | H16: =IFERROR(INDEX('Data Fields'!$B:$K,MATCH($B16,'Data Fields'!$B:$B,0),MATCH(G$9,'Data Fields'!$9:$9,0)),0) -> Member | I16: =IFERROR(INDEX('Data Fields'!$B:$K,MATCH($B16,'Data Fields'!$B:$B,0),MATCH(H$9,'Data Fields'!$9:$9,0)),0) -> To determine attendance of Loan Briefing | J16: =IFERROR(INDEX('Data Fields'!$B:$K,MATCH($B16,'Data Fields'!$B:$B,0),MATCH(I$9,'Data Fields'!$9:$9,0)),0) -> 0 | K16: =IFERROR(INDEX('Data Fields'!$B:$K,MATCH($B16,'Data Fields'!$B:$B,0),MATCH(J$9,'Data Fields'!$9:$9,0)),0) -> Education and Training Committee
B17: 898 | C17: =IFERROR(INDEX('Data Fields'!$B:$K,MATCH($B17,'Data Fields'!$B:$B,0),MATCH(B$9,'Data Fields'!$9:$9,0)),0) -> Contact No. | D17: =IFERROR(INDEX('Data Fields'!$B:$K,MATCH($B17,'Data Fields'!$B:$B,0),MATCH(C$9,'Data Fields'!$9:$9,0)),0) -> Loan Briefing Attendance Sheet | E17: =IFERROR(INDEX('Data Fields'!$B:$K,MATCH($B17,'Data Fields'!$B:$B,0),MATCH(D$9,'Data Fields'!$9:$9,0)),0) -> DI-ED-02 | F17: =IFERROR(INDEX('Data Fields'!$B:$K,MATCH($B17,'Data Fields'!$B:$B,0),MATCH(E$9,'Data Fields'!$9:$9,0)),0) -> 0 | G17: =IFERROR(INDEX('Data Fields'!$B:$K,MATCH($B17,'Data Fields'!$B:$B,0),MATCH(F$9,'Data Fields'!$9:$9,0)),0) -> Personal Information | H17: =IFERROR(INDEX('Data Fields'!$B:$K,MATCH($B17,'Data Fields'!$B:$B,0),MATCH(G$9,'Data Fields'!$9:$9,0)),0) -> Member | I17: =IFERROR(INDEX('Data Fields'!$B:$K,MATCH($B17,'Data Fields'!$B:$B,0),MATCH(H$9,'Data Fields'!$9:$9,0)),0) -> To determine attendance of Loan Briefing | J17: =IFERROR(INDEX('Data Fields'!$B:$K,MATCH($B17,'Data Fields'!$B:$B,0),MATCH(I$9,'Data Fields'!$9:$9,0)),0) -> 0 | K17: =IFERROR(INDEX('Data Fields'!$B:$K,MATCH($B17,'Data Fields'!$B:$B,0),MATCH(J$9,'Data Fields'!$9:$9,0)),0) -> Education and Training Committee
B18: 899 | C18: =IFERROR(INDEX('Data Fields'!$B:$K,MATCH($B18,'Data Fields'!$B:$B,0),MATCH(B$9,'Data Fields'!$9:$9,0)),0) -> Signature | D18: =IFERROR(INDEX('Data Fields'!$B:$K,MATCH($B18,'Data Fields'!$B:$B,0),MATCH(C$9,'Data Fields'!$9:$9,0)),0) -> Loan Briefing Attendance Sheet | E18: =IFERROR(INDEX('Data Fields'!$B:$K,MATCH($B18,'Data Fields'!$B:$B,0),MATCH(D$9,'Data Fields'!$9:$9,0)),0) -> DI-ED-02 | F18: =IFERROR(INDEX('Data Fields'!$B:$K,MATCH($B18,'Data Fields'!$B:$B,0),MATCH(E$9,'Data Fields'!$9:$9,0)),0) -> 0 | G18: =IFERROR(INDEX('Data Fields'!$B:$K,MATCH($B18,'Data Fields'!$B:$B,0),MATCH(F$9,'Data Fields'!$9:$9,0)),0) -> Sensitive Personal Information | H18: =IFERROR(INDEX('Data Fields'!$B:$K,MATCH($B18,'Data Fields'!$B:$B,0),MATCH(G$9,'Data Fields'!$9:$9,0)),0) -> Member | I18: =IFERROR(INDEX('Data Fields'!$B:$K,MATCH($B18,'Data Fields'!$B:$B,0),MATCH(H$9,'Data Fields'!$9:$9,0)),0) -> To determine attendance of Loan Briefing | J18: =IFERROR(INDEX('Data Fields'!$B:$K,MATCH($B18,'Data Fields'!$B:$B,0),MATCH(I$9,'Data Fields'!$9:$9,0)),0) -> 0 | K18: =IFERROR(INDEX('Data Fields'!$B:$K,MATCH($B18,'Data Fields'!$B:$B,0),MATCH(J$9,'Data Fields'!$9:$9,0)),0) -> Education and Training Committee
B19: 900 | C19: =IFERROR(INDEX('Data Fields'!$B:$K,MATCH($B19,'Data Fields'!$B:$B,0),MATCH(B$9,'Data Fields'!$9:$9,0)),0) -> Date | D19: =IFERROR(INDEX('Data Fields'!$B:$K,MATCH($B19,'Data Fields'!$B:$B,0),MATCH(C$9,'Data Fields'!$9:$9,0)),0) -> EdCom Volunteer's Profile | E19: =IFERROR(INDEX('Data Fields'!$B:$K,MATCH($B19,'Data Fields'!$B:$B,0),MATCH(D$9,'Data Fields'!$9:$9,0)),0) -> DI-ED-03 | F19: =IFERROR(INDEX('Data Fields'!$B:$K,MATCH($B19,'Data Fields'!$B:$B,0),MATCH(E$9,'Data Fields'!$9:$9,0)),0) -> 0 | G19: =IFERROR(INDEX('Data Fields'!$B:$K,MATCH($B19,'Data Fields'!$B:$B,0),MATCH(F$9,'Data Fields'!$9:$9,0)),0) -> Non-personal Information | H19: =IFERROR(INDEX('Data Fields'!$B:$K,MATCH($B19,'Data Fields'!$B:$B,0),MATCH(G$9,'Data Fields'!$9:$9,0)),0) -> Volunteer | I19: =IFERROR(INDEX('Data Fields'!$B:$K,MATCH($B19,'Data Fields'!$B:$B,0),MATCH(H$9,'Data Fields'!$9:$9,0)),0) -> To determine date of application | J19: =IFERROR(INDEX('Data Fields'!$B:$K,MATCH($B19,'Data Fields'!$B:$B,0),MATCH(I$9,'Data Fields'!$9:$9,0)),0) -> 0 | K19: =IFERROR(INDEX('Data Fields'!$B:$K,MATCH($B19,'Data Fields'!$B:$B,0),MATCH(J$9,'Data Fields'!$9:$9,0)),0) -> Education and Training Committee
B20: 901 | C20: =IFERROR(INDEX('Data Fields'!$B:$K,MATCH($B20,'Data Fields'!$B:$B,0),MATCH(B$9,'Data Fields'!$9:$9,0)),0) -> 2x2 Picture | D20: =IFERROR(INDEX('Data Fields'!$B:$K,MATCH($B20,'Data Fields'!$B:$B,0),MATCH(C$9,'Data Fields'!$9:$9,0)),0) -> EdCom Volunteer's Profile | E20: =IFERROR(INDEX('Data Fields'!$B:$K,MATCH($B20,'Data Fields'!$B:$B,0),MATCH(D$9,'Data Fields'!$9:$9,0)),0) -> DI-ED-03 | F20: =IFERROR(INDEX('Data Fields'!$B:$K,MATCH($B20,'Data Fields'!$B:$B,0),MATCH(E$9,'Data Fields'!$9:$9,0)),0) -> 0 | G20: =IFERROR(INDEX('Data Fields'!$B:$K,MATCH($B20,'Data Fields'!$B:$B,0),MATCH(F$9,'Data Fields'!$9:$9,0)),0) -> Sensitive Personal Information | H20: =IFERROR(INDEX('Data Fields'!$B:$K,MATCH($B20,'Data Fields'!$B:$B,0),MATCH(G$9,'Data Fields'!$9:$9,0)),0) -> Volunteer | I20: =IFERROR(INDEX('Data Fields'!$B:$K,MATCH($B20,'Data Fields'!$B:$B,0),MATCH(H$9,'Data Fields'!$9:$9,0)),0) -> To determine identity of volunteer | J20: =IFERROR(INDEX('Data Fields'!$B:$K,MATCH($B20,'Data Fields'!$B:$B,0),MATCH(I$9,'Data Fields'!$9:$9,0)),0) -> 0 | K20: =IFERROR(INDEX('Data Fields'!$B:$K,MATCH($B20,'Data Fields'!$B:$B,0),MATCH(J$9,'Data Fields'!$9:$9,0)),0) -> Education and Training Committee
B21: 902 | C21: =IFERROR(INDEX('Data Fields'!$B:$K,MATCH($B21,'Data Fields'!$B:$B,0),MATCH(B$9,'Data Fields'!$9:$9,0)),0) -> Date of TOT | D21: =IFERROR(INDEX('Data Fields'!$B:$K,MATCH($B21,'Data Fields'!$B:$B,0),MATCH(C$9,'Data Fields'!$9:$9,0)),0) -> EdCom Volunteer's Profile | E21: =IFERROR(INDEX('Data Fields'!$B:$K,MATCH($B21,'Data Fields'!$B:$B,0),MATCH(D$9,'Data Fields'!$9:$9,0)),0) -> DI-ED-03 | F21: =IFERROR(INDEX('Data Fields'!$B:$K,MATCH($B21,'Data Fields'!$B:$B,0),MATCH(E$9,'Data Fields'!$9:$9,0)),0) -> 0 | G21: =IFERROR(INDEX('Data Fields'!$B:$K,MATCH($B21,'Data Fields'!$B:$B,0),MATCH(F$9,'Data Fields'!$9:$9,0)),0) -> Non-personal Information | H21: =IFERROR(INDEX('Data Fields'!$B:$K,MATCH($B21,'Data Fields'!$B:$B,0),MATCH(G$9,'Data Fields'!$9:$9,0)),0) -> Volunteer | I21: =IFERROR(INDEX('Data Fields'!$B:$K,MATCH($B21,'Data Fields'!$B:$B,0),MATCH(H$9,'Data Fields'!$9:$9,0)),0) -> To determine TOT of volunteer | J21: =IFERROR(INDEX('Data Fields'!$B:$K,MATCH($B21,'Data Fields'!$B:$B,0),MATCH(I$9,'Data Fields'!$9:$9,0)),0) -> 0 | K21: =IFERROR(INDEX('Data Fields'!$B:$K,MATCH($B21,'Data Fields'!$B:$B,0),MATCH(J$9,'Data Fields'!$9:$9,0)),0) -> Education and Training Committee
... B152: 1033 | C152: =IFERROR(INDEX('Data Fields'!$B:$K,MATCH($B152,'Data Fields'!$B:$B,0),MATCH(B$9,'Data Fields'!$9:$9,0)),0) -> Number of Accounts | D152: =IFERROR(INDEX('Data Fields'!$B:$K,MATCH($B152,'Data Fields'!$B:$B,0),MATCH(C$9,'Data Fields'!$9:$9,0)),0) -> Reason/Cause Resulting to Withdrawal of Membership | E152: =IFERROR(INDEX('Data Fields'!$B:$K,MATCH($B152,'Data Fields'!$B:$B,0),MATCH(D$9,'Data Fields'!$9:$9,0)),0) -> DI-ED-07 | F152: =IFERROR(INDEX('Data Fields'!$B:$K,MATCH($B152,'Data Fields'!$B:$B,0),MATCH(E$9,'Data Fields'!$9:$9,0)),0) -> 0 | G152: =IFERROR(INDEX('Data Fields'!$B:$K,MATCH($B152,'Data Fields'!$B:$B,0),MATCH(F$9,'Data Fields'!$9:$9,0)),0) -> Sensitive Personal Information | H152: =IFERROR(INDEX('Data Fields'!$B:$K,MATCH($B152,'Data Fields'!$B:$B,0),MATCH(G$9,'Data Fields'!$9:$9,0)),0) -> Member | I152: =IFERROR(INDEX('Data Fields'!$B:$K,MATCH($B152,'Data Fields'!$B:$B,0),MATCH(H$9,'Data Fields'!$9:$9,0)),0) -> To summarize data for report to Board of Directors | J152: =IFERROR(INDEX('Data Fields'!$B:$K,MATCH($B152,'Data Fields'!$B:$B,0),MATCH(I$9,'Data Fields'!$9:$9,0)),0) -> 0 | K152: =IFERROR(INDEX('Data Fields'!$B:$K,MATCH($B152,'Data Fields'!$B:$B,0),MATCH(J$9,'Data Fields'!$9:$9,0)),0) -> Education and Training Committee

Sheet Finance
B9: No. | C9: No.2 | D9: DATA FIELD | E9: DOCUMENT | F9: Doc Ref No. | G9: GENERIC DATA CLASSIFICATION | H9: DATA CLASSIFICATION | I9: DATA SUBJECT CATEGORY | J9: PURPOSE OF COLLECTION | K9: REMARKS | L9: DOCUMENT OWNER
B10: 1034 | C10: 1 | D10: =IFERROR(INDEX('Data Fields'!$B:$K,MATCH($B10,'Data Fields'!$B:$B,0),MATCH(B$9,'Data Fields'!$9:$9,0)),0) -> Date | E10: =IFERROR(INDEX('Data Fields'!$B:$K,MATCH($B10,'Data Fields'!$B:$B,0),MATCH(D$9,'Data Fields'!$9:$9,0)),0) -> Requisition Slip | F10: =IFERROR(INDEX('Data Fields'!$B:$K,MATCH($B10,'Data Fields'!$B:$B,0),MATCH(E$9,'Data Fields'!$9:$9,0)),0) -> DI-FD-01 | G10: =IFERROR(INDEX('Data Fields'!$B:$K,MATCH($B10,'Data Fields'!$B:$B,0),MATCH(F$9,'Data Fields'!$9:$9,0)),0) -> 0 | H10: =IFERROR(INDEX('Data Fields'!$B:$K,MATCH($B10,'Data Fields'!$B:$B,0),MATCH(G$9,'Data Fields'!$9:$9,0)),0) -> Non-personal Information | I10: =IFERROR(INDEX('Data Fields'!$B:$K,MATCH($B10,'Data Fields'!$B:$B,0),MATCH(H$9,'Data Fields'!$9:$9,0)),0) -> Employee | J10: =IFERROR(INDEX('Data Fields'!$B:$K,MATCH($B10,'Data Fields'!$B:$B,0),MATCH(I$9,'Data Fields'!$9:$9,0)),0) -> To determine the date of the request | K10: =IFERROR(INDEX('Data Fields'!$B:$K,MATCH($B10,'Data Fields'!$B:$B,0),MATCH(J$9,'Data Fields'!$9:$9,0)),0) -> 0 | L10: =IFERROR(INDEX('Data Fields'!$B:$K,MATCH($B10,'Data Fields'!$B:$B,0),MATCH(K$9,'Data Fields'!$9:$9,0)),0) -> Finance Department
B11: 1035 | C11: 2 | D11: =IFERROR(INDEX('Data Fields'!$B:$K,MATCH($B11,'Data Fields'!$B:$B,0),MATCH(B$9,'Data Fields'!$9:$9,0)),0) -> Quantity | E11: =IFERROR(INDEX('Data Fields'!$B:$K,MATCH($B11,'Data Fields'!$B:$B,0),MATCH(D$9,'Data Fields'!$9:$9,0)),0) -> Requisition Slip | F11: =IFERROR(INDEX('Data Fields'!$B:$K,MATCH($B11,'Data Fields'!$B:$B,0),MATCH(E$9,'Data Fields'!$9:$9,0)),0) -> DI-FD-01 | G11: =IFERROR(INDEX('Data Fields'!$B:$K,MATCH($B11,'Data Fields'!$B:$B,0),MATCH(F$9,'Data Fields'!$9:$9,0)),0) -> 0 | H11: =IFERROR(INDEX('Data Fields'!$B:$K,MATCH($B11,'Data Fields'!$B:$B,0),MATCH(G$9,'Data Fields'!$9:$9,0)),0) -> Non-personal Information | I11: =IFERROR(INDEX('Data Fields'!$B:$K,MATCH($B11,'Data Fields'!$B:$B,0),MATCH(H$9,'Data Fields'!$9:$9,0)),0) -> Employee | J11: =IFERROR(INDEX('Data Fields'!$B:$K,MATCH($B11,'Data Fields'!$B:$B,0),MATCH(I$9,'Data Fields'!$9:$9,0)),0) -> To determine the quantity of materials to be acquired | K11: =IFERROR(INDEX('Data Fields'!$B:$K,MATCH($B11,'Data Fields'!$B:$B,0),MATCH(J$9,'Data Fields'!$9:$9,0)),0) -> 0 | L11: =IFERROR(INDEX('Data Fields'!$B:$K,MATCH($B11,'Data Fields'!$B:$B,0),MATCH(K$9,'Data Fields'!$9:$9,0)),0) -> Finance Department
B12: 1036 | C12: 3 | D12: =IFERROR(INDEX('Data Fields'!$B:$K,MATCH($B12,'Data Fields'!$B:$B,0),MATCH(B$9,'Data Fields'!$9:$9,0)),0) -> Unit | E12: =IFERROR(INDEX('Data Fields'!$B:$K,MATCH($B12,'Data Fields'!$B:$B,0),MATCH(D$9,'Data Fields'!$9:$9,0)),0) -> Requisition Slip | F12: =IFERROR(INDEX('Data Fields'!$B:$K,MATCH($B12,'Data Fields'!$B:$B,0),MATCH(E$9,'Data Fields'!$9:$9,0)),0) -> DI-FD-01 | G12: =IFERROR(INDEX('Data Fields'!$B:$K,MATCH($B12,'Data Fields'!$B:$B,0),MATCH(F$9,'Data Fields'!$9:$9,0)),0) -> 0 | H12: =IFERROR(INDEX('Data Fields'!$B:$K,MATCH($B12,'Data Fields'!$B:$B,0),MATCH(G$9,'Data Fields'!$9:$9,0)),0) -> Non-personal Information | I12: =IFERROR(INDEX('Data Fields'!$B:$K,MATCH($B12,'Data Fields'!$B:$B,0),MATCH(H$9,'Data Fields'!$9:$9,0)),0) -> Employee | J12: =IFERROR(INDEX('Data Fields'!$B:$K,MATCH($B12,'Data Fields'!$B:$B,0),MATCH(I$9,'Data Fields'!$9:$9,0)),0) -> To determine the unit quantity of materials to be acquired | K12: =IFERROR(INDEX('Data Fields'!$B:$K,MATCH($B12,'Data Fields'!$B:$B,0),MATCH(J$9,'Data Fields'!$9:$9,0)),0) -> 0 | L12: =IFERROR(INDEX('Data Fields'!$B:$K,MATCH($B12,'Data Fields'!$B:$B,0),MATCH(K$9,'Data Fields'!$9:$9,0)),0) -> Finance Department
B13: 1037 | C13: 4 | D13: =IFERROR(INDEX('Data Fields'!$B:$K,MATCH($B13,'Data Fields'!$B:$B,0),MATCH(B$9,'Data Fields'!$9:$9,0)),0) -> Description | E13: =IFERROR(INDEX('Data Fields'!$B:$K,MATCH($B13,'Data Fields'!$B:$B,0),MATCH(D$9,'Data Fields'!$9:$9,0)),0) -> Requisition Slip | F13: =IFERROR(INDEX('Data Fields'!$B:$K,MATCH($B13,'Data Fields'!$B:$B,0),MATCH(E$9,'Data Fields'!$9:$9,0)),0) -> DI-FD-01 | G13: =IFERROR(INDEX('Data Fields'!$B:$K,MATCH($B13,'Data Fields'!$B:$B,0),MATCH(F$9,'Data Fields'!$9:$9,0)),0) -> 0 | H13: =IFERROR(INDEX('Data Fields'!$B:$K,MATCH($B13,'Data Fields'!$B:$B,0),MATCH(G$9,'Data Fields'!$9:$9,0)),0) -> Non-personal Information | I13: =IFERROR(INDEX('Data Fields'!$B:$K,MATCH($B13,'Data Fields'!$B:$B,0),MATCH(H$9,'Data Fields'!$9:$9,0)),0) -> Employee | J13: =IFERROR(INDEX('Data Fields'!$B:$K,MATCH($B13,'Data Fields'!$B:$B,0),MATCH(I$9,'Data Fields'!$9:$9,0)),0) -> To determine the description of materials to be acquired | K13: =IFERROR(INDEX('Data Fields'!$B:$K,MATCH($B13,'Data Fields'!$B:$B,0),MATCH(J$9,'Data Fields'!$9:$9,0)),0) -> 0 | L13: =IFERROR(INDEX('Data Fields'!$B:$K,MATCH($B13,'Data Fields'!$B:$B,0),MATCH(K$9,'Data Fields'!$9:$9,0)),0) -> Finance Department
B14: 1038 | C14: 5 | D14: =IFERROR(INDEX('Data Fields'!$B:$K,MATCH($B14,'Data Fields'!$B:$B,0),MATCH(B$9,'Data Fields'!$9:$9,0)),0) -> Purpose | E14: =IFERROR(INDEX('Data Fields'!$B:$K,MATCH($B14,'Data Fields'!$B:$B,0),MATCH(D$9,'Data Fields'!$9:$9,0)),0) -> Requisition Slip | F14: =IFERROR(INDEX('Data Fields'!$B:$K,MATCH($B14,'Data Fields'!$B:$B,0),MATCH(E$9,'Data Fields'!$9:$9,0)),0) -> DI-FD-01 | G14: =IFERROR(INDEX('Data Fields'!$B:$K,MATCH($B14,'Data Fields'!$B:$B,0),MATCH(F$9,'Data Fields'!$9:$9,0)),0) -> 0 | H14: =IFERROR(INDEX('Data Fields'!$B:$K,MATCH($B14,'Data Fields'!$B:$B,0),MATCH(G$9,'Data Fields'!$9:$9,0)),0) -> Non-personal Information | I14: =IFERROR(INDEX('Data Fields'!$B:$K,MATCH($B14,'Data Fields'!$B:$B,0),MATCH(H$9,'Data Fields'!$9:$9,0)),0) -> Employee | J14: =IFERROR(INDEX('Data Fields'!$B:$K,MATCH($B14,'Data Fields'!$B:$B,0),MATCH(I$9,'Data Fields'!$9:$9,0)),0) -> To determine the purpose of the acquisition | K14: =IFERROR(INDEX('Data Fields'!$B:$K,MATCH($B14,'Data Fields'!$B:$B,0),MATCH(J$9,'Data Fields'!$9:$9,0)),0) -> 0 | L14: =IFERROR(INDEX('Data Fields'!$B:$K,MATCH($B14,'Data Fields'!$B:$B,0),MATCH(K$9,'Data Fields'!$9:$9,0)),0) -> Finance Department
B15: 1039 | C15: 6 | D15: =IFERROR(INDEX('Data Fields'!$B:$K,MATCH($B15,'Data Fields'!$B:$B,0),MATCH(B$9,'Data Fields'!$9:$9,0)),0) -> Remarks | E15: =IFERROR(INDEX('Data Fields'!$B:$K,MATCH($B15,'Data Fields'!$B:$B,0),MATCH(D$9,'Data Fields'!$9:$9,0)),0) -> Requisition Slip | F15: =IFERROR(INDEX('Data Fields'!$B:$K,MATCH($B15,'Data Fields'!$B:$B,0),MATCH(E$9,'Data Fields'!$9:$9,0)),0) -> DI-FD-01 | G15: =IFERROR(INDEX('Data Fields'!$B:$K,MATCH($B15,'Data Fields'!$B:$B,0),MATCH(F$9,'Data Fields'!$9:$9,0)),0) -> 0 | H15: =IFERROR(INDEX('Data Fields'!$B:$K,MATCH($B15,'Data Fields'!$B:$B,0),MATCH(G$9,'Data Fields'!$9:$9,0)),0) -> Non-personal Information | I15: =IFERROR(INDEX('Data Fields'!$B:$K,MATCH($B15,'Data Fields'!$B:$B,0),MATCH(H$9,'Data Fields'!$9:$9,0)),0) -> Employee | J15: =IFERROR(INDEX('Data Fields'!$B:$K,MATCH($B15,'Data Fields'!$B:$B,0),MATCH(I$9,'Data Fields'!$9:$9,0)),0) -> For remarks | K15: =IFERROR(INDEX('Data Fields'!$B:$K,MATCH($B15,'Data Fields'!$B:$B,0),MATCH(J$9,'Data Fields'!$9:$9,0)),0) -> 0 | L15: =IFERROR(INDEX('Data Fields'!$B:$K,MATCH($B15,'Data Fields'!$B:$B,0),MATCH(K$9,'Data Fields'!$9:$9,0)),0) -> Finance Department
B16: 1040 | C16: 7 | D16: =IFERROR(INDEX('Data Fields'!$B:$K,MATCH($B16,'Data Fields'!$B:$B,0),MATCH(B$9,'Data Fields'!$9:$9,0)),0) -> Approved by | E16: =IFERROR(INDEX('Data Fields'!$B:$K,MATCH($B16,'Data Fields'!$B:$B,0),MATCH(D$9,'Data Fields'!$9:$9,0)),0) -> Requisition Slip | F16: =IFERROR(INDEX('Data Fields'!$B:$K,MATCH($B16,'Data Fields'!$B:$B,0),MATCH(E$9,'Data Fields'!$9:$9,0)),0) -> DI-FD-01 | G16: =IFERROR(INDEX('Data Fields'!$B:$K,MATCH($B16,'Data Fields'!$B:$B,0),MATCH(F$9,'Data Fields'!$9:$9,0)),0) -> 0 | H16: =IFERROR(INDEX('Data Fields'!$B:$K,MATCH($B16,'Data Fields'!$B:$B,0),MATCH(G$9,'Data Fields'!$9:$9,0)),0) -> Personal Information | I16: =IFERROR(INDEX('Data Fields'!$B:$K,MATCH($B16,'Data Fields'!$B:$B,0),MATCH(H$9,'Data Fields'!$9:$9,0)),0) -> Employee | J16: =IFERROR(INDEX('Data Fields'!$B:$K,MATCH($B16,'Data Fields'!$B:$B,0),MATCH(I$9,'Data Fields'!$9:$9,0)),0) -> To determine who approved the acquisition | K16: =IFERROR(INDEX('Data Fields'!$B:$K,MATCH($B16,'Data Fields'!$B:$B,0),MATCH(J$9,'Data Fields'!$9:$9,0)),0) -> 0 | L16: =IFERROR(INDEX('Data Fields'!$B:$K,MATCH($B16,'Data Fields'!$B:$B,0),MATCH(K$9,'Data Fields'!$9:$9,0)),0) -> Finance Department
B17: 1041 | C17: 8 | D17: =IFERROR(INDEX('Data Fields'!$B:$K,MATCH($B17,'Data Fields'!$B:$B,0),MATCH(B$9,'Data Fields'!$9:$9,0)),0) -> Verified by | E17: =IFERROR(INDEX('Data Fields'!$B:$K,MATCH($B17,'Data Fields'!$B:$B,0),MATCH(D$9,'Data Fields'!$9:$9,0)),0) -> Requisition Slip | F17: =IFERROR(INDEX('Data Fields'!$B:$K,MATCH($B17,'Data Fields'!$B:$B,0),MATCH(E$9,'Data Fields'!$9:$9,0)),0) -> DI-FD-01 | G17: =IFERROR(INDEX('Data Fields'!$B:$K,MATCH($B17,'Data Fields'!$B:$B,0),MATCH(F$9,'Data Fields'!$9:$9,0)),0) -> 0 | H17: =IFERROR(INDEX('Data Fields'!$B:$K,MATCH($B17,'Data Fields'!$B:$B,0),MATCH(G$9,'Data Fields'!$9:$9,0)),0) -> Personal Information | I17: =IFERROR(INDEX('Data Fields'!$B:$K,MATCH($B17,'Data Fields'!$B:$B,0),MATCH(H$9,'Data Fields'!$9:$9,0)),0) -> Employee | J17: =IFERROR(INDEX('Data Fields'!$B:$K,MATCH($B17,'Data Fields'!$B:$B,0),MATCH(I$9,'Data Fields'!$9:$9,0)),0) -> To determine who verified the acquisition | K17: =IFERROR(INDEX('Data Fields'!$B:$K,MATCH($B17,'Data Fields'!$B:$B,0),MATCH(J$9,'Data Fields'!$9:$9,0)),0) -> 0 | L17: =IFERROR(INDEX('Data Fields'!$B:$K,MATCH($B17,'Data Fields'!$B:$B,0),MATCH(K$9,'Data Fields'!$9:$9,0)),0) -> Finance Department
B18: 1042 | C18: 9 | D18: =IFERROR(INDEX('Data Fields'!$B:$K,MATCH($B18,'Data Fields'!$B:$B,0),MATCH(B$9,'Data Fields'!$9:$9,0)),0) -> Requested by | E18: =IFERROR(INDEX('Data Fields'!$B:$K,MATCH($B18,'Data Fields'!$B:$B,0),MATCH(D$9,'Data Fields'!$9:$9,0)),0) -> Requisition Slip | F18: =IFERROR(INDEX('Data Fields'!$B:$K,MATCH($B18,'Data Fields'!$B:$B,0),MATCH(E$9,'Data Fields'!$9:$9,0)),0) -> DI-FD-01 | G18: =IFERROR(INDEX('Data Fields'!$B:$K,MATCH($B18,'Data Fields'!$B:$B,0),MATCH(F$9,'Data Fields'!$9:$9,0)),0) -> 0 | H18: =IFERROR(INDEX('Data Fields'!$B:$K,MATCH($B18,'Data Fields'!$B:$B,0),MATCH(G$9,'Data Fields'!$9:$9,0)),0) -> Personal Information | I18: =IFERROR(INDEX('Data Fields'!$B:$K,MATCH($B18,'Data Fields'!$B:$B,0),MATCH(H$9,'Data Fields'!$9:$9,0)),0) -> Employee | J18: =IFERROR(INDEX('Data Fields'!$B:$K,MATCH($B18,'Data Fields'!$B:$B,0),MATCH(I$9,'Data Fields'!$9:$9,0)),0) -> To determine who requested the acquisition | K18: =IFERROR(INDEX('Data Fields'!$B:$K,MATCH($B18,'Data Fields'!$B:$B,0),MATCH(J$9,'Data Fields'!$9:$9,0)),0) -> 0 | L18: =IFERROR(INDEX('Data Fields'!$B:$K,MATCH($B18,'Data Fields'!$B:$B,0),MATCH(K$9,'Data Fields'!$9:$9,0)),0) -> Finance Department
B19: 1043 | C19: 10 | D19: =IFERROR(INDEX('Data Fields'!$B:$K,MATCH($B19,'Data Fields'!$B:$B,0),MATCH(B$9,'Data Fields'!$9:$9,0)),0) -> Date | E19: =IFERROR(INDEX('Data Fields'!$B:$K,MATCH($B19,'Data Fields'!$B:$B,0),MATCH(D$9,'Data Fields'!$9:$9,0)),0) -> Request for Check Issuance | F19: =IFERROR(INDEX('Data Fields'!$B:$K,MATCH($B19,'Data Fields'!$B:$B,0),MATCH(E$9,'Data Fields'!$9:$9,0)),0) -> DI-FD-02 | G19: =IFERROR(INDEX('Data Fields'!$B:$K,MATCH($B19,'Data Fields'!$B:$B,0),MATCH(F$9,'Data Fields'!$9:$9,0)),0) -> 0 | H19: =IFERROR(INDEX('Data Fields'!$B:$K,MATCH($B19,'Data Fields'!$B:$B,0),MATCH(G$9,'Data Fields'!$9:$9,0)),0) -> Non-personal Information | I19: =IFERROR(INDEX('Data Fields'!$B:$K,MATCH($B19,'Data Fields'!$B:$B,0),MATCH(H$9,'Data Fields'!$9:$9,0)),0) -> Employee | J19: =IFERROR(INDEX('Data Fields'!$B:$K,MATCH($B19,'Data Fields'!$B:$B,0),MATCH(I$9,'Data Fields'!$9:$9,0)),0) -> To determine the date the request was made | K19: =IFERROR(INDEX('Data Fields'!$B:$K,MATCH($B19,'Data Fields'!$B:$B,0),MATCH(J$9,'Data Fields'!$9:$9,0)),0) -> 0 | L19: =IFERROR(INDEX('Data Fields'!$B:$K,MATCH($B19,'Data Fields'!$B:$B,0),MATCH(K$9,'Data Fields'!$9:$9,0)),0) -> Finance Department
B20: 1044 | C20: 11 | D20: =IFERROR(INDEX('Data Fields'!$B:$K,MATCH($B20,'Data Fields'!$B:$B,0),MATCH(B$9,'Data Fields'!$9:$9,0)),0) -> Amount | E20: =IFERROR(INDEX('Data Fields'!$B:$K,MATCH($B20,'Data Fields'!$B:$B,0),MATCH(D$9,'Data Fields'!$9:$9,0)),0) -> Request for Check Issuance | F20: =IFERROR(INDEX('Data Fields'!$B:$K,MATCH($B20,'Data Fields'!$B:$B,0),MATCH(E$9,'Data Fields'!$9:$9,0)),0) -> DI-FD-02 | G20: =IFERROR(INDEX('Data Fields'!$B:$K,MATCH($B20,'Data Fields'!$B:$B,0),MATCH(F$9,'Data Fields'!$9:$9,0)),0) -> 0 | H20: =IFERROR(INDEX('Data Fields'!$B:$K,MATCH($B20,'Data Fields'!$B:$B,0),MATCH(G$9,'Data Fields'!$9:$9,0)),0) -> Non-personal Information | I20: =IFERROR(INDEX('Data Fields'!$B:$K,MATCH($B20,'Data Fields'!$B:$B,0),MATCH(H$9,'Data Fields'!$9:$9,0)),0) -> Employee | J20: =IFERROR(INDEX('Data Fields'!$B:$K,MATCH($B20,'Data Fields'!$B:$B,0),MATCH(I$9,'Data Fields'!$9:$9,0)),0) -> To determine the amount requested | K20: =IFERROR(INDEX('Data Fields'!$B:$K,MATCH($B20,'Data Fields'!$B:$B,0),MATCH(J$9,'Data Fields'!$9:$9,0)),0) -> 0 | L20: =IFERROR(INDEX('Data Fields'!$B:$K,MATCH($B20,'Data Fields'!$B:$B,0),MATCH(K$9,'Data Fields'!$9:$9,0)),0) -> Finance Department
B21: 1045 | C21: 12 | D21: =IFERROR(INDEX('Data Fields'!$B:$K,MATCH($B21,'Data Fields'!$B:$B,0),MATCH(B$9,'Data Fields'!$9:$9,0)),0) -> Purpose | E21: =IFERROR(INDEX('Data Fields'!$B:$K,MATCH($B21,'Data Fields'!$B:$B,0),MATCH(D$9,'Data Fields'!$9:$9,0)),0) -> Request for Check Issuance | F21: =IFERROR(INDEX('Data Fields'!$B:$K,MATCH($B21,'Data Fields'!$B:$B,0),MATCH(E$9,'Data Fields'!$9:$9,0)),0) -> DI-FD-02 | G21: =IFERROR(INDEX('Data Fields'!$B:$K,MATCH($B21,'Data Fields'!$B:$B,0),MATCH(F$9,'Data Fields'!$9:$9,0)),0) -> 0 | H21: =IFERROR(INDEX('Data Fields'!$B:$K,MATCH($B21,'Data Fields'!$B:$B,0),MATCH(G$9,'Data Fields'!$9:$9,0)),0) -> Personal Information | I21: =IFERROR(INDEX('Data Fields'!$B:$K,MATCH($B21,'Data Fields'!$B:$B,0),MATCH(H$9,'Data Fields'!$9:$9,0)),0) -> Employee | J21: =IFERROR(INDEX('Data Fields'!$B:$K,MATCH($B21,'Data Fields'!$B:$B,0),MATCH(I$9,'Data Fields'!$9:$9,0)),0) -> To determine the purpose of the request | K21: =IFERROR(INDEX('Data Fields'!$B:$K,MATCH($B21,'Data Fields'!$B:$B,0),MATCH(J$9,'Data Fields'!$9:$9,0)),0) -> 0 | L21: =IFERROR(INDEX('Data Fields'!$B:$K,MATCH($B21,'Data Fields'!$B:$B,0),MATCH(K$9,'Data Fields'!$9:$9,0)),0) -> Finance Department
... B91: 2504 | C91: 82 | D91: =IFERROR(INDEX('Data Fields'!$B:$K,MATCH($B91,'Data Fields'!$B:$B,0),MATCH(B$9,'Data Fields'!$9:$9,0)),0) -> CR | E91: =IFERROR(INDEX('Data Fields'!$B:$K,MATCH($B91,'Data Fields'!$B:$B,0),MATCH(D$9,'Data Fields'!$9:$9,0)),0) -> General Journal - Salaries | F91: =IFERROR(INDEX('Data Fields'!$B:$K,MATCH($B91,'Data Fields'!$B:$B,0),MATCH(E$9,'Data Fields'!$9:$9,0)),0) -> DI-FD-08 | G91: =IFERROR(INDEX('Data Fields'!$B:$K,MATCH($B91,'Data Fields'!$B:$B,0),MATCH(F$9,'Data Fields'!$9:$9,0)),0) -> 0 | H91: =IFERROR(INDEX('Data Fields'!$B:$K,MATCH($B91,'Data Fields'!$B:$B,0),MATCH(G$9,'Data Fields'!$9:$9,0)),0) -> Non-personal Information | I91: =IFERROR(INDEX('Data Fields'!$B:$K,MATCH($B91,'Data Fields'!$B:$B,0),MATCH(H$9,'Data Fields'!$9:$9,0)),0) -> Employee | J91: =IFERROR(INDEX('Data Fields'!$B:$K,MATCH($B91,'Data Fields'!$B:$B,0),MATCH(I$9,'Data Fields'!$9:$9,0)),0) -> To determine recording of salaries for employees | K91: =IFERROR(INDEX('Data Fields'!$B:$K,MATCH($B91,'Data Fields'!$B:$B,0),MATCH(J$9,'Data Fields'!$9:$9,0)),0) -> 0 | L91: =IFERROR(INDEX('Data Fields'!$B:$K,MATCH($B91,'Data Fields'!$B:$B,0),MATCH(K$9,'Data Fields'!$9:$9,0)),0) -> Finance Department

Sheet HR
B9: No. | C9: No.2 | D9: DATA FIELD | E9: DOCUMENT | F9: Doc Ref No. | G9: GENERIC DATA CLASSIFICATION | H9: DATA CLASSIFICATION | I9: DATA SUBJECT CATEGORY | J9: PURPOSE OF COLLECTION | K9: REMARKS | L9: DOCUMENT OWNER
B10: 1107 | C10: 1 | D10: =IFERROR(INDEX('Data Fields'!$B:$K,MATCH($B10,'Data Fields'!$B:$B,0),MATCH(B$9,'Data Fields'!$9:$9,0)),0) -> Background Investigation Report for: | E10: =IFERROR(INDEX('Data Fields'!$B:$K,MATCH($B10,'Data Fields'!$B:$B,0),MATCH(D$9,'Data Fields'!$9:$9,0)),0) -> Applicant Background Investigation Report | F10: =IFERROR(INDEX('Data Fields'!$B:$K,MATCH($B10,'Data Fields'!$B:$B,0),MATCH(E$9,'Data Fields'!$9:$9,0)),0) -> DI-HR-01 | G10: =IFERROR(INDEX('Data Fields'!$B:$K,MATCH($B10,'Data Fields'!$B:$B,0),MATCH(F$9,'Data Fields'!$9:$9,0)),0) -> 0 | H10: =IFERROR(INDEX('Data Fields'!$B:$K,MATCH($B10,'Data Fields'!$B:$B,0),MATCH(G$9,'Data Fields'!$9:$9,0)),0) -> Sensitive Personal Information | I10: =IFERROR(INDEX('Data Fields'!$B:$K,MATCH($B10,'Data Fields'!$B:$B,0),MATCH(H$9,'Data Fields'!$9:$9,0)),0) -> Applicant | J10: =IFERROR(INDEX('Data Fields'!$B:$K,MATCH($B10,'Data Fields'!$B:$B,0),MATCH(I$9,'Data Fields'!$9:$9,0)),0) -> To determine the Background Investigation Report for: of the Applicant | K10: =IFERROR(INDEX('Data Fields'!$B:$K,MATCH($B10,'Data Fields'!$B:$B,0),MATCH(J$9,'Data Fields'!$9:$9,0)),0) -> 0 | L10: =IFERROR(INDEX('Data Fields'!$B:$K,MATCH($B10,'Data Fields'!$B:$B,0),MATCH(K$9,'Data Fields'!$9:$9,0)),0) -> Human Resource Department
B11: 1108 | C11: 2 | D11: =IFERROR(INDEX('Data Fields'!$B:$K,MATCH($B11,'Data Fields'!$B:$B,0),MATCH(B$9,'Data Fields'!$9:$9,0)),0) -> Declared address 1 | E11: =IFERROR(INDEX('Data Fields'!$B:$K,MATCH($B11,'Data Fields'!$B:$B,0),MATCH(D$9,'Data Fields'!$9:$9,0)),0) -> Applicant Background Investigation Report | F11: =IFERROR(INDEX('Data Fields'!$B:$K,MATCH($B11,'Data Fields'!$B:$B,0),MATCH(E$9,'Data Fields'!$9:$9,0)),0) -> DI-HR-01 | G11: =IFERROR(INDEX('Data Fields'!$B:$K,MATCH($B11,'Data Fields'!$B:$B,0),MATCH(F$9,'Data Fields'!$9:$9,0)),0) -> 0 | H11: =IFERROR(INDEX('Data Fields'!$B:$K,MATCH($B11,'Data Fields'!$B:$B,0),MATCH(G$9,'Data Fields'!$9:$9,0)),0) -> Sensitive Personal Information | I11: =IFERROR(INDEX('Data Fields'!$B:$K,MATCH($B11,'Data Fields'!$B:$B,0),MATCH(H$9,'Data Fields'!$9:$9,0)),0) -> Applicant | J11: =IFERROR(INDEX('Data Fields'!$B:$K,MATCH($B11,'Data Fields'!$B:$B,0),MATCH(I$9,'Data Fields'!$9:$9,0)),0) -> To determine the Declared address 1 of the Applicant | K11: =IFERROR(INDEX('Data Fields'!$B:$K,MATCH($B11,'Data Fields'!$B:$B,0),MATCH(J$9,'Data Fields'!$9:$9,0)),0) -> 0 | L11: =IFERROR(INDEX('Data Fields'!$B:$K,MATCH($B11,'Data Fields'!$B:$B,0),MATCH(K$9,'Data Fields'!$9:$9,0)),0) -> Human Resource Department
B12: 1109 | C12: 3 | D12: =IFERROR(INDEX('Data Fields'!$B:$K,MATCH($B12,'Data Fields'!$B:$B,0),MATCH(B$9,'Data Fields'!$9:$9,0)),0) -> Declared address 2 | E12: =IFERROR(INDEX('Data Fields'!$B:$K,MATCH($B12,'Data Fields'!$B:$B,0),MATCH(D$9,'Data Fields'!$9:$9,0)),0) -> Applicant Background Investigation Report | F12: =IFERROR(INDEX('Data Fields'!$B:$K,MATCH($B12,'Data Fields'!$B:$B,0),MATCH(E$9,'Data Fields'!$9:$9,0)),0) -> DI-HR-01 | G12: =IFERROR(INDEX('Data Fields'!$B:$K,MATCH($B12,'Data Fields'!$B:$B,0),MATCH(F$9,'Data Fields'!$9:$9,0)),0) -> 0 | H12: =IFERROR(INDEX('Data Fields'!$B:$K,MATCH($B12,'Data Fields'!$B:$B,0),MATCH(G$9,'Data Fields'!$9:$9,0)),0) -> Sensitive Personal Information | I12: =IFERROR(INDEX('Data Fields'!$B:$K,MATCH($B12,'Data Fields'!$B:$B,0),MATCH(H$9,'Data Fields'!$9:$9,0)),0) -> Applicant | J12: =IFERROR(INDEX('Data Fields'!$B:$K,MATCH($B12,'Data Fields'!$B:$B,0),MATCH(I$9,'Data Fields'!$9:$9,0)),0) -> To determine the Declared address 2 of the Applicant | K12: =IFERROR(INDEX('Data Fields'!$B:$K,MATCH($B12,'Data Fields'!$B:$B,0),MATCH(J$9,'Data Fields'!$9:$9,0)),0) -> 0 | L12: =IFERROR(INDEX('Data Fields'!$B:$K,MATCH($B12,'Data Fields'!$B:$B,0),MATCH(K$9,'Data Fields'!$9:$9,0)),0) -> Human Resource Department
B13: 1110 | C13: 4 | D13: =IFERROR(INDEX('Data Fields'!$B:$K,MATCH($B13,'Data Fields'!$B:$B,0),MATCH(B$9,'Data Fields'!$9:$9,0)),0) -> Verified address | E13: =IFERROR(INDEX('Data Fields'!$B:$K,MATCH($B13,'Data Fields'!$B:$B,0),MATCH(D$9,'Data Fields'!$9:$9,0)),0) -> Applicant Background Investigation Report | F13: =IFERROR(INDEX('Data Fields'!$B:$K,MATCH($B13,'Data Fields'!$B:$B,0),MATCH(E$9,'Data Fields'!$9:$9,0)),0) -> DI-HR-01 | G13: =IFERROR(INDEX('Data Fields'!$B:$K,MATCH($B13,'Data Fields'!$B:$B,0),MATCH(F$9,'Data Fields'!$9:$9,0)),0) -> 0 | H13: =IFERROR(INDEX('Data Fields'!$B:$K,MATCH($B13,'Data Fields'!$B:$B,0),MATCH(G$9,'Data Fields'!$9:$9,0)),0) -> Sensitive Personal Information | I13: =IFERROR(INDEX('Data Fields'!$B:$K,MATCH($B13,'Data Fields'!$B:$B,0),MATCH(H$9,'Data Fields'!$9:$9,0)),0) -> Applicant | J13: =IFERROR(INDEX('Data Fields'!$B:$K,MATCH($B13,'Data Fields'!$B:$B,0),MATCH(I$9,'Data Fields'!$9:$9,0)),0) -> To determine the Verified address of the Applicant | K13: =IFERROR(INDEX('Data Fields'!$B:$K,MATCH($B13,'Data Fields'!$B:$B,0),MATCH(J$9,'Data Fields'!$9:$9,0)),0) -> 0 | L13: =IFERROR(INDEX('Data Fields'!$B:$K,MATCH($B13,'Data Fields'!$B:$B,0),MATCH(K$9,'Data Fields'!$9:$9,0)),0) -> Human Resource Department
B14: 1111 | C14: 5 | D14: =IFERROR(INDEX('Data Fields'!$B:$K,MATCH($B14,'Data Fields'!$B:$B,0),MATCH(B$9,'Data Fields'!$9:$9,0)),0) -> Contact nos. | E14: =IFERROR(INDEX('Data Fields'!$B:$K,MATCH($B14,'Data Fields'!$B:$B,0),MATCH(D$9,'Data Fields'!$9:$9,0)),0) -> Applicant Background Investigation Report | F14: =IFERROR(INDEX('Data Fields'!$B:$K,MATCH($B14,'Data Fields'!$B:$B,0),MATCH(E$9,'Data Fields'!$9:$9,0)),0) -> DI-HR-01 | G14: =IFERROR(INDEX('Data Fields'!$B:$K,MATCH($B14,'Data Fields'!$B:$B,0),MATCH(F$9,'Data Fields'!$9:$9,0)),0) -> 0 | H14: =IFERROR(INDEX('Data Fields'!$B:$K,MATCH($B14,'Data Fields'!$B:$B,0),MATCH(G$9,'Data Fields'!$9:$9,0)),0) -> Sensitive Personal Information | I14: =IFERROR(INDEX('Data Fields'!$B:$K,MATCH($B14,'Data Fields'!$B:$B,0),MATCH(H$9,'Data Fields'!$9:$9,0)),0) -> Applicant | J14: =IFERROR(INDEX('Data Fields'!$B:$K,MATCH($B14,'Data Fields'!$B:$B,0),MATCH(I$9,'Data Fields'!$9:$9,0)),0) -> To determine the Contact nos. of the Applicant | K14: =IFERROR(INDEX('Data Fields'!$B:$K,MATCH($B14,'Data Fields'!$B:$B,0),MATCH(J$9,'Data Fields'!$9:$9,0)),0) -> 0 | L14: =IFERROR(INDEX('Data Fields'!$B:$K,MATCH($B14,'Data Fields'!$B:$B,0),MATCH(K$9,'Data Fields'!$9:$9,0)),0) -> Human Resource Department
B15: 1112 | C15: 6 | D15: =IFERROR(INDEX('Data Fields'!$B:$K,MATCH($B15,'Data Fields'!$B:$B,0),MATCH(B$9,'Data Fields'!$9:$9,0)),0) -> Email address | E15: =IFERROR(INDEX('Data Fields'!$B:$K,MATCH($B15,'Data Fields'!$B:$B,0),MATCH(D$9,'Data Fields'!$9:$9,0)),0) -> Applicant Background Investigation Report | F15: =IFERROR(INDEX('Data Fields'!$B:$K,MATCH($B15,'Data Fields'!$B:$B,0),MATCH(E$9,'Data Fields'!$9:$9,0)),0) -> DI-HR-01 | G15: =IFERROR(INDEX('Data Fields'!$B:$K,MATCH($B15,'Data Fields'!$B:$B,0),MATCH(F$9,'Data Fields'!$9:$9,0)),0) -> 0 | H15: =IFERROR(INDEX('Data Fields'!$B:$K,MATCH($B15,'Data Fields'!$B:$B,0),MATCH(G$9,'Data Fields'!$9:$9,0)),0) -> Sensitive Personal Information | I15: =IFERROR(INDEX('Data Fields'!$B:$K,MATCH($B15,'Data Fields'!$B:$B,0),MATCH(H$9,'Data Fields'!$9:$9,0)),0) -> Applicant | J15: =IFERROR(INDEX('Data Fields'!$B:$K,MATCH($B15,'Data Fields'!$B:$B,0),MATCH(I$9,'Data Fields'!$9:$9,0)),0) -> To determine the Email address of the Applicant | K15: =IFERROR(INDEX('Data Fields'!$B:$K,MATCH($B15,'Data Fields'!$B:$B,0),MATCH(J$9,'Data Fields'!$9:$9,0)),0) -> 0 | L15: =IFERROR(INDEX('Data Fields'!$B:$K,MATCH($B15,'Data Fields'!$B:$B,0),MATCH(K$9,'Data Fields'!$9:$9,0)),0) -> Human Resource Department
B16: 1113 | C16: 7 | D16: =IFERROR(INDEX('Data Fields'!$B:$K,MATCH($B16,'Data Fields'!$B:$B,0),MATCH(B$9,'Data Fields'!$9:$9,0)),0) -> Personal and family background check: Remarks/Results | E16: =IFERROR(INDEX('Data Fields'!$B:$K,MATCH($B16,'Data Fields'!$B:$B,0),MATCH(D$9,'Data Fields'!$9:$9,0)),0) -> Applicant Background Investigation Report | F16: =IFERROR(INDEX('Data Fields'!$B:$K,MATCH($B16,'Data Fields'!$B:$B,0),MATCH(E$9,'Data Fields'!$9:$9,0)),0) -> DI-HR-01 | G16: =IFERROR(INDEX('Data Fields'!$B:$K,MATCH($B16,'Data Fields'!$B:$B,0),MATCH(F$9,'Data Fields'!$9:$9,0)),0) -> 0 | H16: =IFERROR(INDEX('Data Fields'!$B:$K,MATCH($B16,'Data Fields'!$B:$B,0),MATCH(G$9,'Data Fields'!$9:$9,0)),0) -> Sensitive Personal Information | I16: =IFERROR(INDEX('Data Fields'!$B:$K,MATCH($B16,'Data Fields'!$B:$B,0),MATCH(H$9,'Data Fields'!$9:$9,0)),0) -> Applicant | J16: =IFERROR(INDEX('Data Fields'!$B:$K,MATCH($B16,'Data Fields'!$B:$B,0),MATCH(I$9,'Data Fields'!$9:$9,0)),0) -> To determine the Personal and family background check: Remarks/Results of the Applicant | K16: =IFERROR(INDEX('Data Fields'!$B:$K,MATCH($B16,'Data Fields'!$B:$B,0),MATCH(J$9,'Data Fields'!$9:$9,0)),0) -> 0 | L16: =IFERROR(INDEX('Data Fields'!$B:$K,MATCH($B16,'Data Fields'!$B:$B,0),MATCH(K$9,'Data Fields'!$9:$9,0)),0) -> Human Resource Department
B17: 1114 | C17: 8 | D17: =IFERROR(INDEX('Data Fields'!$B:$K,MATCH($B17,'Data Fields'!$B:$B,0),MATCH(B$9,'Data Fields'!$9:$9,0)),0) -> Education check: Remarks/Results | E17: =IFERROR(INDEX('Data Fields'!$B:$K,MATCH($B17,'Data Fields'!$B:$B,0),MATCH(D$9,'Data Fields'!$9:$9,0)),0) -> Applicant Background Investigation Report | F17: =IFERROR(INDEX('Data Fields'!$B:$K,MATCH($B17,'Data Fields'!$B:$B,0),MATCH(E$9,'Data Fields'!$9:$9,0)),0) -> DI-HR-01 | G17: =IFERROR(INDEX('Data Fields'!$B:$K,MATCH($B17,'Data Fields'!$B:$B,0),MATCH(F$9,'Data Fields'!$9:$9,0)),0) -> 0 | H17: =IFERROR(INDEX('Data Fields'!$B:$K,MATCH($B17,'Data Fields'!$B:$B,0),MATCH(G$9,'Data Fields'!$9:$9,0)),0) -> Sensitive Personal Information | I17: =IFERROR(INDEX('Data Fields'!$B:$K,MATCH($B17,'Data Fields'!$B:$B,0),MATCH(H$9,'Data Fields'!$9:$9,0)),0) -> Applicant | J17: =IFERROR(INDEX('Data Fields'!$B:$K,MATCH($B17,'Data Fields'!$B:$B,0),MATCH(I$9,'Data Fields'!$9:$9,0)),0) -> To determine the Education check: Remarks/Results of the Applicant | K17: =IFERROR(INDEX('Data Fields'!$B:$K,MATCH($B17,'Data Fields'!$B:$B,0),MATCH(J$9,'Data Fields'!$9:$9,0)),0) -> 0 | L17: =IFERROR(INDEX('Data Fields'!$B:$K,MATCH($B17,'Data Fields'!$B:$B,0),MATCH(K$9,'Data Fields'!$9:$9,0)),0) -> Human Resource Department
B18: 1115 | C18: 9 | D18: =IFERROR(INDEX('Data Fields'!$B:$K,MATCH($B18,'Data Fields'!$B:$B,0),MATCH(B$9,'Data Fields'!$9:$9,0)),0) -> Employment check: Remarks/Results | E18: =IFERROR(INDEX('Data Fields'!$B:$K,MATCH($B18,'Data Fields'!$B:$B,0),MATCH(D$9,'Data Fields'!$9:$9,0)),0) -> Applicant Background Investigation Report | F18: =IFERROR(INDEX('Data Fields'!$B:$K,MATCH($B18,'Data Fields'!$B:$B,0),MATCH(E$9,'Data Fields'!$9:$9,0)),0) -> DI-HR-01 | G18: =IFERROR(INDEX('Data Fields'!$B:$K,MATCH($B18,'Data Fields'!$B:$B,0),MATCH(F$9,'Data Fields'!$9:$9,0)),0) -> 0 | H18: =IFERROR(INDEX('Data Fields'!$B:$K,MATCH($B18,'Data Fields'!$B:$B,0),MATCH(G$9,'Data Fields'!$9:$9,0)),0) -> Sensitive Personal Information | I18: =IFERROR(INDEX('Data Fields'!$B:$K,MATCH($B18,'Data Fields'!$B:$B,0),MATCH(H$9,'Data Fields'!$9:$9,0)),0) -> Applicant | J18: =IFERROR(INDEX('Data Fields'!$B:$K,MATCH($B18,'Data Fields'!$B:$B,0),MATCH(I$9,'Data Fields'!$9:$9,0)),0) -> To determine the Employment check: Remarks/Results of the Applicant | K18: =IFERROR(INDEX('Data Fields'!$B:$K,MATCH($B18,'Data Fields'!$B:$B,0),MATCH(J$9,'Data Fields'!$9:$9,0)),0) -> 0 | L18: =IFERROR(INDEX('Data Fields'!$B:$K,MATCH($B18,'Data Fields'!$B:$B,0),MATCH(K$9,'Data Fields'!$9:$9,0)),0) -> Human Resource Department
B19: 1116 | C19: 10 | D19: =IFERROR(INDEX('Data Fields'!$B:$K,MATCH($B19,'Data Fields'!$B:$B,0),MATCH(B$9,'Data Fields'!$9:$9,0)),0) -> Reference check: Remarks/Results | E19: =IFERROR(INDEX('Data Fields'!$B:$K,MATCH($B19,'Data Fields'!$B:$B,0),MATCH(D$9,'Data Fields'!$9:$9,0)),0) -> Applicant Background Investigation Report | F19: =IFERROR(INDEX('Data Fields'!$B:$K,MATCH($B19,'Data Fields'!$B:$B,0),MATCH(E$9,'Data Fields'!$9:$9,0)),0) -> DI-HR-01 | G19: =IFERROR(INDEX('Data Fields'!$B:$K,MATCH($B19,'Data Fields'!$B:$B,0),MATCH(F$9,'Data Fields'!$9:$9,0)),0) -> 0 | H19: =IFERROR(INDEX('Data Fields'!$B:$K,MATCH($B19,'Data Fields'!$B:$B,0),MATCH(G$9,'Data Fields'!$9:$9,0)),0) -> Sensitive Personal Information | I19: =IFERROR(INDEX('Data Fields'!$B:$K,MATCH($B19,'Data Fields'!$B:$B,0),MATCH(H$9,'Data Fields'!$9:$9,0)),0) -> Applicant | J19: =IFERROR(INDEX('Data Fields'!$B:$K,MATCH($B19,'Data Fields'!$B:$B,0),MATCH(I$9,'Data Fields'!$9:$9,0)),0) -> To determine the Reference check: Remarks/Results of the Applicant | K19: =IFERROR(INDEX('Data Fields'!$B:$K,MATCH($B19,'Data Fields'!$B:$B,0),MATCH(J$9,'Data Fields'!$9:$9,0)),0) -> 0 | L19: =IFERROR(INDEX('Data Fields'!$B:$K,MATCH($B19,'Data Fields'!$B:$B,0),MATCH(K$9,'Data Fields'!$9:$9,0)),0) -> Human Resource Department
B20: 1117 | C20: 11 | D20: =IFERROR(INDEX('Data Fields'!$B:$K,MATCH($B20,'Data Fields'!$B:$B,0),MATCH(B$9,'Data Fields'!$9:$9,0)),0) -> Community standing (Neighborhood check): Remarks/Results | E20: =IFERROR(INDEX('Data Fields'!$B:$K,MATCH($B20,'Data Fields'!$B:$B,0),MATCH(D$9,'Data Fields'!$9:$9,0)),0) -> Applicant Background Investigation Report | F20: =IFERROR(INDEX('Data Fields'!$B:$K,MATCH($B20,'Data Fields'!$B:$B,0),MATCH(E$9,'Data Fields'!$9:$9,0)),0) -> DI-HR-01 | G20: =IFERROR(INDEX('Data Fields'!$B:$K,MATCH($B20,'Data Fields'!$B:$B,0),MATCH(F$9,'Data Fields'!$9:$9,0)),0) -> 0 | H20: =IFERROR(INDEX('Data Fields'!$B:$K,MATCH($B20,'Data Fields'!$B:$B,0),MATCH(G$9,'Data Fields'!$9:$9,0)),0) -> Sensitive Personal Information | I20: =IFERROR(INDEX('Data Fields'!$B:$K,MATCH($B20,'Data Fields'!$B:$B,0),MATCH(H$9,'Data Fields'!$9:$9,0)),0) -> Applicant | J20: =IFERROR(INDEX('Data Fields'!$B:$K,MATCH($B20,'Data Fields'!$B:$B,0),MATCH(I$9,'Data Fields'!$9:$9,0)),0) -> To determine the Community standing (Neighborhood check): Remarks/Results of the Applicant | K20: =IFERROR(INDEX('Data Fields'!$B:$K,MATCH($B20,'Data Fields'!$B:$B,0),MATCH(J$9,'Data Fields'!$9:$9,0)),0) -> 0 | L20: =IFERROR(INDEX('Data Fields'!$B:$K,MATCH($B20,'Data Fields'!$B:$B,0),MATCH(K$9,'Data Fields'!$9:$9,0)),0) -> Human Resource Department
B21: 1118 | C21: 12 | D21: =IFERROR(INDEX('Data Fields'!$B:$K,MATCH($B21,'Data Fields'!$B:$B,0),MATCH(B$9,'Data Fields'!$9:$9,0)),0) -> Barangay/ Police check: Remarks/Results | E21: =IFERROR(INDEX('Data Fields'!$B:$K,MATCH($B21,'Data Fields'!$B:$B,0),MATCH(D$9,'Data Fields'!$9:$9,0)),0) -> Applicant Background Investigation Report | F21: =IFERROR(INDEX('Data Fields'!$B:$K,MATCH($B21,'Data Fields'!$B:$B,0),MATCH(E$9,'Data Fields'!$9:$9,0)),0) -> DI-HR-01 | G21: =IFERROR(INDEX('Data Fields'!$B:$K,MATCH($B21,'Data Fields'!$B:$B,0),MATCH(F$9,'Data Fields'!$9:$9,0)),0) -> 0 | H21: =IFERROR(INDEX('Data Fields'!$B:$K,MATCH($B21,'Data Fields'!$B:$B,0),MATCH(G$9,'Data Fields'!$9:$9,0)),0) -> Sensitive Personal Information | I21: =IFERROR(INDEX('Data Fields'!$B:$K,MATCH($B21,'Data Fields'!$B:$B,0),MATCH(H$9,'Data Fields'!$9:$9,0)),0) -> Applicant | J21: =IFERROR(INDEX('Data Fields'!$B:$K,MATCH($B21,'Data Fields'!$B:$B,0),MATCH(I$9,'Data Fields'!$9:$9,0)),0) -> To determine the Barangay/ Police check: Remarks/Results of the Applicant | K21: =IFERROR(INDEX('Data Fields'!$B:$K,MATCH($B21,'Data Fields'!$B:$B,0),MATCH(J$9,'Data Fields'!$9:$9,0)),0) -> 0 | L21: =IFERROR(INDEX('Data Fields'!$B:$K,MATCH($B21,'Data Fields'!$B:$B,0),MATCH(K$9,'Data Fields'!$9:$9,0)),0) -> Human Resource Department
... B875: 1972 | C875: 866 | D875: =IFERROR(INDEX('Data Fields'!$B:$K,MATCH($B875,'Data Fields'!$B:$B,0),MATCH(B$9,'Data Fields'!$9:$9,0)),0) -> Time out | E875: =IFERROR(INDEX('Data Fields'!$B:$K,MATCH($B875,'Data Fields'!$B:$B,0),MATCH(D$9,'Data Fields'!$9:$9,0)),0) -> Employees Attendance Logbook | F875: =IFERROR(INDEX('Data Fields'!$B:$K,MATCH($B875,'Data Fields'!$B:$B,0),MATCH(E$9,'Data Fields'!$9:$9,0)),0) -> DI-HR-30 | G875: =IFERROR(INDEX('Data Fields'!$B:$K,MATCH($B875,'Data Fields'!$B:$B,0),MATCH(F$9,'Data Fields'!$9:$9,0)),0) -> 0 | H875: =IFERROR(INDEX('Data Fields'!$B:$K,MATCH($B875,'Data Fields'!$B:$B,0),MATCH(G$9,'Data Fields'!$9:$9,0)),0) -> Personal Information | I875: =IFERROR(INDEX('Data Fields'!$B:$K,MATCH($B875,'Data Fields'!$B:$B,0),MATCH(H$9,'Data Fields'!$9:$9,0)),0) -> Employee | J875: =IFERROR(INDEX('Data Fields'!$B:$K,MATCH($B875,'Data Fields'!$B:$B,0),MATCH(I$9,'Data Fields'!$9:$9,0)),0) -> To determine the log out time of the employee | K875: =IFERROR(INDEX('Data Fields'!$B:$K,MATCH($B875,'Data Fields'!$B:$B,0),MATCH(J$9,'Data Fields'!$9:$9,0)),0) -> 0 | L875: =IFERROR(INDEX('Data Fields'!$B:$K,MATCH($B875,'Data Fields'!$B:$B,0),MATCH(K$9,'Data Fields'!$9:$9,0)),0) -> Human Resource Department

Sheet IT
B9: No. | C9: DATA FIELD | D9: DOCUMENT | E9: Doc Ref No. | F9: GENERIC DATA CLASSIFICATION | G9: DATA CLASSIFICATION | H9: DATA SUBJECT CATEGORY | I9: PURPOSE OF COLLECTION | J9: REMARKS | K9: DOCUMENT OWNER
B10: 2364 | C10: =IFERROR(INDEX('Data Fields'!$B:$K,MATCH($B10,'Data Fields'!$B:$B,0),MATCH(B$9,'Data Fields'!$9:$9,0)),0) -> User ID | D10: =IFERROR(INDEX('Data Fields'!$B:$K,MATCH($B10,'Data Fields'!$B:$B,0),MATCH(C$9,'Data Fields'!$9:$9,0)),0) -> User Access Level, Rights and Privileges | E10: =IFERROR(INDEX('Data Fields'!$B:$K,MATCH($B10,'Data Fields'!$B:$B,0),MATCH(D$9,'Data Fields'!$9:$9,0)),0) -> DI-IT-01 | F10: =IFERROR(INDEX('Data Fields'!$B:$K,MATCH($B10,'Data Fields'!$B:$B,0),MATCH(E$9,'Data Fields'!$9:$9,0)),0) -> 0 | G10: =IFERROR(INDEX('Data Fields'!$B:$K,MATCH($B10,'Data Fields'!$B:$B,0),MATCH(F$9,'Data Fields'!$9:$9,0)),0) -> Sensitive Personal Information | H10: =IFERROR(INDEX('Data Fields'!$B:$K,MATCH($B10,'Data Fields'!$B:$B,0),MATCH(G$9,'Data Fields'!$9:$9,0)),0) -> Employee | I10: =IFERROR(INDEX('Data Fields'!$B:$K,MATCH($B10,'Data Fields'!$B:$B,0),MATCH(H$9,'Data Fields'!$9:$9,0)),0) -> To identify employee to be given access rights | J10: =IFERROR(INDEX('Data Fields'!$B:$K,MATCH($B10,'Data Fields'!$B:$B,0),MATCH(I$9,'Data Fields'!$9:$9,0)),0) -> 0 | K10: =IFERROR(INDEX('Data Fields'!$B:$K,MATCH($B10,'Data Fields'!$B:$B,0),MATCH(J$9,'Data Fields'!$9:$9,0)),0) -> Information Technology Department
B11: 2365 | C11: =IFERROR(INDEX('Data Fields'!$B:$K,MATCH($B11,'Data Fields'!$B:$B,0),MATCH(B$9,'Data Fields'!$9:$9,0)),0) -> Full Name | D11: =IFERROR(INDEX('Data Fields'!$B:$K,MATCH($B11,'Data Fields'!$B:$B,0),MATCH(C$9,'Data Fields'!$9:$9,0)),0) -> User Access Level, Rights and Privileges | E11: =IFERROR(INDEX('Data Fields'!$B:$K,MATCH($B11,'Data Fields'!$B:$B,0),MATCH(D$9,'Data Fields'!$9:$9,0)),0) -> DI-IT-01 | F11: =IFERROR(INDEX('Data Fields'!$B:$K,MATCH($B11,'Data Fields'!$B:$B,0),MATCH(E$9,'Data Fields'!$9:$9,0)),0) -> 0 | G11: =IFERROR(INDEX('Data Fields'!$B:$K,MATCH($B11,'Data Fields'!$B:$B,0),MATCH(F$9,'Data Fields'!$9:$9,0)),0) -> Personal Information | H11: =IFERROR(INDEX('Data Fields'!$B:$K,MATCH($B11,'Data Fields'!$B:$B,0),MATCH(G$9,'Data Fields'!$9:$9,0)),0) -> Employee | I11: =IFERROR(INDEX('Data Fields'!$B:$K,MATCH($B11,'Data Fields'!$B:$B,0),MATCH(H$9,'Data Fields'!$9:$9,0)),0) -> To identify employee to be given access rights | J11: =IFERROR(INDEX('Data Fields'!$B:$K,MATCH($B11,'Data Fields'!$B:$B,0),MATCH(I$9,'Data Fields'!$9:$9,0)),0) -> 0 | K11: =IFERROR(INDEX('Data Fields'!$B:$K,MATCH($B11,'Data Fields'!$B:$B,0),MATCH(J$9,'Data Fields'!$9:$9,0)),0) -> Information Technology Department
B12: 2366 | C12: =IFERROR(INDEX('Data Fields'!$B:$K,MATCH($B12,'Data Fields'!$B:$B,0),MATCH(B$9,'Data Fields'!$9:$9,0)),0) -> Password | D12: =IFERROR(INDEX('Data Fields'!$B:$K,MATCH($B12,'Data Fields'!$B:$B,0),MATCH(C$9,'Data Fields'!$9:$9,0)),0) -> User Access Level, Rights and Privileges | E12: =IFERROR(INDEX('Data Fields'!$B:$K,MATCH($B12,'Data Fields'!$B:$B,0),MATCH(D$9,'Data Fields'!$9:$9,0)),0) -> DI-IT-01 | F12: =IFERROR(INDEX('Data Fields'!$B:$K,MATCH($B12,'Data Fields'!$B:$B,0),MATCH(E$9,'Data Fields'!$9:$9,0)),0) -> 0 | G12: =IFERROR(INDEX('Data Fields'!$B:$K,MATCH($B12,'Data Fields'!$B:$B,0),MATCH(F$9,'Data Fields'!$9:$9,0)),0) -> Sensitive Personal Information | H12: =IFERROR(INDEX('Data Fields'!$B:$K,MATCH($B12,'Data Fields'!$B:$B,0),MATCH(G$9,'Data Fields'!$9:$9,0)),0) -> Employee | I12: =IFERROR(INDEX('Data Fields'!$B:$K,MATCH($B12,'Data Fields'!$B:$B,0),MATCH(H$9,'Data Fields'!$9:$9,0)),0) -> To identify employee to be given access rights | J12: =IFERROR(INDEX('Data Fields'!$B:$K,MATCH($B12,'Data Fields'!$B:$B,0),MATCH(I$9,'Data Fields'!$9:$9,0)),0) -> 0 | K12: =IFERROR(INDEX('Data Fields'!$B:$K,MATCH($B12,'Data Fields'!$B:$B,0),MATCH(J$9,'Data Fields'!$9:$9,0)),0) -> Information Technology Department
B13: 2367 | C13: =IFERROR(INDEX('Data Fields'!$B:$K,MATCH($B13,'Data Fields'!$B:$B,0),MATCH(B$9,'Data Fields'!$9:$9,0)),0) -> Authority Level | D13: =IFERROR(INDEX('Data Fields'!$B:$K,MATCH($B13,'Data Fields'!$B:$B,0),MATCH(C$9,'Data Fields'!$9:$9,0)),0) -> User Access Level, Rights and Privileges | E13: =IFERROR(INDEX('Data Fields'!$B:$K,MATCH($B13,'Data Fields'!$B:$B,0),MATCH(D$9,'Data Fields'!$9:$9,0)),0) -> DI-IT-01 | F13: =IFERROR(INDEX('Data Fields'!$B:$K,MATCH($B13,'Data Fields'!$B:$B,0),MATCH(E$9,'Data Fields'!$9:$9,0)),0) -> 0 | G13: =IFERROR(INDEX('Data Fields'!$B:$K,MATCH($B13,'Data Fields'!$B:$B,0),MATCH(F$9,'Data Fields'!$9:$9,0)),0) -> Sensitive Personal Information | H13: =IFERROR(INDEX('Data Fields'!$B:$K,MATCH($B13,'Data Fields'!$B:$B,0),MATCH(G$9,'Data Fields'!$9:$9,0)),0) -> Employee | I13: =IFERROR(INDEX('Data Fields'!$B:$K,MATCH($B13,'Data Fields'!$B:$B,0),MATCH(H$9,'Data Fields'!$9:$9,0)),0) -> To designate authority to employee with regards to access rights | J13: =IFERROR(INDEX('Data Fields'!$B:$K,MATCH($B13,'Data Fields'!$B:$B,0),MATCH(I$9,'Data Fields'!$9:$9,0)),0) -> 0 | K13: =IFERROR(INDEX('Data Fields'!$B:$K,MATCH($B13,'Data Fields'!$B:$B,0),MATCH(J$9,'Data Fields'!$9:$9,0)),0) -> Information Technology Department
B14: 2368 | C14: =IFERROR(INDEX('Data Fields'!$B:$K,MATCH($B14,'Data Fields'!$B:$B,0),MATCH(B$9,'Data Fields'!$9:$9,0)),0) -> Current Assignment | D14: =IFERROR(INDEX('Data Fields'!$B:$K,MATCH($B14,'Data Fields'!$B:$B,0),MATCH(C$9,'Data Fields'!$9:$9,0)),0) -> User Access Level, Rights and Privileges | E14: =IFERROR(INDEX('Data Fields'!$B:$K,MATCH($B14,'Data Fields'!$B:$B,0),MATCH(D$9,'Data Fields'!$9:$9,0)),0) -> DI-IT-01 | F14: =IFERROR(INDEX('Data Fields'!$B:$K,MATCH($B14,'Data Fields'!$B:$B,0),MATCH(E$9,'Data Fields'!$9:$9,0)),0) -> 0 | G14: =IFERROR(INDEX('Data Fields'!$B:$K,MATCH($B14,'Data Fields'!$B:$B,0),MATCH(F$9,'Data Fields'!$9:$9,0)),0) -> Personal Information | H14: =IFERROR(INDEX('Data Fields'!$B:$K,MATCH($B14,'Data Fields'!$B:$B,0),MATCH(G$9,'Data Fields'!$9:$9,0)),0) -> Employee | I14: =IFERROR(INDEX('Data Fields'!$B:$K,MATCH($B14,'Data Fields'!$B:$B,0),MATCH(H$9,'Data Fields'!$9:$9,0)),0) -> To designate authority to employee with regards to access rights | J14: =IFERROR(INDEX('Data Fields'!$B:$K,MATCH($B14,'Data Fields'!$B:$B,0),MATCH(I$9,'Data Fields'!$9:$9,0)),0) -> 0 | K14: =IFERROR(INDEX('Data Fields'!$B:$K,MATCH($B14,'Data Fields'!$B:$B,0),MATCH(J$9,'Data Fields'!$9:$9,0)),0) -> Information Technology Department
B15: 2369 | C15: =IFERROR(INDEX('Data Fields'!$B:$K,MATCH($B15,'Data Fields'!$B:$B,0),MATCH(B$9,'Data Fields'!$9:$9,0)),0) -> Cashier/Teller | D15: =IFERROR(INDEX('Data Fields'!$B:$K,MATCH($B15,'Data Fields'!$B:$B,0),MATCH(C$9,'Data Fields'!$9:$9,0)),0) -> User Access Level, Rights and Privileges | E15: =IFERROR(INDEX('Data Fields'!$B:$K,MATCH($B15,'Data Fields'!$B:$B,0),MATCH(D$9,'Data Fields'!$9:$9,0)),0) -> DI-IT-01 | F15: =IFERROR(INDEX('Data Fields'!$B:$K,MATCH($B15,'Data Fields'!$B:$B,0),MATCH(E$9,'Data Fields'!$9:$9,0)),0) -> 0 | G15: =IFERROR(INDEX('Data Fields'!$B:$K,MATCH($B15,'Data Fields'!$B:$B,0),MATCH(F$9,'Data Fields'!$9:$9,0)),0) -> Personal Information | H15: =IFERROR(INDEX('Data Fields'!$B:$K,MATCH($B15,'Data Fields'!$B:$B,0),MATCH(G$9,'Data Fields'!$9:$9,0)),0) -> Employee | I15: =IFERROR(INDEX('Data Fields'!$B:$K,MATCH($B15,'Data Fields'!$B:$B,0),MATCH(H$9,'Data Fields'!$9:$9,0)),0) -> To designate authority to employee with regards to access rights | J15: =IFERROR(INDEX('Data Fields'!$B:$K,MATCH($B15,'Data Fields'!$B:$B,0),MATCH(I$9,'Data Fields'!$9:$9,0)),0) -> 0 | K15: =IFERROR(INDEX('Data Fields'!$B:$K,MATCH($B15,'Data Fields'!$B:$B,0),MATCH(J$9,'Data Fields'!$9:$9,0)),0) -> Information Technology Department
B16: 2370 | C16: =IFERROR(INDEX('Data Fields'!$B:$K,MATCH($B16,'Data Fields'!$B:$B,0),MATCH(B$9,'Data Fields'!$9:$9,0)),0) -> Cashier Status | D16: =IFERROR(INDEX('Data Fields'!$B:$K,MATCH($B16,'Data Fields'!$B:$B,0),MATCH(C$9,'Data Fields'!$9:$9,0)),0) -> User Access Level, Rights and Privileges | E16: =IFERROR(INDEX('Data Fields'!$B:$K,MATCH($B16,'Data Fields'!$B:$B,0),MATCH(D$9,'Data Fields'!$9:$9,0)),0) -> DI-IT-01 | F16: =IFERROR(INDEX('Data Fields'!$B:$K,MATCH($B16,'Data Fields'!$B:$B,0),MATCH(E$9,'Data Fields'!$9:$9,0)),0) -> 0 | G16: =IFERROR(INDEX('Data Fields'!$B:$K,MATCH($B16,'Data Fields'!$B:$B,0),MATCH(F$9,'Data Fields'!$9:$9,0)),0) -> Personal Information | H16: =IFERROR(INDEX('Data Fields'!$B:$K,MATCH($B16,'Data Fields'!$B:$B,0),MATCH(G$9,'Data Fields'!$9:$9,0)),0) -> Employee | I16: =IFERROR(INDEX('Data Fields'!$B:$K,MATCH($B16,'Data Fields'!$B:$B,0),MATCH(H$9,'Data Fields'!$9:$9,0)),0) -> To designate authority to employee with regards to access rights | J16: =IFERROR(INDEX('Data Fields'!$B:$K,MATCH($B16,'Data Fields'!$B:$B,0),MATCH(I$9,'Data Fields'!$9:$9,0)),0) -> 0 | K16: =IFERROR(INDEX('Data Fields'!$B:$K,MATCH($B16,'Data Fields'!$B:$B,0),MATCH(J$9,'Data Fields'!$9:$9,0)),0) -> Information Technology Department
B17: 2371 | C17: =IFERROR(INDEX('Data Fields'!$B:$K,MATCH($B17,'Data Fields'!$B:$B,0),MATCH(B$9,'Data Fields'!$9:$9,0)),0) -> Disbursement Limit | D17: =IFERROR(INDEX('Data Fields'!$B:$K,MATCH($B17,'Data Fields'!$B:$B,0),MATCH(C$9,'Data Fields'!$9:$9,0)),0) -> User Access Level, Rights and Privileges | E17: =IFERROR(INDEX('Data Fields'!$B:$K,MATCH($B17,'Data Fields'!$B:$B,0),MATCH(D$9,'Data Fields'!$9:$9,0)),0) -> DI-IT-01 | F17: =IFERROR(INDEX('Data Fields'!$B:$K,MATCH($B17,'Data Fields'!$B:$B,0),MATCH(E$9,'Data Fields'!$9:$9,0)),0) -> 0 | G17: =IFERROR(INDEX('Data Fields'!$B:$K,MATCH($B17,'Data Fields'!$B:$B,0),MATCH(F$9,'Data Fields'!$9:$9,0)),0) -> Non-personal Information | H17: =IFERROR(INDEX('Data Fields'!$B:$K,MATCH($B17,'Data Fields'!$B:$B,0),MATCH(G$9,'Data Fields'!$9:$9,0)),0) -> Employee | I17: =IFERROR(INDEX('Data Fields'!$B:$K,MATCH($B17,'Data Fields'!$B:$B,0),MATCH(H$9,'Data Fields'!$9:$9,0)),0) -> To designate authority to employee with regards to access rights | J17: =IFERROR(INDEX('Data Fields'!$B:$K,MATCH($B17,'Data Fields'!$B:$B,0),MATCH(I$9,'Data Fields'!$9:$9,0)),0) -> 0 | K17: =IFERROR(INDEX('Data Fields'!$B:$K,MATCH($B17,'Data Fields'!$B:$B,0),MATCH(J$9,'Data Fields'!$9:$9,0)),0) -> Information Technology Department
B18: 2372 | C18: =IFERROR(INDEX('Data Fields'!$B:$K,MATCH($B18,'Data Fields'!$B:$B,0),MATCH(B$9,'Data Fields'!$9:$9,0)),0) -> Privileged Operations | D18: =IFERROR(INDEX('Data Fields'!$B:$K,MATCH($B18,'Data Fields'!$B:$B,0),MATCH(C$9,'Data Fields'!$9:$9,0)),0) -> User Access Level, Rights and Privileges | E18: =IFERROR(INDEX('Data Fields'!$B:$K,MATCH($B18,'Data Fields'!$B:$B,0),MATCH(D$9,'Data Fields'!$9:$9,0)),0) -> DI-IT-01 | F18: =IFERROR(INDEX('Data Fields'!$B:$K,MATCH($B18,'Data Fields'!$B:$B,0),MATCH(E$9,'Data Fields'!$9:$9,0)),0) -> 0 | G18: =IFERROR(INDEX('Data Fields'!$B:$K,MATCH($B18,'Data Fields'!$B:$B,0),MATCH(F$9,'Data Fields'!$9:$9,0)),0) -> Non-personal Information | H18: =IFERROR(INDEX('Data Fields'!$B:$K,MATCH($B18,'Data Fields'!$B:$B,0),MATCH(G$9,'Data Fields'!$9:$9,0)),0) -> Employee | I18: =IFERROR(INDEX('Data Fields'!$B:$K,MATCH($B18,'Data Fields'!$B:$B,0),MATCH(H$9,'Data Fields'!$9:$9,0)),0) -> To designate authority to employee with regards to access rights | J18: =IFERROR(INDEX('Data Fields'!$B:$K,MATCH($B18,'Data Fields'!$B:$B,0),MATCH(I$9,'Data Fields'!$9:$9,0)),0) -> 0 | K18: =IFERROR(INDEX('Data Fields'!$B:$K,MATCH($B18,'Data Fields'!$B:$B,0),MATCH(J$9,'Data Fields'!$9:$9,0)),0) -> Information Technology Department
B19: 2373 | C19: =IFERROR(INDEX('Data Fields'!$B:$K,MATCH($B19,'Data Fields'!$B:$B,0),MATCH(B$9,'Data Fields'!$9:$9,0)),0) -> Override Privileges | D19: =IFERROR(INDEX('Data Fields'!$B:$K,MATCH($B19,'Data Fields'!$B:$B,0),MATCH(C$9,'Data Fields'!$9:$9,0)),0) -> User Access Level, Rights and Privileges | E19: =IFERROR(INDEX('Data Fields'!$B:$K,MATCH($B19,'Data Fields'!$B:$B,0),MATCH(D$9,'Data Fields'!$9:$9,0)),0) -> DI-IT-01 | F19: =IFERROR(INDEX('Data Fields'!$B:$K,MATCH($B19,'Data Fields'!$B:$B,0),MATCH(E$9,'Data Fields'!$9:$9,0)),0) -> 0 | G19: =IFERROR(INDEX('Data Fields'!$B:$K,MATCH($B19,'Data Fields'!$B:$B,0),MATCH(F$9,'Data Fields'!$9:$9,0)),0) -> Non-personal Information | H19: =IFERROR(INDEX('Data Fields'!$B:$K,MATCH($B19,'Data Fields'!$B:$B,0),MATCH(G$9,'Data Fields'!$9:$9,0)),0) -> Employee | I19: =IFERROR(INDEX('Data Fields'!$B:$K,MATCH($B19,'Data Fields'!$B:$B,0),MATCH(H$9,'Data Fields'!$9:$9,0)),0) -> To designate authority to employee with regards to access rights | J19: =IFERROR(INDEX('Data Fields'!$B:$K,MATCH($B19,'Data Fields'!$B:$B,0),MATCH(I$9,'Data Fields'!$9:$9,0)),0) -> 0 | K19: =IFERROR(INDEX('Data Fields'!$B:$K,MATCH($B19,'Data Fields'!$B:$B,0),MATCH(J$9,'Data Fields'!$9:$9,0)),0) -> Information Technology Department

Sheet INBD
B9: No. | C9: Column1 | D9: DATA FIELD | E9: DOCUMENT | F9: Doc Ref No. | G9: GENERIC DATA CLASSIFICATION | H9: DATA CLASSIFICATION | I9: DATA SUBJECT CATEGORY | J9: PURPOSE OF COLLECTION | K9: REMARKS | L9: DOCUMENT OWNER
B10: 1973 | C10: 1 | D10: =IFERROR(INDEX('Data Fields'!$B:$K,MATCH($B10,'Data Fields'!$B:$B,0),MATCH(B$9,'Data Fields'!$9:$9,0)),0) -> FICCO Branch | E10: =IFERROR(INDEX('Data Fields'!$B:$K,MATCH($B10,'Data Fields'!$B:$B,0),MATCH(D$9,'Data Fields'!$9:$9,0)),0) -> Application for Insurance | F10: =IFERROR(INDEX('Data Fields'!$B:$K,MATCH($B10,'Data Fields'!$B:$B,0),MATCH(E$9,'Data Fields'!$9:$9,0)),0) -> DI-IN-01 | G10: =IFERROR(INDEX('Data Fields'!$B:$K,MATCH($B10,'Data Fields'!$B:$B,0),MATCH(F$9,'Data Fields'!$9:$9,0)),0) -> 0 | H10: =IFERROR(INDEX('Data Fields'!$B:$K,MATCH($B10,'Data Fields'!$B:$B,0),MATCH(G$9,'Data Fields'!$9:$9,0)),0) -> Personal Information | I10: =IFERROR(INDEX('Data Fields'!$B:$K,MATCH($B10,'Data Fields'!$B:$B,0),MATCH(H$9,'Data Fields'!$9:$9,0)),0) -> Member | J10: =IFERROR(INDEX('Data Fields'!$B:$K,MATCH($B10,'Data Fields'!$B:$B,0),MATCH(I$9,'Data Fields'!$9:$9,0)),0) -> To determine servicing branch of member | K10: =IFERROR(INDEX('Data Fields'!$B:$K,MATCH($B10,'Data Fields'!$B:$B,0),MATCH(J$9,'Data Fields'!$9:$9,0)),0) -> 0 | L10: =IFERROR(INDEX('Data Fields'!$B:$K,MATCH($B10,'Data Fields'!$B:$B,0),MATCH(K$9,'Data Fields'!$9:$9,0)),0) -> Insurance and Non-Banking Department
B11: 1974 | C11: 2 | D11: =IFERROR(INDEX('Data Fields'!$B:$K,MATCH($B11,'Data Fields'!$B:$B,0),MATCH(B$9,'Data Fields'!$9:$9,0)),0) -> Passbook Number | E11: =IFERROR(INDEX('Data Fields'!$B:$K,MATCH($B11,'Data Fields'!$B:$B,0),MATCH(D$9,'Data Fields'!$9:$9,0)),0) -> Application for Insurance | F11: =IFERROR(INDEX('Data Fields'!$B:$K,MATCH($B11,'Data Fields'!$B:$B,0),MATCH(E$9,'Data Fields'!$9:$9,0)),0) -> DI-IN-01 | G11: =IFERROR(INDEX('Data Fields'!$B:$K,MATCH($B11,'Data Fields'!$B:$B,0),MATCH(F$9,'Data Fields'!$9:$9,0)),0) -> 0 | H11: =IFERROR(INDEX('Data Fields'!$B:$K,MATCH($B11,'Data Fields'!$B:$B,0),MATCH(G$9,'Data Fields'!$9:$9,0)),0) -> Sensitive Personal Information | I11: =IFERROR(INDEX('Data Fields'!$B:$K,MATCH($B11,'Data Fields'!$B:$B,0),MATCH(H$9,'Data Fields'!$9:$9,0)),0) -> Member | J11: =IFERROR(INDEX('Data Fields'!$B:$K,MATCH($B11,'Data Fields'!$B:$B,0),MATCH(I$9,'Data Fields'!$9:$9,0)),0) -> To determine if applicant is a bona fide member | K11: =IFERROR(INDEX('Data Fields'!$B:$K,MATCH($B11,'Data Fields'!$B:$B,0),MATCH(J$9,'Data Fields'!$9:$9,0)),0) -> 0 | L11: =IFERROR(INDEX('Data Fields'!$B:$K,MATCH($B11,'Data Fields'!$B:$B,0),MATCH(K$9,'Data Fields'!$9:$9,0)),0) -> Insurance and Non-Banking Department
B12: 1975 | C12: 3 | D12: =IFERROR(INDEX('Data Fields'!$B:$K,MATCH($B12,'Data Fields'!$B:$B,0),MATCH(B$9,'Data Fields'!$9:$9,0)),0) -> Date or Year of Membership | E12: =IFERROR(INDEX('Data Fields'!$B:$K,MATCH($B12,'Data Fields'!$B:$B,0),MATCH(D$9,'Data Fields'!$9:$9,0)),0) -> Application for Insurance | F12: =IFERROR(INDEX('Data Fields'!$B:$K,MATCH($B12,'Data Fields'!$B:$B,0),MATCH(E$9,'Data Fields'!$9:$9,0)),0) -> DI-IN-01 | G12: =IFERROR(INDEX('Data Fields'!$B:$K,MATCH($B12,'Data Fields'!$B:$B,0),MATCH(F$9,'Data Fields'!$9:$9,0)),0) -> 0 | H12: =IFERROR(INDEX('Data Fields'!$B:$K,MATCH($B12,'Data Fields'!$B:$B,0),MATCH(G$9,'Data Fields'!$9:$9,0)),0) -> Personal Information | I12: =IFERROR(INDEX('Data Fields'!$B:$K,MATCH($B12,'Data Fields'!$B:$B,0),MATCH(H$9,'Data Fields'!$9:$9,0)),0) -> Member | J12: =IFERROR(INDEX('Data Fields'!$B:$K,MATCH($B12,'Data Fields'!$B:$B,0),MATCH(I$9,'Data Fields'!$9:$9,0)),0) -> To determine if applicant is qualified to apply for insurance | K12: =IFERROR(INDEX('Data Fields'!$B:$K,MATCH($B12,'Data Fields'!$B:$B,0),MATCH(J$9,'Data Fields'!$9:$9,0)),0) -> 0 | L12: =IFERROR(INDEX('Data Fields'!$B:$K,MATCH($B12,'Data Fields'!$B:$B,0),MATCH(K$9,'Data Fields'!$9:$9,0)),0) -> Insurance and Non-Banking Department
B13: 1976 | C13: 4 | D13: =IFERROR(INDEX('Data Fields'!$B:$K,MATCH($B13,'Data Fields'!$B:$B,0),MATCH(B$9,'Data Fields'!$9:$9,0)),0) -> Name of other Coop you are a member of | E13: =IFERROR(INDEX('Data Fields'!$B:$K,MATCH($B13,'Data Fields'!$B:$B,0),MATCH(D$9,'Data Fields'!$9:$9,0)),0) -> Application for Insurance | F13: =IFERROR(INDEX('Data Fields'!$B:$K,MATCH($B13,'Data Fields'!$B:$B,0),MATCH(E$9,'Data Fields'!$9:$9,0)),0) -> DI-IN-01 | G13: =IFERROR(INDEX('Data Fields'!$B:$K,MATCH($B13,'Data Fields'!$B:$B,0),MATCH(F$9,'Data Fields'!$9:$9,0)),0) -> 0 | H13: =IFERROR(INDEX('Data Fields'!$B:$K,MATCH($B13,'Data Fields'!$B:$B,0),MATCH(G$9,'Data Fields'!$9:$9,0)),0) -> Sensitive Personal Information | I13: =IFERROR(INDEX('Data Fields'!$B:$K,MATCH($B13,'Data Fields'!$B:$B,0),MATCH(H$9,'Data Fields'!$9:$9,0)),0) -> Member | J13: =IFERROR(INDEX('Data Fields'!$B:$K,MATCH($B13,'Data Fields'!$B:$B,0),MATCH(I$9,'Data Fields'!$9:$9,0)),0) -> To determine other insurance policies the applicant has taken | K13: =IFERROR(INDEX('Data Fields'!$B:$K,MATCH($B13,'Data Fields'!$B:$B,0),MATCH(J$9,'Data Fields'!$9:$9,0)),0) -> 0 | L13: =IFERROR(INDEX('Data Fields'!$B:$K,MATCH($B13,'Data Fields'!$B:$B,0),MATCH(K$9,'Data Fields'!$9:$9,0)),0) -> Insurance and Non-Banking Department
B14: 1977 | C14: 5 | D14: =IFERROR(INDEX('Data Fields'!$B:$K,MATCH($B14,'Data Fields'!$B:$B,0),MATCH(B$9,'Data Fields'!$9:$9,0)),0) -> Last Name | E14: =IFERROR(INDEX('Data Fields'!$B:$K,MATCH($B14,'Data Fields'!$B:$B,0),MATCH(D$9,'Data Fields'!$9:$9,0)),0) -> Application for Insurance | F14: =IFERROR(INDEX('Data Fields'!$B:$K,MATCH($B14,'Data Fields'!$B:$B,0),MATCH(E$9,'Data Fields'!$9:$9,0)),0) -> DI-IN-01 | G14: =IFERROR(INDEX('Data Fields'!$B:$K,MATCH($B14,'Data Fields'!$B:$B,0),MATCH(F$9,'Data Fields'!$9:$9,0)),0) -> 0 | H14: =IFERROR(INDEX('Data Fields'!$B:$K,MATCH($B14,'Data Fields'!$B:$B,0),MATCH(G$9,'Data Fields'!$9:$9,0)),0) -> Personal Information | I14: =IFERROR(INDEX('Data Fields'!$B:$K,MATCH($B14,'Data Fields'!$B:$B,0),MATCH(H$9,'Data Fields'!$9:$9,0)),0) -> Member | J14: =IFERROR(INDEX('Data Fields'!$B:$K,MATCH($B14,'Data Fields'!$B:$B,0),MATCH(I$9,'Data Fields'!$9:$9,0)),0) -> To determine last name of applicant | K14: =IFERROR(INDEX('Data Fields'!$B:$K,MATCH($B14,'Data Fields'!$B:$B,0),MATCH(J$9,'Data Fields'!$9:$9,0)),0) -> 0 | L14: =IFERROR(INDEX('Data Fields'!$B:$K,MATCH($B14,'Data Fields'!$B:$B,0),MATCH(K$9,'Data Fields'!$9:$9,0)),0) -> Insurance and Non-Banking Department
B15: 1978 | C15: 6 | D15: =IFERROR(INDEX('Data Fields'!$B:$K,MATCH($B15,'Data Fields'!$B:$B,0),MATCH(B$9,'Data Fields'!$9:$9,0)),0) -> First Name | E15: =IFERROR(INDEX('Data Fields'!$B:$K,MATCH($B15,'Data Fields'!$B:$B,0),MATCH(D$9,'Data Fields'!$9:$9,0)),0) -> Application for Insurance | F15: =IFERROR(INDEX('Data Fields'!$B:$K,MATCH($B15,'Data Fields'!$B:$B,0),MATCH(E$9,'Data Fields'!$9:$9,0)),0) -> DI-IN-01 | G15: =IFERROR(INDEX('Data Fields'!$B:$K,MATCH($B15,'Data Fields'!$B:$B,0),MATCH(F$9,'Data Fields'!$9:$9,0)),0) -> 0 | H15: =IFERROR(INDEX('Data Fields'!$B:$K,MATCH($B15,'Data Fields'!$B:$B,0),MATCH(G$9,'Data Fields'!$9:$9,0)),0) -> Personal Information | I15: =IFERROR(INDEX('Data Fields'!$B:$K,MATCH($B15,'Data Fields'!$B:$B,0),MATCH(H$9,'Data Fields'!$9:$9,0)),0) -> Member | J15: =IFERROR(INDEX('Data Fields'!$B:$K,MATCH($B15,'Data Fields'!$B:$B,0),MATCH(I$9,'Data Fields'!$9:$9,0)),0) -> To determine first name of applicant | K15: =IFERROR(INDEX('Data Fields'!$B:$K,MATCH($B15,'Data Fields'!$B:$B,0),MATCH(J$9,'Data Fields'!$9:$9,0)),0) -> 0 | L15: =IFERROR(INDEX('Data Fields'!$B:$K,MATCH($B15,'Data Fields'!$B:$B,0),MATCH(K$9,'Data Fields'!$9:$9,0)),0) -> Insurance and Non-Banking Department
B16: 1979 | C16: 7 | D16: =IFERROR(INDEX('Data Fields'!$B:$K,MATCH($B16,'Data Fields'!$B:$B,0),MATCH(B$9,'Data Fields'!$9:$9,0)),0) -> Middle Name | E16: =IFERROR(INDEX('Data Fields'!$B:$K,MATCH($B16,'Data Fields'!$B:$B,0),MATCH(D$9,'Data Fields'!$9:$9,0)),0) -> Application for Insurance | F16: =IFERROR(INDEX('Data Fields'!$B:$K,MATCH($B16,'Data Fields'!$B:$B,0),MATCH(E$9,'Data Fields'!$9:$9,0)),0) -> DI-IN-01 | G16: =IFERROR(INDEX('Data Fields'!$B:$K,MATCH($B16,'Data Fields'!$B:$B,0),MATCH(F$9,'Data Fields'!$9:$9,0)),0) -> 0 | H16: =IFERROR(INDEX('Data Fields'!$B:$K,MATCH($B16,'Data Fields'!$B:$B,0),MATCH(G$9,'Data Fields'!$9:$9,0)),0) -> Personal Information | I16: =IFERROR(INDEX('Data Fields'!$B:$K,MATCH($B16,'Data Fields'!$B:$B,0),MATCH(H$9,'Data Fields'!$9:$9,0)),0) -> Member | J16: =IFERROR(INDEX('Data Fields'!$B:$K,MATCH($B16,'Data Fields'!$B:$B,0),MATCH(I$9,'Data Fields'!$9:$9,0)),0) -> To determine middle name of applicant | K16: =IFERROR(INDEX('Data Fields'!$B:$K,MATCH($B16,'Data Fields'!$B:$B,0),MATCH(J$9,'Data Fields'!$9:$9,0)),0) -> 0 | L16: =IFERROR(INDEX('Data Fields'!$B:$K,MATCH($B16,'Data Fields'!$B:$B,0),MATCH(K$9,'Data Fields'!$9:$9,0)),0) -> Insurance and Non-Banking Department
B17: 1980 | C17: 8 | D17: =IFERROR(INDEX('Data Fields'!$B:$K,MATCH($B17,'Data Fields'!$B:$B,0),MATCH(B$9,'Data Fields'!$9:$9,0)),0) -> Residence Address [ ] Own [ ] Rented [ ] Living with rented [ ] Loan with Pag-ibig or others | E17: =IFERROR(INDEX('Data Fields'!$B:$K,MATCH($B17,'Data Fields'!$B:$B,0),MATCH(D$9,'Data Fields'!$9:$9,0)),0) -> Application for Insurance | F17: =IFERROR(INDEX('Data Fields'!$B:$K,MATCH($B17,'Data Fields'!$B:$B,0),MATCH(E$9,'Data Fields'!$9:$9,0)),0) -> DI-IN-01 | G17: =IFERROR(INDEX('Data Fields'!$B:$K,MATCH($B17,'Data Fields'!$B:$B,0),MATCH(F$9,'Data Fields'!$9:$9,0)),0) -> 0 | H17: =IFERROR(INDEX('Data Fields'!$B:$K,MATCH($B17,'Data Fields'!$B:$B,0),MATCH(G$9,'Data Fields'!$9:$9,0)),0) -> Personal Information | I17: =IFERROR(INDEX('Data Fields'!$B:$K,MATCH($B17,'Data Fields'!$B:$B,0),MATCH(H$9,'Data Fields'!$9:$9,0)),0) -> Member | J17: =IFERROR(INDEX('Data Fields'!$B:$K,MATCH($B17,'Data Fields'!$B:$B,0),MATCH(I$9,'Data Fields'!$9:$9,0)),0) -> To locate applicant | K17: =IFERROR(INDEX('Data Fields'!$B:$K,MATCH($B17,'Data Fields'!$B:$B,0),MATCH(J$9,'Data Fields'!$9:$9,0)),0) -> 0 | L17: =IFERROR(INDEX('Data Fields'!$B:$K,MATCH($B17,'Data Fields'!$B:$B,0),MATCH(K$9,'Data Fields'!$9:$9,0)),0) -> Insurance and Non-Banking Department
B18: 1981 | C18: 9 | D18: =IFERROR(INDEX('Data Fields'!$B:$K,MATCH($B18,'Data Fields'!$B:$B,0),MATCH(B$9,'Data Fields'!$9:$9,0)),0) -> Contact Numbers | E18: =IFERROR(INDEX('Data Fields'!$B:$K,MATCH($B18,'Data Fields'!$B:$B,0),MATCH(D$9,'Data Fields'!$9:$9,0)),0) -> Application for Insurance | F18: =IFERROR(INDEX('Data Fields'!$B:$K,MATCH($B18,'Data Fields'!$B:$B,0),MATCH(E$9,'Data Fields'!$9:$9,0)),0) -> DI-IN-01 | G18: =IFERROR(INDEX('Data Fields'!$B:$K,MATCH($B18,'Data Fields'!$B:$B,0),MATCH(F$9,'Data Fields'!$9:$9,0)),0) -> 0 | H18: =IFERROR(INDEX('Data Fields'!$B:$K,MATCH($B18,'Data Fields'!$B:$B,0),MATCH(G$9,'Data Fields'!$9:$9,0)),0) -> Sensitive Personal Information | I18: =IFERROR(INDEX('Data Fields'!$B:$K,MATCH($B18,'Data Fields'!$B:$B,0),MATCH(H$9,'Data Fields'!$9:$9,0)),0) -> Member | J18: =IFERROR(INDEX('Data Fields'!$B:$K,MATCH($B18,'Data Fields'!$B:$B,0),MATCH(I$9,'Data Fields'!$9:$9,0)),0) -> To contact applicant regarding application | K18: =IFERROR(INDEX('Data Fields'!$B:$K,MATCH($B18,'Data Fields'!$B:$B,0),MATCH(J$9,'Data Fields'!$9:$9,0)),0) -> 0 | L18: =IFERROR(INDEX('Data Fields'!$B:$K,MATCH($B18,'Data Fields'!$B:$B,0),MATCH(K$9,'Data Fields'!$9:$9,0)),0) -> Insurance and Non-Banking Department
B19: 1982 | C19: 10 | D19: =IFERROR(INDEX('Data Fields'!$B:$K,MATCH($B19,'Data Fields'!$B:$B,0),MATCH(B$9,'Data Fields'!$9:$9,0)),0) -> Date of Birth | E19: =IFERROR(INDEX('Data Fields'!$B:$K,MATCH($B19,'Data Fields'!$B:$B,0),MATCH(D$9,'Data Fields'!$9:$9,0)),0) -> Application for Insurance | F19: =IFERROR(INDEX('Data Fields'!$B:$K,MATCH($B19,'Data Fields'!$B:$B,0),MATCH(E$9,'Data Fields'!$9:$9,0)),0) -> DI-IN-01 | G19: =IFERROR(INDEX('Data Fields'!$B:$K,MATCH($B19,'Data Fields'!$B:$B,0),MATCH(F$9,'Data Fields'!$9:$9,0)),0) -> 0 | H19: =IFERROR(INDEX('Data Fields'!$B:$K,MATCH($B19,'Data Fields'!$B:$B,0),MATCH(G$9,'Data Fields'!$9:$9,0)),0) -> Personal Information | I19: =IFERROR(INDEX('Data Fields'!$B:$K,MATCH($B19,'Data Fields'!$B:$B,0),MATCH(H$9,'Data Fields'!$9:$9,0)),0) -> Member | J19: =IFERROR(INDEX('Data Fields'!$B:$K,MATCH($B19,'Data Fields'!$B:$B,0),MATCH(I$9,'Data Fields'!$9:$9,0)),0) -> To determine if applicant is of legal age | K19: =IFERROR(INDEX('Data Fields'!$B:$K,MATCH($B19,'Data Fields'!$B:$B,0),MATCH(J$9,'Data Fields'!$9:$9,0)),0) -> 0 | L19: =IFERROR(INDEX('Data Fields'!$B:$K,MATCH($B19,'Data Fields'!$B:$B,0),MATCH(K$9,'Data Fields'!$9:$9,0)),0) -> Insurance and Non-Banking Department
B20: 1983 | C20: 11 | D20: =IFERROR(INDEX('Data Fields'!$B:$K,MATCH($B20,'Data Fields'!$B:$B,0),MATCH(B$9,'Data Fields'!$9:$9,0)),0) -> Age | E20: =IFERROR(INDEX('Data Fields'!$B:$K,MATCH($B20,'Data Fields'!$B:$B,0),MATCH(D$9,'Data Fields'!$9:$9,0)),0) -> Application for Insurance | F20: =IFERROR(INDEX('Data Fields'!$B:$K,MATCH($B20,'Data Fields'!$B:$B,0),MATCH(E$9,'Data Fields'!$9:$9,0)),0) -> DI-IN-01 | G20: =IFERROR(INDEX('Data Fields'!$B:$K,MATCH($B20,'Data Fields'!$B:$B,0),MATCH(F$9,'Data Fields'!$9:$9,0)),0) -> 0 | H20: =IFERROR(INDEX('Data Fields'!$B:$K,MATCH($B20,'Data Fields'!$B:$B,0),MATCH(G$9,'Data Fields'!$9:$9,0)),0) -> Personal Information | I20: =IFERROR(INDEX('Data Fields'!$B:$K,MATCH($B20,'Data Fields'!$B:$B,0),MATCH(H$9,'Data Fields'!$9:$9,0)),0) -> Member | J20: =IFERROR(INDEX('Data Fields'!$B:$K,MATCH($B20,'Data Fields'!$B:$B,0),MATCH(I$9,'Data Fields'!$9:$9,0)),0) -> To determine if applicant is of legal age | K20: =IFERROR(INDEX('Data Fields'!$B:$K,MATCH($B20,'Data Fields'!$B:$B,0),MATCH(J$9,'Data Fields'!$9:$9,0)),0) -> 0 | L20: =IFERROR(INDEX('Data Fields'!$B:$K,MATCH($B20,'Data Fields'!$B:$B,0),MATCH(K$9,'Data Fields'!$9:$9,0)),0) -> Insurance and Non-Banking Department
B21: 1984 | C21: 12 | D21: =IFERROR(INDEX('Data Fields'!$B:$K,MATCH($B21,'Data Fields'!$B:$B,0),MATCH(B$9,'Data Fields'!$9:$9,0)),0) -> Place of Birth | E21: =IFERROR(INDEX('Data Fields'!$B:$K,MATCH($B21,'Data Fields'!$B:$B,0),MATCH(D$9,'Data Fields'!$9:$9,0)),0) -> Application for Insurance | F21: =IFERROR(INDEX('Data Fields'!$B:$K,MATCH($B21,'Data Fields'!$B:$B,0),MATCH(E$9,'Data Fields'!$9:$9,0)),0) -> DI-IN-01 | G21: =IFERROR(INDEX('Data Fields'!$B:$K,MATCH($B21,'Data Fields'!$B:$B,0),MATCH(F$9,'Data Fields'!$9:$9,0)),0) -> 0 | H21: =IFERROR(INDEX('Data Fields'!$B:$K,MATCH($B21,'Data Fields'!$B:$B,0),MATCH(G$9,'Data Fields'!$9:$9,0)),0) -> Personal Information | I21: =IFERROR(INDEX('Data Fields'!$B:$K,MATCH($B21,'Data Fields'!$B:$B,0),MATCH(H$9,'Data Fields'!$9:$9,0)),0) -> Member | J21: =IFERROR(INDEX('Data Fields'!$B:$K,MATCH($B21,'Data Fields'!$B:$B,0),MATCH(I$9,'Data Fields'!$9:$9,0)),0) -> To determine place of birth of applicant | K21: =IFERROR(INDEX('Data Fields'!$B:$K,MATCH($B21,'Data Fields'!$B:$B,0),MATCH(J$9,'Data Fields'!$9:$9,0)),0) -> 0 | L21: =IFERROR(INDEX('Data Fields'!$B:$K,MATCH($B21,'Data Fields'!$B:$B,0),MATCH(K$9,'Data Fields'!$9:$9,0)),0) -> Insurance and Non-Banking Department
... B400: 2363 | C400: 391 | D400: =IFERROR(INDEX('Data Fields'!$B:$K,MATCH($B400,'Data Fields'!$B:$B,0),MATCH(B$9,'Data Fields'!$9:$9,0)),0) -> Date (Confirmation of Coverage) | E400: =IFERROR(INDEX('Data Fields'!$B:$K,MATCH($B400,'Data Fields'!$B:$B,0),MATCH(D$9,'Data Fields'!$9:$9,0)),0) -> Application for Group Memorial Service Benefit | F400: =IFERROR(INDEX('Data Fields'!$B:$K,MATCH($B400,'Data Fields'!$B:$B,0),MATCH(E$9,'Data Fields'!$9:$9,0)),0) -> DI-IN-10 | G400: =IFERROR(INDEX('Data Fields'!$B:$K,MATCH($B400,'Data Fields'!$B:$B,0),MATCH(F$9,'Data Fields'!$9:$9,0)),0) -> 0 | H400: =IFERROR(INDEX('Data Fields'!$B:$K,MATCH($B400,'Data Fields'!$B:$B,0),MATCH(G$9,'Data Fields'!$9:$9,0)),0) -> Non-personal Information | I400: =IFERROR(INDEX('Data Fields'!$B:$K,MATCH($B400,'Data Fields'!$B:$B,0),MATCH(H$9,'Data Fields'!$9:$9,0)),0) -> Member | J400: =IFERROR(INDEX('Data Fields'!$B:$K,MATCH($B400,'Data Fields'!$B:$B,0),MATCH(I$9,'Data Fields'!$9:$9,0)),0) -> To ensure information is correct and accurate | K400: =IFERROR(INDEX('Data Fields'!$B:$K,MATCH($B400,'Data Fields'!$B:$B,0),MATCH(J$9,'Data Fields'!$9:$9,0)),0) -> 0 | L400: =IFERROR(INDEX('Data Fields'!$B:$K,MATCH($B400,'Data Fields'!$B:$B,0),MATCH(K$9,'Data Fields'!$9:$9,0)),0) -> Insurance and Non-Banking Department

Sheet Legal
B9: No. | C9: No.2 | D9: DATA FIELD | E9: DOCUMENT | F9: Doc Ref No. | G9: GENERIC DATA CLASSIFICATION | H9: DATA CLASSIFICATION | I9: DATA SUBJECT CATEGORY | J9: PURPOSE OF COLLECTION | K9: REMARKS | L9: DOCUMENT OWNER
B10: 2374 | C10: 1 | D10: =IFERROR(INDEX('Data Fields'!$B:$K,MATCH($B10,'Data Fields'!$B:$B,0),MATCH(B$9,'Data Fields'!$9:$9,0)),0) -> Principal | E10: =IFERROR(INDEX('Data Fields'!$B:$K,MATCH($B10,'Data Fields'!$B:$B,0),MATCH(D$9,'Data Fields'!$9:$9,0)),0) -> Final Demand Letter | F10: =IFERROR(INDEX('Data Fields'!$B:$K,MATCH($B10,'Data Fields'!$B:$B,0),MATCH(E$9,'Data Fields'!$9:$9,0)),0) -> DI-LD-01 | G10: =IFERROR(INDEX('Data Fields'!$B:$K,MATCH($B10,'Data Fields'!$B:$B,0),MATCH(F$9,'Data Fields'!$9:$9,0)),0) -> 0 | H10: =IFERROR(INDEX('Data Fields'!$B:$K,MATCH($B10,'Data Fields'!$B:$B,0),MATCH(G$9,'Data Fields'!$9:$9,0)),0) -> Personal Information | I10: =IFERROR(INDEX('Data Fields'!$B:$K,MATCH($B10,'Data Fields'!$B:$B,0),MATCH(H$9,'Data Fields'!$9:$9,0)),0) -> Member | J10: =IFERROR(INDEX('Data Fields'!$B:$K,MATCH($B10,'Data Fields'!$B:$B,0),MATCH(I$9,'Data Fields'!$9:$9,0)),0) -> To demand collection from delinquent account | K10: =IFERROR(INDEX('Data Fields'!$B:$K,MATCH($B10,'Data Fields'!$B:$B,0),MATCH(J$9,'Data Fields'!$9:$9,0)),0) -> 0 | L10: =IFERROR(INDEX('Data Fields'!$B:$K,MATCH($B10,'Data Fields'!$B:$B,0),MATCH(K$9,'Data Fields'!$9:$9,0)),0) -> Legal Department
B11: 2375 | C11: 2 | D11: =IFERROR(INDEX('Data Fields'!$B:$K,MATCH($B11,'Data Fields'!$B:$B,0),MATCH(B$9,'Data Fields'!$9:$9,0)),0) -> Co-maker | E11: =IFERROR(INDEX('Data Fields'!$B:$K,MATCH($B11,'Data Fields'!$B:$B,0),MATCH(D$9,'Data Fields'!$9:$9,0)),0) -> Final Demand Letter | F11: =IFERROR(INDEX('Data Fields'!$B:$K,MATCH($B11,'Data Fields'!$B:$B,0),MATCH(E$9,'Data Fields'!$9:$9,0)),0) -> DI-LD-01 | G11: =IFERROR(INDEX('Data Fields'!$B:$K,MATCH($B11,'Data Fields'!$B:$B,0),MATCH(F$9,'Data Fields'!$9:$9,0)),0) -> 0 | H11: =IFERROR(INDEX('Data Fields'!$B:$K,MATCH($B11,'Data Fields'!$B:$B,0),MATCH(G$9,'Data Fields'!$9:$9,0)),0) -> Personal Information | I11: =IFERROR(INDEX('Data Fields'!$B:$K,MATCH($B11,'Data Fields'!$B:$B,0),MATCH(H$9,'Data Fields'!$9:$9,0)),0) -> Member | J11: =IFERROR(INDEX('Data Fields'!$B:$K,MATCH($B11,'Data Fields'!$B:$B,0),MATCH(I$9,'Data Fields'!$9:$9,0)),0) -> To demand collection from delinquent account | K11: =IFERROR(INDEX('Data Fields'!$B:$K,MATCH($B11,'Data Fields'!$B:$B,0),MATCH(J$9,'Data Fields'!$9:$9,0)),0) -> 0 | L11: =IFERROR(INDEX('Data Fields'!$B:$K,MATCH($B11,'Data Fields'!$B:$B,0),MATCH(K$9,'Data Fields'!$9:$9,0)),0) -> Legal Department
B12: 2376 | C12: 3 | D12: =IFERROR(INDEX('Data Fields'!$B:$K,MATCH($B12,'Data Fields'!$B:$B,0),MATCH(B$9,'Data Fields'!$9:$9,0)),0) -> Loan Balance | E12: =IFERROR(INDEX('Data Fields'!$B:$K,MATCH($B12,'Data Fields'!$B:$B,0),MATCH(D$9,'Data Fields'!$9:$9,0)),0) -> Final Demand Letter | F12: =IFERROR(INDEX('Data Fields'!$B:$K,MATCH($B12,'Data Fields'!$B:$B,0),MATCH(E$9,'Data Fields'!$9:$9,0)),0) -> DI-LD-01 | G12: =IFERROR(INDEX('Data Fields'!$B:$K,MATCH($B12,'Data Fields'!$B:$B,0),MATCH(F$9,'Data Fields'!$9:$9,0)),0) -> 0 | H12: =IFERROR(INDEX('Data Fields'!$B:$K,MATCH($B12,'Data Fields'!$B:$B,0),MATCH(G$9,'Data Fields'!$9:$9,0)),0) -> Non-personal Information | I12: =IFERROR(INDEX('Data Fields'!$B:$K,MATCH($B12,'Data Fields'!$B:$B,0),MATCH(H$9,'Data Fields'!$9:$9,0)),0) -> Member | J12: =IFERROR(INDEX('Data Fields'!$B:$K,MATCH($B12,'Data Fields'!$B:$B,0),MATCH(I$9,'Data Fields'!$9:$9,0)),0) -> To demand collection from delinquent account | K12: =IFERROR(INDEX('Data Fields'!$B:$K,MATCH($B12,'Data Fields'!$B:$B,0),MATCH(J$9,'Data Fields'!$9:$9,0)),0) -> 0 | L12: =IFERROR(INDEX('Data Fields'!$B:$K,MATCH($B12,'Data Fields'!$B:$B,0),MATCH(K$9,'Data Fields'!$9:$9,0)),0) -> Legal Department
B13: 2377 | C13: 4 | D13: =IFERROR(INDEX('Data Fields'!$B:$K,MATCH($B13,'Data Fields'!$B:$B,0),MATCH(B$9,'Data Fields'!$9:$9,0)),0) -> Interest | E13: =IFERROR(INDEX('Data Fields'!$B:$K,MATCH($B13,'Data Fields'!$B:$B,0),MATCH(D$9,'Data Fields'!$9:$9,0)),0) -> Final Demand Letter | F13: =IFERROR(INDEX('Data Fields'!$B:$K,MATCH($B13,'Data Fields'!$B:$B,0),MATCH(E$9,'Data Fields'!$9:$9,0)),0) -> DI-LD-01 | G13: =IFERROR(INDEX('Data Fields'!$B:$K,MATCH($B13,'Data Fields'!$B:$B,0),MATCH(F$9,'Data Fields'!$9:$9,0)),0) -> 0 | H13: =IFERROR(INDEX('Data Fields'!$B:$K,MATCH($B13,'Data Fields'!$B:$B,0),MATCH(G$9,'Data Fields'!$9:$9,0)),0) -> Non-personal Information | I13: =IFERROR(INDEX('Data Fields'!$B:$K,MATCH($B13,'Data Fields'!$B:$B,0),MATCH(H$9,'Data Fields'!$9:$9,0)),0) -> Member | J13: =IFERROR(INDEX('Data Fields'!$B:$K,MATCH($B13,'Data Fields'!$B:$B,0),MATCH(I$9,'Data Fields'!$9:$9,0)),0) -> To demand collection from delinquent account | K13: =IFERROR(INDEX('Data Fields'!$B:$K,MATCH($B13,'Data Fields'!$B:$B,0),MATCH(J$9,'Data Fields'!$9:$9,0)),0) -> 0 | L13: =IFERROR(INDEX('Data Fields'!$B:$K,MATCH($B13,'Data Fields'!$B:$B,0),MATCH(K$9,'Data Fields'!$9:$9,0)),0) -> Legal Department
B14: 2378 | C14: 5 | D14: =IFERROR(INDEX('Data Fields'!$B:$K,MATCH($B14,'Data Fields'!$B:$B,0),MATCH(B$9,'Data Fields'!$9:$9,0)),0) -> Fines | E14: =IFERROR(INDEX('Data Fields'!$B:$K,MATCH($B14,'Data Fields'!$B:$B,0),MATCH(D$9,'Data Fields'!$9:$9,0)),0) -> Final Demand Letter | F14: =IFERROR(INDEX('Data Fields'!$B:$K,MATCH($B14,'Data Fields'!$B:$B,0),MATCH(E$9,'Data Fields'!$9:$9,0)),0) -> DI-LD-01 | G14: =IFERROR(INDEX('Data Fields'!$B:$K,MATCH($B14,'Data Fields'!$B:$B,0),MATCH(F$9,'Data Fields'!$9:$9,0)),0) -> 0 | H14: =IFERROR(INDEX('Data Fields'!$B:$K,MATCH($B14,'Data Fields'!$B:$B,0),MATCH(G$9,'Data Fields'!$9:$9,0)),0) -> Non-personal Information | I14: =IFERROR(INDEX('Data Fields'!$B:$K,MATCH($B14,'Data Fields'!$B:$B,0),MATCH(H$9,'Data Fields'!$9:$9,0)),0) -> Member | J14: =IFERROR(INDEX('Data Fields'!$B:$K,MATCH($B14,'Data Fields'!$B:$B,0),MATCH(I$9,'Data Fields'!$9:$9,0)),0) -> To demand collection from delinquent account | K14: =IFERROR(INDEX('Data Fields'!$B:$K,MATCH($B14,'Data Fields'!$B:$B,0),MATCH(J$9,'Data Fields'!$9:$9,0)),0) -> 0 | L14: =IFERROR(INDEX('Data Fields'!$B:$K,MATCH($B14,'Data Fields'!$B:$B,0),MATCH(K$9,'Data Fields'!$9:$9,0)),0) -> Legal Department
B15: 2379 | C15: 6 | D15: =IFERROR(INDEX('Data Fields'!$B:$K,MATCH($B15,'Data Fields'!$B:$B,0),MATCH(B$9,'Data Fields'!$9:$9,0)),0) -> Atty.'s Fees | E15: =IFERROR(INDEX('Data Fields'!$B:$K,MATCH($B15,'Data Fields'!$B:$B,0),MATCH(D$9,'Data Fields'!$9:$9,0)),0) -> Final Demand Letter | F15: =IFERROR(INDEX('Data Fields'!$B:$K,MATCH($B15,'Data Fields'!$B:$B,0),MATCH(E$9,'Data Fields'!$9:$9,0)),0) -> DI-LD-01 | G15: =IFERROR(INDEX('Data Fields'!$B:$K,MATCH($B15,'Data Fields'!$B:$B,0),MATCH(F$9,'Data Fields'!$9:$9,0)),0) -> 0 | H15: =IFERROR(INDEX('Data Fields'!$B:$K,MATCH($B15,'Data Fields'!$B:$B,0),MATCH(G$9,'Data Fields'!$9:$9,0)),0) -> Non-personal Information | I15: =IFERROR(INDEX('Data Fields'!$B:$K,MATCH($B15,'Data Fields'!$B:$B,0),MATCH(H$9,'Data Fields'!$9:$9,0)),0) -> Member | J15: =IFERROR(INDEX('Data Fields'!$B:$K,MATCH($B15,'Data Fields'!$B:$B,0),MATCH(I$9,'Data Fields'!$9:$9,0)),0) -> To demand collection from delinquent account | K15: =IFERROR(INDEX('Data Fields'!$B:$K,MATCH($B15,'Data Fields'!$B:$B,0),MATCH(J$9,'Data Fields'!$9:$9,0)),0) -> 0 | L15: =IFERROR(INDEX('Data Fields'!$B:$K,MATCH($B15,'Data Fields'!$B:$B,0),MATCH(K$9,'Data Fields'!$9:$9,0)),0) -> Legal Department
B16: 2380 | C16: 7 | D16: =IFERROR(INDEX('Data Fields'!$B:$K,MATCH($B16,'Data Fields'!$B:$B,0),MATCH(B$9,'Data Fields'!$9:$9,0)),0) -> Expenses | E16: =IFERROR(INDEX('Data Fields'!$B:$K,MATCH($B16,'Data Fields'!$B:$B,0),MATCH(D$9,'Data Fields'!$9:$9,0)),0) -> Final Demand Letter | F16: =IFERROR(INDEX('Data Fields'!$B:$K,MATCH($B16,'Data Fields'!$B:$B,0),MATCH(E$9,'Data Fields'!$9:$9,0)),0) -> DI-LD-01 | G16: =IFERROR(INDEX('Data Fields'!$B:$K,MATCH($B16,'Data Fields'!$B:$B,0),MATCH(F$9,'Data Fields'!$9:$9,0)),0) -> 0 | H16: =IFERROR(INDEX('Data Fields'!$B:$K,MATCH($B16,'Data Fields'!$B:$B,0),MATCH(G$9,'Data Fields'!$9:$9,0)),0) -> Non-personal Information | I16: =IFERROR(INDEX('Data Fields'!$B:$K,MATCH($B16,'Data Fields'!$B:$B,0),MATCH(H$9,'Data Fields'!$9:$9,0)),0) -> Member | J16: =IFERROR(INDEX('Data Fields'!$B:$K,MATCH($B16,'Data Fields'!$B:$B,0),MATCH(I$9,'Data Fields'!$9:$9,0)),0) -> To demand collection from delinquent account | K16: =IFERROR(INDEX('Data Fields'!$B:$K,MATCH($B16,'Data Fields'!$B:$B,0),MATCH(J$9,'Data Fields'!$9:$9,0)),0) -> 0 | L16: =IFERROR(INDEX('Data Fields'!$B:$K,MATCH($B16,'Data Fields'!$B:$B,0),MATCH(K$9,'Data Fields'!$9:$9,0)),0) -> Legal Department
B17: 2381 | C17: 8 | D17: =IFERROR(INDEX('Data Fields'!$B:$K,MATCH($B17,'Data Fields'!$B:$B,0),MATCH(B$9,'Data Fields'!$9:$9,0)),0) -> Total | E17: =IFERROR(INDEX('Data Fields'!$B:$K,MATCH($B17,'Data Fields'!$B:$B,0),MATCH(D$9,'Data Fields'!$9:$9,0)),0) -> Final Demand Letter | F17: =IFERROR(INDEX('Data Fields'!$B:$K,MATCH($B17,'Data Fields'!$B:$B,0),MATCH(E$9,'Data Fields'!$9:$9,0)),0) -> DI-LD-01 | G17: =IFERROR(INDEX('Data Fields'!$B:$K,MATCH($B17,'Data Fields'!$B:$B,0),MATCH(F$9,'Data Fields'!$9:$9,0)),0) -> 0 | H17: =IFERROR(INDEX('Data Fields'!$B:$K,MATCH($B17,'Data Fields'!$B:$B,0),MATCH(G$9,'Data Fields'!$9:$9,0)),0) -> Non-personal Information | I17: =IFERROR(INDEX('Data Fields'!$B:$K,MATCH($B17,'Data Fields'!$B:$B,0),MATCH(H$9,'Data Fields'!$9:$9,0)),0) -> Member | J17: =IFERROR(INDEX('Data Fields'!$B:$K,MATCH($B17,'Data Fields'!$B:$B,0),MATCH(I$9,'Data Fields'!$9:$9,0)),0) -> To demand collection from delinquent account | K17: =IFERROR(INDEX('Data Fields'!$B:$K,MATCH($B17,'Data Fields'!$B:$B,0),MATCH(J$9,'Data Fields'!$9:$9,0)),0) -> 0 | L17: =IFERROR(INDEX('Data Fields'!$B:$K,MATCH($B17,'Data Fields'!$B:$B,0),MATCH(K$9,'Data Fields'!$9:$9,0)),0) -> Legal Department
B18: 2382 | C18: 9 | D18: =IFERROR(INDEX('Data Fields'!$B:$K,MATCH($B18,'Data Fields'!$B:$B,0),MATCH(B$9,'Data Fields'!$9:$9,0)),0) -> Civil Case No. | E18: =IFERROR(INDEX('Data Fields'!$B:$K,MATCH($B18,'Data Fields'!$B:$B,0),MATCH(D$9,'Data Fields'!$9:$9,0)),0) -> Statement of Claim | F18: =IFERROR(INDEX('Data Fields'!$B:$K,MATCH($B18,'Data Fields'!$B:$B,0),MATCH(E$9,'Data Fields'!$9:$9,0)),0) -> DI-LD-02 | G18: =IFERROR(INDEX('Data Fields'!$B:$K,MATCH($B18,'Data Fields'!$B:$B,0),MATCH(F$9,'Data Fields'!$9:$9,0)),0) -> 0 | H18: =IFERROR(INDEX('Data Fields'!$B:$K,MATCH($B18,'Data Fields'!$B:$B,0),MATCH(G$9,'Data Fields'!$9:$9,0)),0) -> Sensitive Personal Information | I18: =IFERROR(INDEX('Data Fields'!$B:$K,MATCH($B18,'Data Fields'!$B:$B,0),MATCH(H$9,'Data Fields'!$9:$9,0)),0) -> Member | J18: =IFERROR(INDEX('Data Fields'!$B:$K,MATCH($B18,'Data Fields'!$B:$B,0),MATCH(I$9,'Data Fields'!$9:$9,0)),0) -> To fill out information for filing of case to RTC | K18: =IFERROR(INDEX('Data Fields'!$B:$K,MATCH($B18,'Data Fields'!$B:$B,0),MATCH(J$9,'Data Fields'!$9:$9,0)),0) -> RTC Form | L18: =IFERROR(INDEX('Data Fields'!$B:$K,MATCH($B18,'Data Fields'!$B:$B,0),MATCH(K$9,'Data Fields'!$9:$9,0)),0) -> Legal Department
B19: 2383 | C19: 10 | D19: =IFERROR(INDEX('Data Fields'!$B:$K,MATCH($B19,'Data Fields'!$B:$B,0),MATCH(B$9,'Data Fields'!$9:$9,0)),0) -> Name of Plantiff/s | E19: =IFERROR(INDEX('Data Fields'!$B:$K,MATCH($B19,'Data Fields'!$B:$B,0),MATCH(D$9,'Data Fields'!$9:$9,0)),0) -> Statement of Claim | F19: =IFERROR(INDEX('Data Fields'!$B:$K,MATCH($B19,'Data Fields'!$B:$B,0),MATCH(E$9,'Data Fields'!$9:$9,0)),0) -> DI-LD-02 | G19: =IFERROR(INDEX('Data Fields'!$B:$K,MATCH($B19,'Data Fields'!$B:$B,0),MATCH(F$9,'Data Fields'!$9:$9,0)),0) -> 0 | H19: =IFERROR(INDEX('Data Fields'!$B:$K,MATCH($B19,'Data Fields'!$B:$B,0),MATCH(G$9,'Data Fields'!$9:$9,0)),0) -> Personal Information | I19: =IFERROR(INDEX('Data Fields'!$B:$K,MATCH($B19,'Data Fields'!$B:$B,0),MATCH(H$9,'Data Fields'!$9:$9,0)),0) -> Member | J19: =IFERROR(INDEX('Data Fields'!$B:$K,MATCH($B19,'Data Fields'!$B:$B,0),MATCH(I$9,'Data Fields'!$9:$9,0)),0) -> To fill out information for filing of case to RTC | K19: =IFERROR(INDEX('Data Fields'!$B:$K,MATCH($B19,'Data Fields'!$B:$B,0),MATCH(J$9,'Data Fields'!$9:$9,0)),0) -> RTC Form | L19: =IFERROR(INDEX('Data Fields'!$B:$K,MATCH($B19,'Data Fields'!$B:$B,0),MATCH(K$9,'Data Fields'!$9:$9,0)),0) -> Legal Department
B20: 2384 | C20: 11 | D20: =IFERROR(INDEX('Data Fields'!$B:$K,MATCH($B20,'Data Fields'!$B:$B,0),MATCH(B$9,'Data Fields'!$9:$9,0)),0) -> Sex | E20: =IFERROR(INDEX('Data Fields'!$B:$K,MATCH($B20,'Data Fields'!$B:$B,0),MATCH(D$9,'Data Fields'!$9:$9,0)),0) -> Statement of Claim | F20: =IFERROR(INDEX('Data Fields'!$B:$K,MATCH($B20,'Data Fields'!$B:$B,0),MATCH(E$9,'Data Fields'!$9:$9,0)),0) -> DI-LD-02 | G20: =IFERROR(INDEX('Data Fields'!$B:$K,MATCH($B20,'Data Fields'!$B:$B,0),MATCH(F$9,'Data Fields'!$9:$9,0)),0) -> 0 | H20: =IFERROR(INDEX('Data Fields'!$B:$K,MATCH($B20,'Data Fields'!$B:$B,0),MATCH(G$9,'Data Fields'!$9:$9,0)),0) -> Personal Information | I20: =IFERROR(INDEX('Data Fields'!$B:$K,MATCH($B20,'Data Fields'!$B:$B,0),MATCH(H$9,'Data Fields'!$9:$9,0)),0) -> Member | J20: =IFERROR(INDEX('Data Fields'!$B:$K,MATCH($B20,'Data Fields'!$B:$B,0),MATCH(I$9,'Data Fields'!$9:$9,0)),0) -> To fill out information for filing of case to RTC | K20: =IFERROR(INDEX('Data Fields'!$B:$K,MATCH($B20,'Data Fields'!$B:$B,0),MATCH(J$9,'Data Fields'!$9:$9,0)),0) -> RTC Form | L20: =IFERROR(INDEX('Data Fields'!$B:$K,MATCH($B20,'Data Fields'!$B:$B,0),MATCH(K$9,'Data Fields'!$9:$9,0)),0) -> Legal Department
B21: 2385 | C21: 12 | D21: =IFERROR(INDEX('Data Fields'!$B:$K,MATCH($B21,'Data Fields'!$B:$B,0),MATCH(B$9,'Data Fields'!$9:$9,0)),0) -> Age | E21: =IFERROR(INDEX('Data Fields'!$B:$K,MATCH($B21,'Data Fields'!$B:$B,0),MATCH(D$9,'Data Fields'!$9:$9,0)),0) -> Statement of Claim | F21: =IFERROR(INDEX('Data Fields'!$B:$K,MATCH($B21,'Data Fields'!$B:$B,0),MATCH(E$9,'Data Fields'!$9:$9,0)),0) -> DI-LD-02 | G21: =IFERROR(INDEX('Data Fields'!$B:$K,MATCH($B21,'Data Fields'!$B:$B,0),MATCH(F$9,'Data Fields'!$9:$9,0)),0) -> 0 | H21: =IFERROR(INDEX('Data Fields'!$B:$K,MATCH($B21,'Data Fields'!$B:$B,0),MATCH(G$9,'Data Fields'!$9:$9,0)),0) -> Personal Information | I21: =IFERROR(INDEX('Data Fields'!$B:$K,MATCH($B21,'Data Fields'!$B:$B,0),MATCH(H$9,'Data Fields'!$9:$9,0)),0) -> Member | J21: =IFERROR(INDEX('Data Fields'!$B:$K,MATCH($B21,'Data Fields'!$B:$B,0),MATCH(I$9,'Data Fields'!$9:$9,0)),0) -> To fill out information for filing of case to RTC | K21: =IFERROR(INDEX('Data Fields'!$B:$K,MATCH($B21,'Data Fields'!$B:$B,0),MATCH(J$9,'Data Fields'!$9:$9,0)),0) -> RTC Form | L21: =IFERROR(INDEX('Data Fields'!$B:$K,MATCH($B21,'Data Fields'!$B:$B,0),MATCH(K$9,'Data Fields'!$9:$9,0)),0) -> Legal Department
... B99: 2463 | C99: 90 | D99: =IFERROR(INDEX('Data Fields'!$B:$K,MATCH($B99,'Data Fields'!$B:$B,0),MATCH(B$9,'Data Fields'!$9:$9,0)),0) -> Computed by: Accountant | E99: =IFERROR(INDEX('Data Fields'!$B:$K,MATCH($B99,'Data Fields'!$B:$B,0),MATCH(D$9,'Data Fields'!$9:$9,0)),0) -> Statement of Account | F99: =IFERROR(INDEX('Data Fields'!$B:$K,MATCH($B99,'Data Fields'!$B:$B,0),MATCH(E$9,'Data Fields'!$9:$9,0)),0) -> DI-LD-03 | G99: =IFERROR(INDEX('Data Fields'!$B:$K,MATCH($B99,'Data Fields'!$B:$B,0),MATCH(F$9,'Data Fields'!$9:$9,0)),0) -> 0 | H99: =IFERROR(INDEX('Data Fields'!$B:$K,MATCH($B99,'Data Fields'!$B:$B,0),MATCH(G$9,'Data Fields'!$9:$9,0)),0) -> Sensitive Personal Information | I99: =IFERROR(INDEX('Data Fields'!$B:$K,MATCH($B99,'Data Fields'!$B:$B,0),MATCH(H$9,'Data Fields'!$9:$9,0)),0) -> Member | J99: =IFERROR(INDEX('Data Fields'!$B:$K,MATCH($B99,'Data Fields'!$B:$B,0),MATCH(I$9,'Data Fields'!$9:$9,0)),0) -> Required details for filing of case to RTC | K99: =IFERROR(INDEX('Data Fields'!$B:$K,MATCH($B99,'Data Fields'!$B:$B,0),MATCH(J$9,'Data Fields'!$9:$9,0)),0) -> 0 | L99: =IFERROR(INDEX('Data Fields'!$B:$K,MATCH($B99,'Data Fields'!$B:$B,0),MATCH(K$9,'Data Fields'!$9:$9,0)),0) -> Legal Department

Sheet Admin
B9: No. | C9: DATA FIELD | D9: DOCUMENT | E9: Doc Ref No. | F9: GENERIC DATA CLASSIFICATION | G9: DATA CLASSIFICATION | H9: DATA SUBJECT CATEGORY | I9: PURPOSE OF COLLECTION | J9: REMARKS | K9: DOCUMENT OWNER
B10: 2464 | C10: =IFERROR(INDEX('Data Fields'!$B:$K,MATCH($B10,'Data Fields'!$B:$B,0),MATCH(B$9,'Data Fields'!$9:$9,0)),0) -> Date | D10: =IFERROR(INDEX('Data Fields'!$B:$K,MATCH($B10,'Data Fields'!$B:$B,0),MATCH(C$9,'Data Fields'!$9:$9,0)),0) -> Visitors' Logbook | E10: =IFERROR(INDEX('Data Fields'!$B:$K,MATCH($B10,'Data Fields'!$B:$B,0),MATCH(D$9,'Data Fields'!$9:$9,0)),0) -> DI-AD-01 | F10: =IFERROR(INDEX('Data Fields'!$B:$K,MATCH($B10,'Data Fields'!$B:$B,0),MATCH(E$9,'Data Fields'!$9:$9,0)),0) -> 0 | G10: =IFERROR(INDEX('Data Fields'!$B:$K,MATCH($B10,'Data Fields'!$B:$B,0),MATCH(F$9,'Data Fields'!$9:$9,0)),0) -> Personal Information | H10: =IFERROR(INDEX('Data Fields'!$B:$K,MATCH($B10,'Data Fields'!$B:$B,0),MATCH(G$9,'Data Fields'!$9:$9,0)),0) -> Visitors | I10: =IFERROR(INDEX('Data Fields'!$B:$K,MATCH($B10,'Data Fields'!$B:$B,0),MATCH(H$9,'Data Fields'!$9:$9,0)),0) -> To determine the date | J10: =IFERROR(INDEX('Data Fields'!$B:$K,MATCH($B10,'Data Fields'!$B:$B,0),MATCH(I$9,'Data Fields'!$9:$9,0)),0) -> 0 | K10: =IFERROR(INDEX('Data Fields'!$B:$K,MATCH($B10,'Data Fields'!$B:$B,0),MATCH(J$9,'Data Fields'!$9:$9,0)),0) -> Administrative department
B11: 2465 | C11: =IFERROR(INDEX('Data Fields'!$B:$K,MATCH($B11,'Data Fields'!$B:$B,0),MATCH(B$9,'Data Fields'!$9:$9,0)),0) -> Time in | D11: =IFERROR(INDEX('Data Fields'!$B:$K,MATCH($B11,'Data Fields'!$B:$B,0),MATCH(C$9,'Data Fields'!$9:$9,0)),0) -> Visitors' Logbook | E11: =IFERROR(INDEX('Data Fields'!$B:$K,MATCH($B11,'Data Fields'!$B:$B,0),MATCH(D$9,'Data Fields'!$9:$9,0)),0) -> DI-AD-01 | F11: =IFERROR(INDEX('Data Fields'!$B:$K,MATCH($B11,'Data Fields'!$B:$B,0),MATCH(E$9,'Data Fields'!$9:$9,0)),0) -> 0 | G11: =IFERROR(INDEX('Data Fields'!$B:$K,MATCH($B11,'Data Fields'!$B:$B,0),MATCH(F$9,'Data Fields'!$9:$9,0)),0) -> Personal Information | H11: =IFERROR(INDEX('Data Fields'!$B:$K,MATCH($B11,'Data Fields'!$B:$B,0),MATCH(G$9,'Data Fields'!$9:$9,0)),0) -> Visitors | I11: =IFERROR(INDEX('Data Fields'!$B:$K,MATCH($B11,'Data Fields'!$B:$B,0),MATCH(H$9,'Data Fields'!$9:$9,0)),0) -> To determine the time in of the visitor | J11: =IFERROR(INDEX('Data Fields'!$B:$K,MATCH($B11,'Data Fields'!$B:$B,0),MATCH(I$9,'Data Fields'!$9:$9,0)),0) -> 0 | K11: =IFERROR(INDEX('Data Fields'!$B:$K,MATCH($B11,'Data Fields'!$B:$B,0),MATCH(J$9,'Data Fields'!$9:$9,0)),0) -> Administrative department
B12: 2466 | C12: =IFERROR(INDEX('Data Fields'!$B:$K,MATCH($B12,'Data Fields'!$B:$B,0),MATCH(B$9,'Data Fields'!$9:$9,0)),0) -> Name | D12: =IFERROR(INDEX('Data Fields'!$B:$K,MATCH($B12,'Data Fields'!$B:$B,0),MATCH(C$9,'Data Fields'!$9:$9,0)),0) -> Visitors' Logbook | E12: =IFERROR(INDEX('Data Fields'!$B:$K,MATCH($B12,'Data Fields'!$B:$B,0),MATCH(D$9,'Data Fields'!$9:$9,0)),0) -> DI-AD-01 | F12: =IFERROR(INDEX('Data Fields'!$B:$K,MATCH($B12,'Data Fields'!$B:$B,0),MATCH(E$9,'Data Fields'!$9:$9,0)),0) -> 0 | G12: =IFERROR(INDEX('Data Fields'!$B:$K,MATCH($B12,'Data Fields'!$B:$B,0),MATCH(F$9,'Data Fields'!$9:$9,0)),0) -> Personal Information | H12: =IFERROR(INDEX('Data Fields'!$B:$K,MATCH($B12,'Data Fields'!$B:$B,0),MATCH(G$9,'Data Fields'!$9:$9,0)),0) -> Visitors | I12: =IFERROR(INDEX('Data Fields'!$B:$K,MATCH($B12,'Data Fields'!$B:$B,0),MATCH(H$9,'Data Fields'!$9:$9,0)),0) -> To determine the name of the visitor | J12: =IFERROR(INDEX('Data Fields'!$B:$K,MATCH($B12,'Data Fields'!$B:$B,0),MATCH(I$9,'Data Fields'!$9:$9,0)),0) -> 0 | K12: =IFERROR(INDEX('Data Fields'!$B:$K,MATCH($B12,'Data Fields'!$B:$B,0),MATCH(J$9,'Data Fields'!$9:$9,0)),0) -> Administrative department
B13: 2467 | C13: =IFERROR(INDEX('Data Fields'!$B:$K,MATCH($B13,'Data Fields'!$B:$B,0),MATCH(B$9,'Data Fields'!$9:$9,0)),0) -> Purpose | D13: =IFERROR(INDEX('Data Fields'!$B:$K,MATCH($B13,'Data Fields'!$B:$B,0),MATCH(C$9,'Data Fields'!$9:$9,0)),0) -> Visitors' Logbook | E13: =IFERROR(INDEX('Data Fields'!$B:$K,MATCH($B13,'Data Fields'!$B:$B,0),MATCH(D$9,'Data Fields'!$9:$9,0)),0) -> DI-AD-01 | F13: =IFERROR(INDEX('Data Fields'!$B:$K,MATCH($B13,'Data Fields'!$B:$B,0),MATCH(E$9,'Data Fields'!$9:$9,0)),0) -> 0 | G13: =IFERROR(INDEX('Data Fields'!$B:$K,MATCH($B13,'Data Fields'!$B:$B,0),MATCH(F$9,'Data Fields'!$9:$9,0)),0) -> Personal Information | H13: =IFERROR(INDEX('Data Fields'!$B:$K,MATCH($B13,'Data Fields'!$B:$B,0),MATCH(G$9,'Data Fields'!$9:$9,0)),0) -> Visitors | I13: =IFERROR(INDEX('Data Fields'!$B:$K,MATCH($B13,'Data Fields'!$B:$B,0),MATCH(H$9,'Data Fields'!$9:$9,0)),0) -> To determine the purpose of the visit | J13: =IFERROR(INDEX('Data Fields'!$B:$K,MATCH($B13,'Data Fields'!$B:$B,0),MATCH(I$9,'Data Fields'!$9:$9,0)),0) -> 0 | K13: =IFERROR(INDEX('Data Fields'!$B:$K,MATCH($B13,'Data Fields'!$B:$B,0),MATCH(J$9,'Data Fields'!$9:$9,0)),0) -> Administrative department
B14: 2468 | C14: =IFERROR(INDEX('Data Fields'!$B:$K,MATCH($B14,'Data Fields'!$B:$B,0),MATCH(B$9,'Data Fields'!$9:$9,0)),0) -> Time out | D14: =IFERROR(INDEX('Data Fields'!$B:$K,MATCH($B14,'Data Fields'!$B:$B,0),MATCH(C$9,'Data Fields'!$9:$9,0)),0) -> Visitors' Logbook | E14: =IFERROR(INDEX('Data Fields'!$B:$K,MATCH($B14,'Data Fields'!$B:$B,0),MATCH(D$9,'Data Fields'!$9:$9,0)),0) -> DI-AD-01 | F14: =IFERROR(INDEX('Data Fields'!$B:$K,MATCH($B14,'Data Fields'!$B:$B,0),MATCH(E$9,'Data Fields'!$9:$9,0)),0) -> 0 | G14: =IFERROR(INDEX('Data Fields'!$B:$K,MATCH($B14,'Data Fields'!$B:$B,0),MATCH(F$9,'Data Fields'!$9:$9,0)),0) -> Personal Information | H14: =IFERROR(INDEX('Data Fields'!$B:$K,MATCH($B14,'Data Fields'!$B:$B,0),MATCH(G$9,'Data Fields'!$9:$9,0)),0) -> Visitors | I14: =IFERROR(INDEX('Data Fields'!$B:$K,MATCH($B14,'Data Fields'!$B:$B,0),MATCH(H$9,'Data Fields'!$9:$9,0)),0) -> To determine the time out of the visitor | J14: =IFERROR(INDEX('Data Fields'!$B:$K,MATCH($B14,'Data Fields'!$B:$B,0),MATCH(I$9,'Data Fields'!$9:$9,0)),0) -> 0 | K14: =IFERROR(INDEX('Data Fields'!$B:$K,MATCH($B14,'Data Fields'!$B:$B,0),MATCH(J$9,'Data Fields'!$9:$9,0)),0) -> Administrative department
B15: 2469 | C15: =IFERROR(INDEX('Data Fields'!$B:$K,MATCH($B15,'Data Fields'!$B:$B,0),MATCH(B$9,'Data Fields'!$9:$9,0)),0) -> Signature | D15: =IFERROR(INDEX('Data Fields'!$B:$K,MATCH($B15,'Data Fields'!$B:$B,0),MATCH(C$9,'Data Fields'!$9:$9,0)),0) -> Visitors' Logbook | E15: =IFERROR(INDEX('Data Fields'!$B:$K,MATCH($B15,'Data Fields'!$B:$B,0),MATCH(D$9,'Data Fields'!$9:$9,0)),0) -> DI-AD-01 | F15: =IFERROR(INDEX('Data Fields'!$B:$K,MATCH($B15,'Data Fields'!$B:$B,0),MATCH(E$9,'Data Fields'!$9:$9,0)),0) -> 0 | G15: =IFERROR(INDEX('Data Fields'!$B:$K,MATCH($B15,'Data Fields'!$B:$B,0),MATCH(F$9,'Data Fields'!$9:$9,0)),0) -> Sensitive Personal Information | H15: =IFERROR(INDEX('Data Fields'!$B:$K,MATCH($B15,'Data Fields'!$B:$B,0),MATCH(G$9,'Data Fields'!$9:$9,0)),0) -> Visitors | I15: =IFERROR(INDEX('Data Fields'!$B:$K,MATCH($B15,'Data Fields'!$B:$B,0),MATCH(H$9,'Data Fields'!$9:$9,0)),0) -> To determine the signature of the visitor | J15: =IFERROR(INDEX('Data Fields'!$B:$K,MATCH($B15,'Data Fields'!$B:$B,0),MATCH(I$9,'Data Fields'!$9:$9,0)),0) -> 0 | K15: =IFERROR(INDEX('Data Fields'!$B:$K,MATCH($B15,'Data Fields'!$B:$B,0),MATCH(J$9,'Data Fields'!$9:$9,0)),0) -> Administrative department
B16: 2470 | C16: =IFERROR(INDEX('Data Fields'!$B:$K,MATCH($B16,'Data Fields'!$B:$B,0),MATCH(B$9,'Data Fields'!$9:$9,0)),0) -> Date | D16: =IFERROR(INDEX('Data Fields'!$B:$K,MATCH($B16,'Data Fields'!$B:$B,0),MATCH(C$9,'Data Fields'!$9:$9,0)),0) -> Vault Logbook | E16: =IFERROR(INDEX('Data Fields'!$B:$K,MATCH($B16,'Data Fields'!$B:$B,0),MATCH(D$9,'Data Fields'!$9:$9,0)),0) -> DI-AD-02 | F16: =IFERROR(INDEX('Data Fields'!$B:$K,MATCH($B16,'Data Fields'!$B:$B,0),MATCH(E$9,'Data Fields'!$9:$9,0)),0) -> 0 | G16: =IFERROR(INDEX('Data Fields'!$B:$K,MATCH($B16,'Data Fields'!$B:$B,0),MATCH(F$9,'Data Fields'!$9:$9,0)),0) -> Personal Information | H16: =IFERROR(INDEX('Data Fields'!$B:$K,MATCH($B16,'Data Fields'!$B:$B,0),MATCH(G$9,'Data Fields'!$9:$9,0)),0) -> Employee | I16: =IFERROR(INDEX('Data Fields'!$B:$K,MATCH($B16,'Data Fields'!$B:$B,0),MATCH(H$9,'Data Fields'!$9:$9,0)),0) -> To determine the date of visit to the vault | J16: =IFERROR(INDEX('Data Fields'!$B:$K,MATCH($B16,'Data Fields'!$B:$B,0),MATCH(I$9,'Data Fields'!$9:$9,0)),0) -> 0 | K16: =IFERROR(INDEX('Data Fields'!$B:$K,MATCH($B16,'Data Fields'!$B:$B,0),MATCH(J$9,'Data Fields'!$9:$9,0)),0) -> Administrative department
B17: 2471 | C17: =IFERROR(INDEX('Data Fields'!$B:$K,MATCH($B17,'Data Fields'!$B:$B,0),MATCH(B$9,'Data Fields'!$9:$9,0)),0) -> Name | D17: =IFERROR(INDEX('Data Fields'!$B:$K,MATCH($B17,'Data Fields'!$B:$B,0),MATCH(C$9,'Data Fields'!$9:$9,0)),0) -> Vault Logbook | E17: =IFERROR(INDEX('Data Fields'!$B:$K,MATCH($B17,'Data Fields'!$B:$B,0),MATCH(D$9,'Data Fields'!$9:$9,0)),0) -> DI-AD-02 | F17: =IFERROR(INDEX('Data Fields'!$B:$K,MATCH($B17,'Data Fields'!$B:$B,0),MATCH(E$9,'Data Fields'!$9:$9,0)),0) -> 0 | G17: =IFERROR(INDEX('Data Fields'!$B:$K,MATCH($B17,'Data Fields'!$B:$B,0),MATCH(F$9,'Data Fields'!$9:$9,0)),0) -> Personal Information | H17: =IFERROR(INDEX('Data Fields'!$B:$K,MATCH($B17,'Data Fields'!$B:$B,0),MATCH(G$9,'Data Fields'!$9:$9,0)),0) -> Employee | I17: =IFERROR(INDEX('Data Fields'!$B:$K,MATCH($B17,'Data Fields'!$B:$B,0),MATCH(H$9,'Data Fields'!$9:$9,0)),0) -> To determine the name of the employee visited the vault | J17: =IFERROR(INDEX('Data Fields'!$B:$K,MATCH($B17,'Data Fields'!$B:$B,0),MATCH(I$9,'Data Fields'!$9:$9,0)),0) -> 0 | K17: =IFERROR(INDEX('Data Fields'!$B:$K,MATCH($B17,'Data Fields'!$B:$B,0),MATCH(J$9,'Data Fields'!$9:$9,0)),0) -> Administrative department
B18: 2472 | C18: =IFERROR(INDEX('Data Fields'!$B:$K,MATCH($B18,'Data Fields'!$B:$B,0),MATCH(B$9,'Data Fields'!$9:$9,0)),0) -> Time in | D18: =IFERROR(INDEX('Data Fields'!$B:$K,MATCH($B18,'Data Fields'!$B:$B,0),MATCH(C$9,'Data Fields'!$9:$9,0)),0) -> Vault Logbook | E18: =IFERROR(INDEX('Data Fields'!$B:$K,MATCH($B18,'Data Fields'!$B:$B,0),MATCH(D$9,'Data Fields'!$9:$9,0)),0) -> DI-AD-02 | F18: =IFERROR(INDEX('Data Fields'!$B:$K,MATCH($B18,'Data Fields'!$B:$B,0),MATCH(E$9,'Data Fields'!$9:$9,0)),0) -> 0 | G18: =IFERROR(INDEX('Data Fields'!$B:$K,MATCH($B18,'Data Fields'!$B:$B,0),MATCH(F$9,'Data Fields'!$9:$9,0)),0) -> Personal Information | H18: =IFERROR(INDEX('Data Fields'!$B:$K,MATCH($B18,'Data Fields'!$B:$B,0),MATCH(G$9,'Data Fields'!$9:$9,0)),0) -> Employee | I18: =IFERROR(INDEX('Data Fields'!$B:$K,MATCH($B18,'Data Fields'!$B:$B,0),MATCH(H$9,'Data Fields'!$9:$9,0)),0) -> To determine the time in of visit the vault | J18: =IFERROR(INDEX('Data Fields'!$B:$K,MATCH($B18,'Data Fields'!$B:$B,0),MATCH(I$9,'Data Fields'!$9:$9,0)),0) -> 0 | K18: =IFERROR(INDEX('Data Fields'!$B:$K,MATCH($B18,'Data Fields'!$B:$B,0),MATCH(J$9,'Data Fields'!$9:$9,0)),0) -> Administrative department
B19: 2473 | C19: =IFERROR(INDEX('Data Fields'!$B:$K,MATCH($B19,'Data Fields'!$B:$B,0),MATCH(B$9,'Data Fields'!$9:$9,0)),0) -> Time out | D19: =IFERROR(INDEX('Data Fields'!$B:$K,MATCH($B19,'Data Fields'!$B:$B,0),MATCH(C$9,'Data Fields'!$9:$9,0)),0) -> Vault Logbook | E19: =IFERROR(INDEX('Data Fields'!$B:$K,MATCH($B19,'Data Fields'!$B:$B,0),MATCH(D$9,'Data Fields'!$9:$9,0)),0) -> DI-AD-02 | F19: =IFERROR(INDEX('Data Fields'!$B:$K,MATCH($B19,'Data Fields'!$B:$B,0),MATCH(E$9,'Data Fields'!$9:$9,0)),0) -> 0 | G19: =IFERROR(INDEX('Data Fields'!$B:$K,MATCH($B19,'Data Fields'!$B:$B,0),MATCH(F$9,'Data Fields'!$9:$9,0)),0) -> Personal Information | H19: =IFERROR(INDEX('Data Fields'!$B:$K,MATCH($B19,'Data Fields'!$B:$B,0),MATCH(G$9,'Data Fields'!$9:$9,0)),0) -> Employee | I19: =IFERROR(INDEX('Data Fields'!$B:$K,MATCH($B19,'Data Fields'!$B:$B,0),MATCH(H$9,'Data Fields'!$9:$9,0)),0) -> To determine the time out of visit the vault | J19: =IFERROR(INDEX('Data Fields'!$B:$K,MATCH($B19,'Data Fields'!$B:$B,0),MATCH(I$9,'Data Fields'!$9:$9,0)),0) -> 0 | K19: =IFERROR(INDEX('Data Fields'!$B:$K,MATCH($B19,'Data Fields'!$B:$B,0),MATCH(J$9,'Data Fields'!$9:$9,0)),0) -> Administrative department
B20: 2474 | C20: =IFERROR(INDEX('Data Fields'!$B:$K,MATCH($B20,'Data Fields'!$B:$B,0),MATCH(B$9,'Data Fields'!$9:$9,0)),0) -> Name | D20: =IFERROR(INDEX('Data Fields'!$B:$K,MATCH($B20,'Data Fields'!$B:$B,0),MATCH(C$9,'Data Fields'!$9:$9,0)),0) -> Collector's Daily Destination Report | E20: =IFERROR(INDEX('Data Fields'!$B:$K,MATCH($B20,'Data Fields'!$B:$B,0),MATCH(D$9,'Data Fields'!$9:$9,0)),0) -> DI-AD-03 | F20: =IFERROR(INDEX('Data Fields'!$B:$K,MATCH($B20,'Data Fields'!$B:$B,0),MATCH(E$9,'Data Fields'!$9:$9,0)),0) -> 0 | G20: =IFERROR(INDEX('Data Fields'!$B:$K,MATCH($B20,'Data Fields'!$B:$B,0),MATCH(F$9,'Data Fields'!$9:$9,0)),0) -> Personal Information | H20: =IFERROR(INDEX('Data Fields'!$B:$K,MATCH($B20,'Data Fields'!$B:$B,0),MATCH(G$9,'Data Fields'!$9:$9,0)),0) -> Employee | I20: =IFERROR(INDEX('Data Fields'!$B:$K,MATCH($B20,'Data Fields'!$B:$B,0),MATCH(H$9,'Data Fields'!$9:$9,0)),0) -> To determine the name of the collector | J20: =IFERROR(INDEX('Data Fields'!$B:$K,MATCH($B20,'Data Fields'!$B:$B,0),MATCH(I$9,'Data Fields'!$9:$9,0)),0) -> 0 | K20: =IFERROR(INDEX('Data Fields'!$B:$K,MATCH($B20,'Data Fields'!$B:$B,0),MATCH(J$9,'Data Fields'!$9:$9,0)),0) -> Administrative department
B21: 2475 | C21: =IFERROR(INDEX('Data Fields'!$B:$K,MATCH($B21,'Data Fields'!$B:$B,0),MATCH(B$9,'Data Fields'!$9:$9,0)),0) -> Position | D21: =IFERROR(INDEX('Data Fields'!$B:$K,MATCH($B21,'Data Fields'!$B:$B,0),MATCH(C$9,'Data Fields'!$9:$9,0)),0) -> Collector's Daily Destination Report | E21: =IFERROR(INDEX('Data Fields'!$B:$K,MATCH($B21,'Data Fields'!$B:$B,0),MATCH(D$9,'Data Fields'!$9:$9,0)),0) -> DI-AD-03 | F21: =IFERROR(INDEX('Data Fields'!$B:$K,MATCH($B21,'Data Fields'!$B:$B,0),MATCH(E$9,'Data Fields'!$9:$9,0)),0) -> 0 | G21: =IFERROR(INDEX('Data Fields'!$B:$K,MATCH($B21,'Data Fields'!$B:$B,0),MATCH(F$9,'Data Fields'!$9:$9,0)),0) -> Personal Information | H21: =IFERROR(INDEX('Data Fields'!$B:$K,MATCH($B21,'Data Fields'!$B:$B,0),MATCH(G$9,'Data Fields'!$9:$9,0)),0) -> Employee | I21: =IFERROR(INDEX('Data Fields'!$B:$K,MATCH($B21,'Data Fields'!$B:$B,0),MATCH(H$9,'Data Fields'!$9:$9,0)),0) -> To determine the position of the collector | J21: =IFERROR(INDEX('Data Fields'!$B:$K,MATCH($B21,'Data Fields'!$B:$B,0),MATCH(I$9,'Data Fields'!$9:$9,0)),0) -> 0 | K21: =IFERROR(INDEX('Data Fields'!$B:$K,MATCH($B21,'Data Fields'!$B:$B,0),MATCH(J$9,'Data Fields'!$9:$9,0)),0) -> Administrative department
... B27: 2481 | C27: =IFERROR(INDEX('Data Fields'!$B:$K,MATCH($B27,'Data Fields'!$B:$B,0),MATCH(B$9,'Data Fields'!$9:$9,0)),0) -> Noted by (Branch Manager) | D27: =IFERROR(INDEX('Data Fields'!$B:$K,MATCH($B27,'Data Fields'!$B:$B,0),MATCH(C$9,'Data Fields'!$9:$9,0)),0) -> Collector's Daily Destination Report | E27: =IFERROR(INDEX('Data Fields'!$B:$K,MATCH($B27,'Data Fields'!$B:$B,0),MATCH(D$9,'Data Fields'!$9:$9,0)),0) -> DI-AD-03 | F27: =IFERROR(INDEX('Data Fields'!$B:$K,MATCH($B27,'Data Fields'!$B:$B,0),MATCH(E$9,'Data Fields'!$9:$9,0)),0) -> 0 | G27: =IFERROR(INDEX('Data Fields'!$B:$K,MATCH($B27,'Data Fields'!$B:$B,0),MATCH(F$9,'Data Fields'!$9:$9,0)),0) -> Sensitive Personal Information | H27: =IFERROR(INDEX('Data Fields'!$B:$K,MATCH($B27,'Data Fields'!$B:$B,0),MATCH(G$9,'Data Fields'!$9:$9,0)),0) -> Employee | I27: =IFERROR(INDEX('Data Fields'!$B:$K,MATCH($B27,'Data Fields'!$B:$B,0),MATCH(H$9,'Data Fields'!$9:$9,0)),0) -> To determine who noted the report | J27: =IFERROR(INDEX('Data Fields'!$B:$K,MATCH($B27,'Data Fields'!$B:$B,0),MATCH(I$9,'Data Fields'!$9:$9,0)),0) -> 0 | K27: =IFERROR(INDEX('Data Fields'!$B:$K,MATCH($B27,'Data Fields'!$B:$B,0),MATCH(J$9,'Data Fields'!$9:$9,0)),0) -> Administrative department

Sheet IA
B9: No. | C9: DATA FIELD | D9: DOCUMENT | E9: Doc Ref No. | F9: GENERIC DATA CLASSIFICATION | G9: DATA CLASSIFICATION | H9: DATA SUBJECT CATEGORY | I9: PURPOSE OF COLLECTION | J9: REMARKS | K9: DOCUMENT OWNER
B10: 2589 | C10: =IFERROR(INDEX('Data Fields'!$B:$K,MATCH($B10,'Data Fields'!$B:$B,0),MATCH(B$9,'Data Fields'!$9:$9,0)),0) -> Date Conducted | D10: =IFERROR(INDEX('Data Fields'!$B:$K,MATCH($B10,'Data Fields'!$B:$B,0),MATCH(C$9,'Data Fields'!$9:$9,0)),0) -> Audit Work Program | E10: =IFERROR(INDEX('Data Fields'!$B:$K,MATCH($B10,'Data Fields'!$B:$B,0),MATCH(D$9,'Data Fields'!$9:$9,0)),0) -> DI-IA-01 | F10: =IFERROR(INDEX('Data Fields'!$B:$K,MATCH($B10,'Data Fields'!$B:$B,0),MATCH(E$9,'Data Fields'!$9:$9,0)),0) -> 0 | G10: =IFERROR(INDEX('Data Fields'!$B:$K,MATCH($B10,'Data Fields'!$B:$B,0),MATCH(F$9,'Data Fields'!$9:$9,0)),0) -> Non-personal Information | H10: =IFERROR(INDEX('Data Fields'!$B:$K,MATCH($B10,'Data Fields'!$B:$B,0),MATCH(G$9,'Data Fields'!$9:$9,0)),0) -> Employee | I10: =IFERROR(INDEX('Data Fields'!$B:$K,MATCH($B10,'Data Fields'!$B:$B,0),MATCH(H$9,'Data Fields'!$9:$9,0)),0) -> To determine date of performance of procedure | J10: =IFERROR(INDEX('Data Fields'!$B:$K,MATCH($B10,'Data Fields'!$B:$B,0),MATCH(I$9,'Data Fields'!$9:$9,0)),0) -> 0 | K10: =IFERROR(INDEX('Data Fields'!$B:$K,MATCH($B10,'Data Fields'!$B:$B,0),MATCH(J$9,'Data Fields'!$9:$9,0)),0) -> Internal Audit
B11: 2590 | C11: =IFERROR(INDEX('Data Fields'!$B:$K,MATCH($B11,'Data Fields'!$B:$B,0),MATCH(B$9,'Data Fields'!$9:$9,0)),0) -> FICCO Branch/Office | D11: =IFERROR(INDEX('Data Fields'!$B:$K,MATCH($B11,'Data Fields'!$B:$B,0),MATCH(C$9,'Data Fields'!$9:$9,0)),0) -> Audit Work Program | E11: =IFERROR(INDEX('Data Fields'!$B:$K,MATCH($B11,'Data Fields'!$B:$B,0),MATCH(D$9,'Data Fields'!$9:$9,0)),0) -> DI-IA-01 | F11: =IFERROR(INDEX('Data Fields'!$B:$K,MATCH($B11,'Data Fields'!$B:$B,0),MATCH(E$9,'Data Fields'!$9:$9,0)),0) -> 0 | G11: =IFERROR(INDEX('Data Fields'!$B:$K,MATCH($B11,'Data Fields'!$B:$B,0),MATCH(F$9,'Data Fields'!$9:$9,0)),0) -> Non-personal Information | H11: =IFERROR(INDEX('Data Fields'!$B:$K,MATCH($B11,'Data Fields'!$B:$B,0),MATCH(G$9,'Data Fields'!$9:$9,0)),0) -> Employee | I11: =IFERROR(INDEX('Data Fields'!$B:$K,MATCH($B11,'Data Fields'!$B:$B,0),MATCH(H$9,'Data Fields'!$9:$9,0)),0) -> To determine branch/office being audited | J11: =IFERROR(INDEX('Data Fields'!$B:$K,MATCH($B11,'Data Fields'!$B:$B,0),MATCH(I$9,'Data Fields'!$9:$9,0)),0) -> 0 | K11: =IFERROR(INDEX('Data Fields'!$B:$K,MATCH($B11,'Data Fields'!$B:$B,0),MATCH(J$9,'Data Fields'!$9:$9,0)),0) -> Internal Audit
B12: 2591 | C12: =IFERROR(INDEX('Data Fields'!$B:$K,MATCH($B12,'Data Fields'!$B:$B,0),MATCH(B$9,'Data Fields'!$9:$9,0)),0) -> Procedures | D12: =IFERROR(INDEX('Data Fields'!$B:$K,MATCH($B12,'Data Fields'!$B:$B,0),MATCH(C$9,'Data Fields'!$9:$9,0)),0) -> Audit Work Program | E12: =IFERROR(INDEX('Data Fields'!$B:$K,MATCH($B12,'Data Fields'!$B:$B,0),MATCH(D$9,'Data Fields'!$9:$9,0)),0) -> DI-IA-01 | F12: =IFERROR(INDEX('Data Fields'!$B:$K,MATCH($B12,'Data Fields'!$B:$B,0),MATCH(E$9,'Data Fields'!$9:$9,0)),0) -> 0 | G12: =IFERROR(INDEX('Data Fields'!$B:$K,MATCH($B12,'Data Fields'!$B:$B,0),MATCH(F$9,'Data Fields'!$9:$9,0)),0) -> Non-personal Information | H12: =IFERROR(INDEX('Data Fields'!$B:$K,MATCH($B12,'Data Fields'!$B:$B,0),MATCH(G$9,'Data Fields'!$9:$9,0)),0) -> Member/Employee/Vendor | I12: =IFERROR(INDEX('Data Fields'!$B:$K,MATCH($B12,'Data Fields'!$B:$B,0),MATCH(H$9,'Data Fields'!$9:$9,0)),0) -> To determine audit procedures to perform | J12: =IFERROR(INDEX('Data Fields'!$B:$K,MATCH($B12,'Data Fields'!$B:$B,0),MATCH(I$9,'Data Fields'!$9:$9,0)),0) -> 0 | K12: =IFERROR(INDEX('Data Fields'!$B:$K,MATCH($B12,'Data Fields'!$B:$B,0),MATCH(J$9,'Data Fields'!$9:$9,0)),0) -> Internal Audit
B13: 2592 | C13: =IFERROR(INDEX('Data Fields'!$B:$K,MATCH($B13,'Data Fields'!$B:$B,0),MATCH(B$9,'Data Fields'!$9:$9,0)),0) -> Findings | D13: =IFERROR(INDEX('Data Fields'!$B:$K,MATCH($B13,'Data Fields'!$B:$B,0),MATCH(C$9,'Data Fields'!$9:$9,0)),0) -> Audit Work Program | E13: =IFERROR(INDEX('Data Fields'!$B:$K,MATCH($B13,'Data Fields'!$B:$B,0),MATCH(D$9,'Data Fields'!$9:$9,0)),0) -> DI-IA-01 | F13: =IFERROR(INDEX('Data Fields'!$B:$K,MATCH($B13,'Data Fields'!$B:$B,0),MATCH(E$9,'Data Fields'!$9:$9,0)),0) -> 0 | G13: =IFERROR(INDEX('Data Fields'!$B:$K,MATCH($B13,'Data Fields'!$B:$B,0),MATCH(F$9,'Data Fields'!$9:$9,0)),0) -> Non-personal Information | H13: =IFERROR(INDEX('Data Fields'!$B:$K,MATCH($B13,'Data Fields'!$B:$B,0),MATCH(G$9,'Data Fields'!$9:$9,0)),0) -> Member/Employee/Vendor | I13: =IFERROR(INDEX('Data Fields'!$B:$K,MATCH($B13,'Data Fields'!$B:$B,0),MATCH(H$9,'Data Fields'!$9:$9,0)),0) -> To determine audit findings | J13: =IFERROR(INDEX('Data Fields'!$B:$K,MATCH($B13,'Data Fields'!$B:$B,0),MATCH(I$9,'Data Fields'!$9:$9,0)),0) -> 0 | K13: =IFERROR(INDEX('Data Fields'!$B:$K,MATCH($B13,'Data Fields'!$B:$B,0),MATCH(J$9,'Data Fields'!$9:$9,0)),0) -> Internal Audit

Sheet AM
B9: No. | C9: DATA FIELD | D9: DOCUMENT | E9: Doc Ref No. | F9: GENERIC DATA CLASSIFICATION | G9: DATA CLASSIFICATION | H9: DATA SUBJECT CATEGORY | I9: PURPOSE OF COLLECTION | J9: REMARKS | K9: DOCUMENT OWNER
B10: 2593 | C10: =IFERROR(INDEX('Data Fields'!$B:$K,MATCH($B10,'Data Fields'!$B:$B,0),MATCH(B$9,'Data Fields'!$9:$9,0)),0) -> Name of Company/Bidder | D10: =IFERROR(INDEX('Data Fields'!$B:$K,MATCH($B10,'Data Fields'!$B:$B,0),MATCH(C$9,'Data Fields'!$9:$9,0)),0) -> Pre-Qualification Checklist | E10: =IFERROR(INDEX('Data Fields'!$B:$K,MATCH($B10,'Data Fields'!$B:$B,0),MATCH(D$9,'Data Fields'!$9:$9,0)),0) -> DI-AM-01 | F10: =IFERROR(INDEX('Data Fields'!$B:$K,MATCH($B10,'Data Fields'!$B:$B,0),MATCH(E$9,'Data Fields'!$9:$9,0)),0) -> 0 | G10: =IFERROR(INDEX('Data Fields'!$B:$K,MATCH($B10,'Data Fields'!$B:$B,0),MATCH(F$9,'Data Fields'!$9:$9,0)),0) -> Non-personal Information | H10: =IFERROR(INDEX('Data Fields'!$B:$K,MATCH($B10,'Data Fields'!$B:$B,0),MATCH(G$9,'Data Fields'!$9:$9,0)),0) -> Bidder | I10: =IFERROR(INDEX('Data Fields'!$B:$K,MATCH($B10,'Data Fields'!$B:$B,0),MATCH(H$9,'Data Fields'!$9:$9,0)),0) -> To determine if bidder is qualified to enter construction service | J10: =IFERROR(INDEX('Data Fields'!$B:$K,MATCH($B10,'Data Fields'!$B:$B,0),MATCH(I$9,'Data Fields'!$9:$9,0)),0) -> 0 | K10: =IFERROR(INDEX('Data Fields'!$B:$K,MATCH($B10,'Data Fields'!$B:$B,0),MATCH(J$9,'Data Fields'!$9:$9,0)),0) -> Asset Management
B11: 2594 | C11: =IFERROR(INDEX('Data Fields'!$B:$K,MATCH($B11,'Data Fields'!$B:$B,0),MATCH(B$9,'Data Fields'!$9:$9,0)),0) -> Business Trade Name and Principal business address | D11: =IFERROR(INDEX('Data Fields'!$B:$K,MATCH($B11,'Data Fields'!$B:$B,0),MATCH(C$9,'Data Fields'!$9:$9,0)),0) -> Pre-Qualification Checklist | E11: =IFERROR(INDEX('Data Fields'!$B:$K,MATCH($B11,'Data Fields'!$B:$B,0),MATCH(D$9,'Data Fields'!$9:$9,0)),0) -> DI-AM-01 | F11: =IFERROR(INDEX('Data Fields'!$B:$K,MATCH($B11,'Data Fields'!$B:$B,0),MATCH(E$9,'Data Fields'!$9:$9,0)),0) -> 0 | G11: =IFERROR(INDEX('Data Fields'!$B:$K,MATCH($B11,'Data Fields'!$B:$B,0),MATCH(F$9,'Data Fields'!$9:$9,0)),0) -> Non-personal Information | H11: =IFERROR(INDEX('Data Fields'!$B:$K,MATCH($B11,'Data Fields'!$B:$B,0),MATCH(G$9,'Data Fields'!$9:$9,0)),0) -> Bidder | I11: =IFERROR(INDEX('Data Fields'!$B:$K,MATCH($B11,'Data Fields'!$B:$B,0),MATCH(H$9,'Data Fields'!$9:$9,0)),0) -> To determine if bidder is qualified to enter construction service | J11: =IFERROR(INDEX('Data Fields'!$B:$K,MATCH($B11,'Data Fields'!$B:$B,0),MATCH(I$9,'Data Fields'!$9:$9,0)),0) -> 0 | K11: =IFERROR(INDEX('Data Fields'!$B:$K,MATCH($B11,'Data Fields'!$B:$B,0),MATCH(J$9,'Data Fields'!$9:$9,0)),0) -> Asset Management
B12: 2595 | C12: =IFERROR(INDEX('Data Fields'!$B:$K,MATCH($B12,'Data Fields'!$B:$B,0),MATCH(B$9,'Data Fields'!$9:$9,0)),0) -> Business permit | D12: =IFERROR(INDEX('Data Fields'!$B:$K,MATCH($B12,'Data Fields'!$B:$B,0),MATCH(C$9,'Data Fields'!$9:$9,0)),0) -> Pre-Qualification Checklist | E12: =IFERROR(INDEX('Data Fields'!$B:$K,MATCH($B12,'Data Fields'!$B:$B,0),MATCH(D$9,'Data Fields'!$9:$9,0)),0) -> DI-AM-01 | F12: =IFERROR(INDEX('Data Fields'!$B:$K,MATCH($B12,'Data Fields'!$B:$B,0),MATCH(E$9,'Data Fields'!$9:$9,0)),0) -> 0 | G12: =IFERROR(INDEX('Data Fields'!$B:$K,MATCH($B12,'Data Fields'!$B:$B,0),MATCH(F$9,'Data Fields'!$9:$9,0)),0) -> Non-personal Information | H12: =IFERROR(INDEX('Data Fields'!$B:$K,MATCH($B12,'Data Fields'!$B:$B,0),MATCH(G$9,'Data Fields'!$9:$9,0)),0) -> Bidder | I12: =IFERROR(INDEX('Data Fields'!$B:$K,MATCH($B12,'Data Fields'!$B:$B,0),MATCH(H$9,'Data Fields'!$9:$9,0)),0) -> To determine if bidder is qualified to enter construction service | J12: =IFERROR(INDEX('Data Fields'!$B:$K,MATCH($B12,'Data Fields'!$B:$B,0),MATCH(I$9,'Data Fields'!$9:$9,0)),0) -> 0 | K12: =IFERROR(INDEX('Data Fields'!$B:$K,MATCH($B12,'Data Fields'!$B:$B,0),MATCH(J$9,'Data Fields'!$9:$9,0)),0) -> Asset Management
B13: 2596 | C13: =IFERROR(INDEX('Data Fields'!$B:$K,MATCH($B13,'Data Fields'!$B:$B,0),MATCH(B$9,'Data Fields'!$9:$9,0)),0) -> SEC Registration/DTI | D13: =IFERROR(INDEX('Data Fields'!$B:$K,MATCH($B13,'Data Fields'!$B:$B,0),MATCH(C$9,'Data Fields'!$9:$9,0)),0) -> Pre-Qualification Checklist | E13: =IFERROR(INDEX('Data Fields'!$B:$K,MATCH($B13,'Data Fields'!$B:$B,0),MATCH(D$9,'Data Fields'!$9:$9,0)),0) -> DI-AM-01 | F13: =IFERROR(INDEX('Data Fields'!$B:$K,MATCH($B13,'Data Fields'!$B:$B,0),MATCH(E$9,'Data Fields'!$9:$9,0)),0) -> 0 | G13: =IFERROR(INDEX('Data Fields'!$B:$K,MATCH($B13,'Data Fields'!$B:$B,0),MATCH(F$9,'Data Fields'!$9:$9,0)),0) -> Non-personal Information | H13: =IFERROR(INDEX('Data Fields'!$B:$K,MATCH($B13,'Data Fields'!$B:$B,0),MATCH(G$9,'Data Fields'!$9:$9,0)),0) -> Bidder | I13: =IFERROR(INDEX('Data Fields'!$B:$K,MATCH($B13,'Data Fields'!$B:$B,0),MATCH(H$9,'Data Fields'!$9:$9,0)),0) -> To determine if bidder is qualified to enter construction service | J13: =IFERROR(INDEX('Data Fields'!$B:$K,MATCH($B13,'Data Fields'!$B:$B,0),MATCH(I$9,'Data Fields'!$9:$9,0)),0) -> 0 | K13: =IFERROR(INDEX('Data Fields'!$B:$K,MATCH($B13,'Data Fields'!$B:$B,0),MATCH(J$9,'Data Fields'!$9:$9,0)),0) -> Asset Management
B14: 2597 | C14: =IFERROR(INDEX('Data Fields'!$B:$K,MATCH($B14,'Data Fields'!$B:$B,0),MATCH(B$9,'Data Fields'!$9:$9,0)),0) -> Certificate of Registration from BIR | D14: =IFERROR(INDEX('Data Fields'!$B:$K,MATCH($B14,'Data Fields'!$B:$B,0),MATCH(C$9,'Data Fields'!$9:$9,0)),0) -> Pre-Qualification Checklist | E14: =IFERROR(INDEX('Data Fields'!$B:$K,MATCH($B14,'Data Fields'!$B:$B,0),MATCH(D$9,'Data Fields'!$9:$9,0)),0) -> DI-AM-01 | F14: =IFERROR(INDEX('Data Fields'!$B:$K,MATCH($B14,'Data Fields'!$B:$B,0),MATCH(E$9,'Data Fields'!$9:$9,0)),0) -> 0 | G14: =IFERROR(INDEX('Data Fields'!$B:$K,MATCH($B14,'Data Fields'!$B:$B,0),MATCH(F$9,'Data Fields'!$9:$9,0)),0) -> Non-personal Information | H14: =IFERROR(INDEX('Data Fields'!$B:$K,MATCH($B14,'Data Fields'!$B:$B,0),MATCH(G$9,'Data Fields'!$9:$9,0)),0) -> Bidder | I14: =IFERROR(INDEX('Data Fields'!$B:$K,MATCH($B14,'Data Fields'!$B:$B,0),MATCH(H$9,'Data Fields'!$9:$9,0)),0) -> To determine if bidder is qualified to enter construction service | J14: =IFERROR(INDEX('Data Fields'!$B:$K,MATCH($B14,'Data Fields'!$B:$B,0),MATCH(I$9,'Data Fields'!$9:$9,0)),0) -> 0 | K14: =IFERROR(INDEX('Data Fields'!$B:$K,MATCH($B14,'Data Fields'!$B:$B,0),MATCH(J$9,'Data Fields'!$9:$9,0)),0) -> Asset Management
B15: 2598 | C15: =IFERROR(INDEX('Data Fields'!$B:$K,MATCH($B15,'Data Fields'!$B:$B,0),MATCH(B$9,'Data Fields'!$9:$9,0)),0) -> Audited Financial Statement for the past 2 years | D15: =IFERROR(INDEX('Data Fields'!$B:$K,MATCH($B15,'Data Fields'!$B:$B,0),MATCH(C$9,'Data Fields'!$9:$9,0)),0) -> Pre-Qualification Checklist | E15: =IFERROR(INDEX('Data Fields'!$B:$K,MATCH($B15,'Data Fields'!$B:$B,0),MATCH(D$9,'Data Fields'!$9:$9,0)),0) -> DI-AM-01 | F15: =IFERROR(INDEX('Data Fields'!$B:$K,MATCH($B15,'Data Fields'!$B:$B,0),MATCH(E$9,'Data Fields'!$9:$9,0)),0) -> 0 | G15: =IFERROR(INDEX('Data Fields'!$B:$K,MATCH($B15,'Data Fields'!$B:$B,0),MATCH(F$9,'Data Fields'!$9:$9,0)),0) -> Non-personal Information | H15: =IFERROR(INDEX('Data Fields'!$B:$K,MATCH($B15,'Data Fields'!$B:$B,0),MATCH(G$9,'Data Fields'!$9:$9,0)),0) -> Bidder | I15: =IFERROR(INDEX('Data Fields'!$B:$K,MATCH($B15,'Data Fields'!$B:$B,0),MATCH(H$9,'Data Fields'!$9:$9,0)),0) -> To determine if bidder is qualified to enter construction service | J15: =IFERROR(INDEX('Data Fields'!$B:$K,MATCH($B15,'Data Fields'!$B:$B,0),MATCH(I$9,'Data Fields'!$9:$9,0)),0) -> 0 | K15: =IFERROR(INDEX('Data Fields'!$B:$K,MATCH($B15,'Data Fields'!$B:$B,0),MATCH(J$9,'Data Fields'!$9:$9,0)),0) -> Asset Management
B16: 2599 | C16: =IFERROR(INDEX('Data Fields'!$B:$K,MATCH($B16,'Data Fields'!$B:$B,0),MATCH(B$9,'Data Fields'!$9:$9,0)),0) -> List of Manpower (Schedule of Manpower) -to include project management team e.g. Civil Engineer, Electrical Engineer, Safety Engineer and foreman. | D16: =IFERROR(INDEX('Data Fields'!$B:$K,MATCH($B16,'Data Fields'!$B:$B,0),MATCH(C$9,'Data Fields'!$9:$9,0)),0) -> Pre-Qualification Checklist | E16: =IFERROR(INDEX('Data Fields'!$B:$K,MATCH($B16,'Data Fields'!$B:$B,0),MATCH(D$9,'Data Fields'!$9:$9,0)),0) -> DI-AM-01 | F16: =IFERROR(INDEX('Data Fields'!$B:$K,MATCH($B16,'Data Fields'!$B:$B,0),MATCH(E$9,'Data Fields'!$9:$9,0)),0) -> 0 | G16: =IFERROR(INDEX('Data Fields'!$B:$K,MATCH($B16,'Data Fields'!$B:$B,0),MATCH(F$9,'Data Fields'!$9:$9,0)),0) -> Non-personal Information | H16: =IFERROR(INDEX('Data Fields'!$B:$K,MATCH($B16,'Data Fields'!$B:$B,0),MATCH(G$9,'Data Fields'!$9:$9,0)),0) -> Bidder | I16: =IFERROR(INDEX('Data Fields'!$B:$K,MATCH($B16,'Data Fields'!$B:$B,0),MATCH(H$9,'Data Fields'!$9:$9,0)),0) -> To determine if bidder is qualified to enter construction service | J16: =IFERROR(INDEX('Data Fields'!$B:$K,MATCH($B16,'Data Fields'!$B:$B,0),MATCH(I$9,'Data Fields'!$9:$9,0)),0) -> 0 | K16: =IFERROR(INDEX('Data Fields'!$B:$K,MATCH($B16,'Data Fields'!$B:$B,0),MATCH(J$9,'Data Fields'!$9:$9,0)),0) -> Asset Management
B17: 2600 | C17: =IFERROR(INDEX('Data Fields'!$B:$K,MATCH($B17,'Data Fields'!$B:$B,0),MATCH(B$9,'Data Fields'!$9:$9,0)),0) -> List of Equipment needed related to FICCO Project | D17: =IFERROR(INDEX('Data Fields'!$B:$K,MATCH($B17,'Data Fields'!$B:$B,0),MATCH(C$9,'Data Fields'!$9:$9,0)),0) -> Pre-Qualification Checklist | E17: =IFERROR(INDEX('Data Fields'!$B:$K,MATCH($B17,'Data Fields'!$B:$B,0),MATCH(D$9,'Data Fields'!$9:$9,0)),0) -> DI-AM-01 | F17: =IFERROR(INDEX('Data Fields'!$B:$K,MATCH($B17,'Data Fields'!$B:$B,0),MATCH(E$9,'Data Fields'!$9:$9,0)),0) -> 0 | G17: =IFERROR(INDEX('Data Fields'!$B:$K,MATCH($B17,'Data Fields'!$B:$B,0),MATCH(F$9,'Data Fields'!$9:$9,0)),0) -> Non-personal Information | H17: =IFERROR(INDEX('Data Fields'!$B:$K,MATCH($B17,'Data Fields'!$B:$B,0),MATCH(G$9,'Data Fields'!$9:$9,0)),0) -> Bidder | I17: =IFERROR(INDEX('Data Fields'!$B:$K,MATCH($B17,'Data Fields'!$B:$B,0),MATCH(H$9,'Data Fields'!$9:$9,0)),0) -> To determine if bidder is qualified to enter construction service | J17: =IFERROR(INDEX('Data Fields'!$B:$K,MATCH($B17,'Data Fields'!$B:$B,0),MATCH(I$9,'Data Fields'!$9:$9,0)),0) -> 0 | K17: =IFERROR(INDEX('Data Fields'!$B:$K,MATCH($B17,'Data Fields'!$B:$B,0),MATCH(J$9,'Data Fields'!$9:$9,0)),0) -> Asset Management
B18: 2601 | C18: =IFERROR(INDEX('Data Fields'!$B:$K,MATCH($B18,'Data Fields'!$B:$B,0),MATCH(B$9,'Data Fields'!$9:$9,0)),0) -> List of On-Going and Past/Completed projects related to FICCO building constriction (with pictures) | D18: =IFERROR(INDEX('Data Fields'!$B:$K,MATCH($B18,'Data Fields'!$B:$B,0),MATCH(C$9,'Data Fields'!$9:$9,0)),0) -> Pre-Qualification Checklist | E18: =IFERROR(INDEX('Data Fields'!$B:$K,MATCH($B18,'Data Fields'!$B:$B,0),MATCH(D$9,'Data Fields'!$9:$9,0)),0) -> DI-AM-01 | F18: =IFERROR(INDEX('Data Fields'!$B:$K,MATCH($B18,'Data Fields'!$B:$B,0),MATCH(E$9,'Data Fields'!$9:$9,0)),0) -> 0 | G18: =IFERROR(INDEX('Data Fields'!$B:$K,MATCH($B18,'Data Fields'!$B:$B,0),MATCH(F$9,'Data Fields'!$9:$9,0)),0) -> Non-personal Information | H18: =IFERROR(INDEX('Data Fields'!$B:$K,MATCH($B18,'Data Fields'!$B:$B,0),MATCH(G$9,'Data Fields'!$9:$9,0)),0) -> Bidder | I18: =IFERROR(INDEX('Data Fields'!$B:$K,MATCH($B18,'Data Fields'!$B:$B,0),MATCH(H$9,'Data Fields'!$9:$9,0)),0) -> To determine if bidder is qualified to enter construction service | J18: =IFERROR(INDEX('Data Fields'!$B:$K,MATCH($B18,'Data Fields'!$B:$B,0),MATCH(I$9,'Data Fields'!$9:$9,0)),0) -> 0 | K18: =IFERROR(INDEX('Data Fields'!$B:$K,MATCH($B18,'Data Fields'!$B:$B,0),MATCH(J$9,'Data Fields'!$9:$9,0)),0) -> Asset Management
B19: 2602 | C19: =IFERROR(INDEX('Data Fields'!$B:$K,MATCH($B19,'Data Fields'!$B:$B,0),MATCH(B$9,'Data Fields'!$9:$9,0)),0) -> Safety officer - Certificate from DOLE | D19: =IFERROR(INDEX('Data Fields'!$B:$K,MATCH($B19,'Data Fields'!$B:$B,0),MATCH(C$9,'Data Fields'!$9:$9,0)),0) -> Pre-Qualification Checklist | E19: =IFERROR(INDEX('Data Fields'!$B:$K,MATCH($B19,'Data Fields'!$B:$B,0),MATCH(D$9,'Data Fields'!$9:$9,0)),0) -> DI-AM-01 | F19: =IFERROR(INDEX('Data Fields'!$B:$K,MATCH($B19,'Data Fields'!$B:$B,0),MATCH(E$9,'Data Fields'!$9:$9,0)),0) -> 0 | G19: =IFERROR(INDEX('Data Fields'!$B:$K,MATCH($B19,'Data Fields'!$B:$B,0),MATCH(F$9,'Data Fields'!$9:$9,0)),0) -> Non-personal Information | H19: =IFERROR(INDEX('Data Fields'!$B:$K,MATCH($B19,'Data Fields'!$B:$B,0),MATCH(G$9,'Data Fields'!$9:$9,0)),0) -> Bidder | I19: =IFERROR(INDEX('Data Fields'!$B:$K,MATCH($B19,'Data Fields'!$B:$B,0),MATCH(H$9,'Data Fields'!$9:$9,0)),0) -> To determine if bidder is qualified to enter construction service | J19: =IFERROR(INDEX('Data Fields'!$B:$K,MATCH($B19,'Data Fields'!$B:$B,0),MATCH(I$9,'Data Fields'!$9:$9,0)),0) -> 0 | K19: =IFERROR(INDEX('Data Fields'!$B:$K,MATCH($B19,'Data Fields'!$B:$B,0),MATCH(J$9,'Data Fields'!$9:$9,0)),0) -> Asset Management

Sheet Documents Mapping
B2: PROVIDED DOCUMENTS MAPPING
B4: Document Name | C4: Process with Privacy Impact | D4: Included in Data Inventory? | E4: Remarks
B5: Application for Coop Loan Protection Plan (LPP) | C5: Processing of Insurance Applications | D5: Yes
B6: Personal Record Card | C6: New accounts Management | D6: Yes
B7: Application for Member's Funeral benefits | C7: Processing of Insurance Applications | D7: Yes
B8: Application for Insurance | C8: Processing of Insurance Applications | D8: Yes
B9: Application for MSCF Lay Away package | C9: Processing of Insurance Applications | D9: Yes
B10: Pre-hospitalization/Medical Loan Application | C10: Loans Processing | D10: Yes
B11: Commodity Loan Application | C11: Loans Processing | D11: Yes
B12: Petty Cash Loan Application | C12: Loans Processing | D12: Yes
B13: SM/Ororama/GC Gift Cheque Loan Application | C13: Loans Processing | D13: Yes
B14: Rice Loan Application & Promissory Note | C14: Loans Processing | D14: Yes
B15: Fuel & Lube Credit Line Application | C15: Loans Processing | D15: Yes
B16: Loan Against Deposits Application | C16: Loans Processing | D16: Yes
... B47: Internet Lease Connectivity Agreement | C47: No Impact on Data Privacy | D47: No
B48: Memorandum of Agreement-ULP | C48: No Impact on Data Privacy | D48: No | E48: Memo
B49: HR 02-2018 Force Leave Schedule | C49: No Impact on Data Privacy | D49: No
B50: HR 06-2018 Revised Withholding Tax Table | C50: No Impact on Data Privacy | D50: No | E50: Memo
B51: HR 25-2018 Housing Allowance | C51: No Impact on Data Privacy | D51: No | E51: Memo
B52: HR 37-2018 Submission of 2017 Performance Evaluation | C52: No Impact on Data Privacy | D52: No | E52: Memo
B53: HR 72-2018 Housing Subsidy | C53: No Impact on Data Privacy | D53: No | E53: Memo
B54: HR 01-2017 Implementing Guidelines for Leave Application Form | C54: No Impact on Data Privacy | D54: No | E54: Memo
B55: HR 05-2017 Human Resource Manual | C55: No Impact on Data Privacy | D55: No | E55: Memo
B56: HR 10-2017 Strict Implementation of Biometrics | C56: No Impact on Data Privacy | D56: No | E56: Memo
B57: HR 11-2017 Librenado Refusal for Promotion | C57: No Impact on Data Privacy | D57: No | E57: Memo
B58: HR 14-2017 Special Non-Working Holiday After FICCO main GA | C58: No Impact on Data Privacy | D58: No | E58: Memo
B59: HR 15-2017 Implementing Guidelines for Pool Service | C59: No Impact on Data Privacy | D59: No | E59: Memo
B60: HR 16-2017 Implementing Guidelines for Rest Day | C60: No Impact on Data Privacy | D60: No | E60: Memo
B61: HR 20-2017 mandatory Update of BIR 2305 | C61: No Impact on Data Privacy | D61: No | E61: Memo
... B70: HR 140-2017 Issuance of Certification | C70: No Impact on Data Privacy | D70: No | E70: Memo
B71: 2017 job factors rating guide | C71: No Impact on Data Privacy | D71: No
B72: RELIEVER Evaluation Form | C72: Performance Appraisal | D72: Yes
B73: attachment apprentice | C73: No Impact on Data Privacy | D73: No
B74: attachment for full-pledged | C74: No Impact on Data Privacy | D74: No
B75: attachment for prob | C75: No Impact on Data Privacy | D75: No
B76: MOA-Collins | C76: No Impact on Data Privacy | D76: No
B77: Contract-Petron | C77: No Impact on Data Privacy | D77: No
B78: Contract-Shell | C78: No Impact on Data Privacy | D78: No
B79: Sky Prepaid Distributorship Agreement | C79: No Impact on Data Privacy | D79: No
B80: SkyCable Agreement | C80: No Impact on Data Privacy | D80: No
B81: Audit Program April 2018 | C81: No Impact on Data Privacy | D81: No
B82: Audit Program May 2018 | C82: No Impact on Data Privacy | D82: No
... B91: Daily Cash Counts | C91: No Impact on Data Privacy | D91: No
B92: Teller Access Rights | C92: User Access Management | D92: NA | E92: Sample of user access rights only
B93: RSPS Interface | C93: No Impact on Data Privacy | D93: No
B94: Payroll Schedule | C94: Compensation and Benefits Management | D94: Yes
B95: Payroll Masterlist | C95: Compensation and Benefits Management | D95: Yes
B96: HRPS Concerns | C96: No Impact on Data Privacy | D96: No
B97: Database Retained since 1991 | C97: Database Management | D97: NA | E97: Sample of instance of oldest data retained in the system
B98: Bookkeeper | C98: No Impact on Data Privacy | D98: No
B99: Accountant, Head Cashier, and Dept Head Access Rights | C99: User Access Management | D99: NA | E99: Sample of user access rights only
B100: AFS Accounting System Interface | C100: No Impact on Data Privacy | D100: No
B101: Schedule of Reports per insurance type | C101: No Impact on Data Privacy | D101: No
B102: MOA-CISP | C102: No Impact on Data Privacy | D102: No
B103: Healthcare Service Agreement - CHMF | C103: No Impact on Data Privacy | D103: No
B104: CISP - New Premium Rate memo | C104: No Impact on Data Privacy | D104: No
B105: Proposed GA Resolutions | C105: No Impact on Data Privacy | D105: No
B106: EdCom Volunteer's Profile | C106: Volunteer Profiling | D106: Yes
B107: Cashier/Teller Transaction Report (Proofsheet) | C107: No Impact on Data Privacy | D107: No
B108: Cash breakdown sample | C108: No Impact on Data Privacy | D108: No
B109: Deposit pick-up authorization form | C109: No Impact on Data Privacy | D109: No
B110: Cash/check deposit slips | C110: No Impact on Data Privacy | D110: No
B111: Loan portfolio analysis (list of past due accounts) | C111: No Impact on Data Privacy | D111: No
... B144: Loan Disclosure Sheet | C144: Loans Processing | D144: Yes
B145: Request for Release form | C145: #N/A | D145: No | E145: Not yet provided
B146: Application for Group Memorial Service Benefit | C146: Processing of Insurance Applications | D146: Yes
B147: Fire Insurance Quotation | C147: Processing of Insurance Applications | D147: Yes
B148: Application for Motor Car Insurance | C148: Processing of Insurance Applications | D148: Yes
B149: Application for Withdrawal of Membership | C149: Withdrawal of membership | D149: Yes
B150: Applicant Evaluation | C150: Recruitment and Placement | D150: Yes
B151: Applicant Background Investigation Report | C151: Recruitment and Placement | D151: Yes
B152: Applicant Essay | C152: Recruitment and Placement | D152: Yes
B153: Employee Information Form | C153: Employee Master File Maintenance | D153: Yes
B154: Applicant Final Evaluation Form (Non-Supervisory) | C154: Recruitment and Placement | D154: Yes
B155: Apprenticeship Agreement | C155: Recruitment and Placement | D155: Yes
B156: Probationary Contract | C156: Recruitment and Placement | D156: Yes
B157: Regular Employment Contract | C157: Recruitment and Placement | D157: Yes
... B192: Credit Committee slip | C192: Loans Processing | D192: Yes

Sheet Document Listing
B2: Ref No. | C2: File Description | D2: Date Received | E2: Source Person | F2: Remarks
B3: 1 | C3: Application for Coop Loan Protection Plan (LPP) | D3: 43249 | E3: May Lee Ann Antoque
B4: 2 | C4: Personal Record Card | D4: 43249 | E4: May Lee Ann Antoque
B5: 3 | C5: Application for Member's Funeral benefits | D5: 43249 | E5: May Lee Ann Antoque
B6: 4 | C6: Application for Insurance | D6: 43249 | E6: May Lee Ann Antoque
B7: 5 | C7: Application for MSCF Lay Away package | D7: 43249 | E7: May Lee Ann Antoque
B8: 6 | C8: Pre-hospitalization/Medical Loan Application | D8: 43249 | E8: May Lee Ann Antoque
B9: 7 | C9: Commodity Loan Application | D9: 43249 | E9: May Lee Ann Antoque
B10: 8 | C10: Petty Cash Loan Application | D10: 43249 | E10: May Lee Ann Antoque
B11: 9 | C11: SM/Ororama/GC Gift Cheque Loan Application | D11: 43249 | E11: May Lee Ann Antoque
B12: 10 | C12: Rice Loan Application & Promissory Note | D12: 43249 | E12: May Lee Ann Antoque
B13: 11 | C13: Fuel & Lube Credit Line Application | D13: 43249 | E13: May Lee Ann Antoque
B14: 12 | C14: Loan Against Deposits Application | D14: 43249 | E14: May Lee Ann Antoque
... B182: 180 | C182: Loan Disclosure Sheet | D182: 43286 | E182: May Lee Ann Antoque

Sheet Documents Recon
B2: DOCUMENT/ FILE NAME | C2: DOCUMENT TYPE | D2: DOCUMENT OWNER
B3: Application for Coop Loan Protection Plan (LPP) | C3: Physical Form | D3: Branch Operations | E3: =VLOOKUP(B3,'Data Fields'!$D:$D,1,FALSE) -> Application for Coop Loan Protection Plan (LPP)
B4: Personal Record Card | C4: Physical Form | D4: Branch Operations | E4: =VLOOKUP(B4,'Data Fields'!$D:$D,1,FALSE) -> Personal Record Card
B5: Application for Member's Funeral benefits | C5: Physical Form | D5: Branch Operations | E5: =VLOOKUP(B5,'Data Fields'!$D:$D,1,FALSE) -> Application for Member's Funeral benefits
B6: Application for Insurance | C6: Physical Form | D6: Branch Operations | E6: =VLOOKUP(B6,'Data Fields'!$D:$D,1,FALSE) -> Application for Insurance
B7: Application for MSCF Lay Away package | C7: Physical Form | D7: Branch Operations | E7: =VLOOKUP(B7,'Data Fields'!$D:$D,1,FALSE) -> Application for MSCF Lay Away package
B8: Pre-hospitalization/Medical Loan Application | C8: Physical Form | D8: Branch Operations | E8: =VLOOKUP(B8,'Data Fields'!$D:$D,1,FALSE) -> Pre-hospitalization/Medical Loan Application
B9: Commodity Loan Application | C9: Physical Form | D9: Branch Operations | E9: =VLOOKUP(B9,'Data Fields'!$D:$D,1,FALSE) -> Commodity Loan Application
B10: Petty Cash Loan Application | C10: Physical Form | D10: Branch Operations | E10: =VLOOKUP(B10,'Data Fields'!$D:$D,1,FALSE) -> Petty Cash Loan Application
B11: SM/Ororama/GC Gift Cheque Loan Application | C11: Physical Form | D11: Branch Operations | E11: =VLOOKUP(B11,'Data Fields'!$D:$D,1,FALSE) -> SM/Ororama/GC Gift Cheque Loan Application
B12: Rice Loan Application & Promissory Note | C12: Physical Form | D12: Branch Operations | E12: =VLOOKUP(B12,'Data Fields'!$D:$D,1,FALSE) -> Rice Loan Application & Promissory Note
B13: Fuel & Lube Credit Line Application | C13: Physical Form | D13: Branch Operations | E13: =VLOOKUP(B13,'Data Fields'!$D:$D,1,FALSE) -> Fuel & Lube Credit Line Application
B14: Loan Against Deposits Application | C14: Physical Form | D14: Branch Operations | E14: =VLOOKUP(B14,'Data Fields'!$D:$D,1,FALSE) -> Loan Against Deposits Application
... B18: Co-maker's Statement | C18: Physical Form | D18: Branch Operations | E18: =VLOOKUP(B18,'Data Fields'!$D:$D,1,FALSE) -> Co-Maker's Statement
B19: HomeSECURE Application | C19: Physical Form | D19: Branch Operations | E19: =VLOOKUP(B19,'Data Fields'!$D:$D,1,FALSE) -> HomeSECURE Application | F19: Revisit why not included in the Data Fields | J19: OK
B20: Membership Application Form (CHMF) | C20: Physical Form | D20: Branch Operations | E20: =VLOOKUP(B20,'Data Fields'!$D:$D,1,FALSE) -> Membership Application Form (CHMF) | F20: Revisit why not included in the Data Fields | J20: OK
B21: Principal Member's Application Form for KOOPamilya Plan | C21: Physical Form | D21: Branch Operations | E21: =VLOOKUP(B21,'Data Fields'!$D:$D,1,FALSE) -> Principal Member's Application Form for KOOPamilya Plan | F21: Revisit why not included in the Data Fields | J21: OK
B22: Receiving Report | C22: Physical Form | D22: Accounting Department | E22: =VLOOKUP(B22,'Data Fields'!$D:$D,1,FALSE) -> Receiving Report
B23: Cash Advance Slip | C23: Physical Form | D23: Accounting Department | E23: =VLOOKUP(B23,'Data Fields'!$D:$D,1,FALSE) -> Cash Advance Slip
B24: Request for Check Issuance | C24: Physical Form | D24: Accounting Department | E24: =VLOOKUP(B24,'Data Fields'!$D:$D,1,FALSE) -> Request for Check Issuance
B25: Requisition Slip | C25: Physical Form | D25: Accounting Department | E25: =VLOOKUP(B25,'Data Fields'!$D:$D,1,FALSE) -> Requisition Slip
B26: Liquidation Voucher | C26: Physical Form | D26: Accounting Department | E26: =VLOOKUP(B26,'Data Fields'!$D:$D,1,FALSE) -> Liquidation Voucher
B27: Application for Group Memorial Service Benefit | C27: Physical Form | D27: Branch Operations | E27: =VLOOKUP(B27,'Data Fields'!$D:$D,1,FALSE) -> Application for Group Memorial Service Benefit
B28: Fire Insurance Quotation | C28: Physical Form | D28: Branch Operations | E28: =VLOOKUP(B28,'Data Fields'!$D:$D,1,FALSE) -> Fire Insurance Quotation
B29: Application for Motor Car Insurance | C29: Physical Form | D29: Branch Operations | E29: =VLOOKUP(B29,'Data Fields'!$D:$D,1,FALSE) -> Application for Motor Car Insurance
B30: Application for Withdrawal of Membership | C30: Physical Form | D30: Branch Operations | E30: =VLOOKUP(B30,'Data Fields'!$D:$D,1,FALSE) -> Application for Withdrawal of Membership
B31: Applicant Evaluation | C31: Electronic Form/Physical Form | D31: Human Resource Department | E31: =VLOOKUP(B31,'Data Fields'!$D:$D,1,FALSE) -> Applicant Evaluation
B32: Applicant Background Investigation Report | C32: Electronic Form/Physical Form | D32: Human Resource Department | E32: =VLOOKUP(B32,'Data Fields'!$D:$D,1,FALSE) -> Applicant Background Investigation Report
B33: Applicant Essay | C33: Electronic Form/Physical Form | D33: Human Resource Department | E33: =VLOOKUP(B33,'Data Fields'!$D:$D,1,FALSE) -> Applicant Essay
... B62: Client Master: Maintenance | C62: Electronic | D62: Branch Operations | E62: =VLOOKUP(B62,'Data Fields'!$D:$D,1,FALSE) -> Client Master: Maintenance

Sheet Data Fields Recon
B2: DOCUMENT | C2: DOCUMENT OWNER | D2: Included in the Documents?
B3: Application for Coop Loan Protection Plan (LPP) | C3: Branch Operations | D3: =VLOOKUP(B3,'Documents Recon'!$B:$B,1,FALSE) -> Application for Coop Loan Protection Plan (LPP)
B4: Personal Record Card | C4: Branch Operations | D4: =VLOOKUP(B4,'Documents Recon'!$B:$B,1,FALSE) -> Personal Record Card
B5: Application for Member's Funeral benefits | C5: Branch Operations | D5: =VLOOKUP(B5,'Documents Recon'!$B:$B,1,FALSE) -> Application for Member's Funeral benefits
B6: Application for Insurance | C6: Branch Operations | D6: =VLOOKUP(B6,'Documents Recon'!$B:$B,1,FALSE) -> Application for Insurance
B7: Application for MSCF Lay Away package | C7: Branch Operations | D7: =VLOOKUP(B7,'Documents Recon'!$B:$B,1,FALSE) -> Application for MSCF Lay Away package
B8: Pre-hospitalization/Medical Loan Application | C8: Branch Operations | D8: =VLOOKUP(B8,'Documents Recon'!$B:$B,1,FALSE) -> Pre-hospitalization/Medical Loan Application
B9: Commodity Loan Application | C9: Branch Operations | D9: =VLOOKUP(B9,'Documents Recon'!$B:$B,1,FALSE) -> Commodity Loan Application
B10: Petty Cash Loan Application | C10: Branch Operations | D10: =VLOOKUP(B10,'Documents Recon'!$B:$B,1,FALSE) -> Petty Cash Loan Application
B11: SM/Ororama/GC Gift Cheque Loan Application | C11: Branch Operations | D11: =VLOOKUP(B11,'Documents Recon'!$B:$B,1,FALSE) -> SM/Ororama/GC Gift Cheque Loan Application
B12: Rice Loan Application & Promissory Note | C12: Branch Operations | D12: =VLOOKUP(B12,'Documents Recon'!$B:$B,1,FALSE) -> Rice Loan Application & Promissory Note
B13: Fuel & Lube Credit Line Application | C13: Branch Operations | D13: =VLOOKUP(B13,'Documents Recon'!$B:$B,1,FALSE) -> Fuel & Lube Credit Line Application
B14: Loan Against Deposits Application | C14: Branch Operations | D14: =VLOOKUP(B14,'Documents Recon'!$B:$B,1,FALSE) -> Loan Against Deposits Application
... B21: Membership Information Sheet | C21: Branch Operations | D21: =VLOOKUP(B21,'Documents Recon'!$B:$B,1,FALSE) -> Membership Information Sheet
B22: Membership Application Form (CHMF) | C22: Branch Operations | D22: =VLOOKUP(B22,'Documents Recon'!$B:$B,1,FALSE) -> Membership Application Form (CHMF) | E22: Revisit why not included in the Documents
B23: HomeSECURE Application | C23: Branch Operations | D23: =VLOOKUP(B23,'Documents Recon'!$B:$B,1,FALSE) -> HomeSECURE Application | E23: Revisit why not included in the Documents
B24: Principal Member's Application Form for KOOPamilya Plan | C24: Branch Operations | D24: =VLOOKUP(B24,'Documents Recon'!$B:$B,1,FALSE) -> Principal Member's Application Form for KOOPamilya Plan | E24: Revisit why not included in the Documents
B25: Request for Check Issuance | C25: Accounting Department | D25: =VLOOKUP(B25,'Documents Recon'!$B:$B,1,FALSE) -> Request for Check Issuance
B26: Cash Advance Slip | C26: Accounting Department | D26: =VLOOKUP(B26,'Documents Recon'!$B:$B,1,FALSE) -> Cash Advance Slip
B27: Receiving Report | C27: Accounting Department | D27: =VLOOKUP(B27,'Documents Recon'!$B:$B,1,FALSE) -> Receiving Report
B28: Liquidation Voucher | C28: Accounting Department | D28: =VLOOKUP(B28,'Documents Recon'!$B:$B,1,FALSE) -> Liquidation Voucher
B29: Requisition Slip | C29: Accounting Department | D29: =VLOOKUP(B29,'Documents Recon'!$B:$B,1,FALSE) -> Requisition Slip
B30: Request of Transfer | C30: Accounting Department | D30: =VLOOKUP(B30,'Documents Recon'!$B:$B,1,FALSE) -> Request of Transfer | E30: Revisit why not included in the Documents
B31: Application for Withdrawal of Membership | C31: Branch Operations | D31: =VLOOKUP(B31,'Documents Recon'!$B:$B,1,FALSE) -> Application for Withdrawal of Membership
B32: Applicant Evaluation | C32: Human Resource Department | D32: =VLOOKUP(B32,'Documents Recon'!$B:$B,1,FALSE) -> Applicant Evaluation
B33: Applicant Background Investigation Report | C33: Human Resource Department | D33: =VLOOKUP(B33,'Documents Recon'!$B:$B,1,FALSE) -> Applicant Background Investigation Report
B34: Applicant Essay | C34: Human Resource Department | D34: =VLOOKUP(B34,'Documents Recon'!$B:$B,1,FALSE) -> Applicant Essay
B35: Employee Information Form | C35: Human Resource Department | D35: =VLOOKUP(B35,'Documents Recon'!$B:$B,1,FALSE) -> Employee Information Form
B36: Applicant Final Evaluation Form (Non-Supervisory) | C36: Human Resource Department | D36: =VLOOKUP(B36,'Documents Recon'!$B:$B,1,FALSE) -> Applicant Final Evaluation Form (Non-Supervisory)
B37: Applicant Final Evaluation Form (Supervisory) | C37: Human Resource Department | D37: =VLOOKUP(B37,'Documents Recon'!$B:$B,1,FALSE) -> Applicant Final Evaluation Form (Supervisory) | E37: Revisit why not included in the Documents
B38: Apprenticeship Agreement | C38: Human Resource Department | D38: =VLOOKUP(B38,'Documents Recon'!$B:$B,1,FALSE) -> Apprenticeship Agreement
B39: Probationary Contract | C39: Human Resource Department | D39: =VLOOKUP(B39,'Documents Recon'!$B:$B,1,FALSE) -> Probationary Contract
B40: Regular Employment Contract | C40: Human Resource Department | D40: =VLOOKUP(B40,'Documents Recon'!$B:$B,1,FALSE) -> Regular Employment Contract
B41: Authority to Deduct | C41: Human Resource Department | D41: =VLOOKUP(B41,'Documents Recon'!$B:$B,1,FALSE) -> Authority to Deduct
B42: Leave Form | C42: Human Resource Department | D42: =VLOOKUP(B42,'Documents Recon'!$B:$B,1,FALSE) -> Leave Form | E42: Revisit why not included in the Documents
B43: Office pass | C43: Human Resource Department | D43: =VLOOKUP(B43,'Documents Recon'!$B:$B,1,FALSE) -> Office pass | E43: Revisit why not included in the Documents
B44: Overtime request form | C44: Human Resource Department | D44: =VLOOKUP(B44,'Documents Recon'!$B:$B,1,FALSE) -> Overtime request form | E44: Revisit why not included in the Documents
B45: Evaluation form for training | C45: Human Resource Department | D45: =VLOOKUP(B45,'Documents Recon'!$B:$B,1,FALSE) -> Evaluation form for training | E45: Revisit why not included in the Documents
B46: Training attendance | C46: Human Resource Department | D46: =VLOOKUP(B46,'Documents Recon'!$B:$B,1,FALSE) -> Training attendance | E46: Revisit why not included in the Documents
B47: 201 Employee files | C47: Human Resource Department | D47: =VLOOKUP(B47,'Documents Recon'!$B:$B,1,FALSE) -> 201 Employee files | E47: Revisit why not included in the Documents
B48: Service records | C48: Human Resource Department | D48: =VLOOKUP(B48,'Documents Recon'!$B:$B,1,FALSE) -> Service records | E48: Revisit why not included in the Documents
B49: PERFORMANCE EVALUATION FORM (PROBATIONARY - Non-Supervisory) | C49: Human Resource Department | D49: =VLOOKUP(B49,'Documents Recon'!$B:$B,1,FALSE) -> PERFORMANCE EVALUATION FORM (PROBATIONARY - Non-Supervisory) | E49: Revisit why not included in the Documents
B50: PERFORMANCE EVALUATION FORM (Full-Fledged/Promotion) | C50: Human Resource Department | D50: =VLOOKUP(B50,'Documents Recon'!$B:$B,1,FALSE) -> PERFORMANCE EVALUATION FORM (Full-Fledged/Promotion) | E50: Revisit why not included in the Documents
B51: PERFORMANCE EVALUATION FORM (Full-Fledged/Promotion – NON-SUPERVISORY) | C51: Human Resource Department | D51: =VLOOKUP(B51,'Documents Recon'!$B:$B,1,FALSE) -> PERFORMANCE EVALUATION FORM (Full-Fledged/Promotion – NON-SUPERVISORY) | E51: Revisit why not included in the Documents
B52: PERFORMANCE EVALUATION FORM (Full-Fledged/Promotion - SUPERVISORY | C52: Human Resource Department | D52: =VLOOKUP(B52,'Documents Recon'!$B:$B,1,FALSE) -> PERFORMANCE EVALUATION FORM (Full-Fledged/Promotion - SUPERVISORY | E52: Revisit why not included in the Documents
B53: PERFORMANCE EVALUATION FORM (Full-Fledged/Promotion) | C53: Human Resource Department | D53: =VLOOKUP(B53,'Documents Recon'!$B:$B,1,FALSE) -> PERFORMANCE EVALUATION FORM (Full-Fledged/Promotion) | E53: Revisit why not included in the Documents
... B57: ACCOMPLISHMENT FORM (FULL-FLEDGED) | C57: Human Resource Department | D57: =VLOOKUP(B57,'Documents Recon'!$B:$B,1,FALSE) -> ACCOMPLISHMENT FORM (FULL-FLEDGED) | E57: Revisit why not included in the Documents
B58: User Access Level, Rights and Privileges | C58: Information Technology Department | D58: =VLOOKUP(B58,'Documents Recon'!$B:$B,1,FALSE) -> User Access Level, Rights and Privileges
B59: Payroll Schedule | C59: Human Resource Department | D59: =VLOOKUP(B59,'Documents Recon'!$B:$B,1,FALSE) -> Payroll Schedule
B60: Payroll Masterlist | C60: Human Resource Department | D60: =VLOOKUP(B60,'Documents Recon'!$B:$B,1,FALSE) -> Payroll Masterlist
B61: Employee Information Sheet | C61: Human Resource Department | D61: =VLOOKUP(B61,'Documents Recon'!$B:$B,1,FALSE) -> Employee Information Sheet
B62: Client Master: Maintenance | C62: Branch Operations | D62: =VLOOKUP(B62,'Documents Recon'!$B:$B,1,FALSE) -> Client Master: Maintenance
